Workbook

Sheet OUTLET WISE  
A1: Outlet Wise Report APRIL 2023
A2: Outlet | B2: Outlet | C2: Booking | D2: Retail | E2: SBI & Other Banks | F2: In House | G2: Pending Login | H2: SBI Pending Login | I2: Pent% | J2: CF | K2: MSSF DISBURSED
A3: ALUVA | B3: ALVA | C3: =COUNTIF(Booking!#REF!,B3) -> #REF! | D3: =COUNTIF(RETAIL!#REF!,B3) -> #REF! | E3: =COUNTIFS(#REF!,+B3,#REF!,"=DISBURSED") -> #REF! | F3: =COUNTIFS(IH!#REF!,+B3,IH!#REF!,"=DISBURSED") -> #REF! | G3: =COUNTIFS(IH!#REF!,+B3,IH!#REF!,"=LOGIN")+COUNTIFS(IH!#REF!,+B3,IH!#REF!,"=APPROVED") -> #REF! | H3: =COUNTIFS(#REF!,+B3,#REF!,"=LOGIN")+COUNTIFS(#REF!,B3,#REF!,"=APPROVED") -> #REF! | I3: =(E3+F3)/D3 -> #REF! | J3: =COUNTIFS(RETAIL!#REF!,+B3,RETAIL!P:P,"=C/F") -> #REF! | K3: 2
A4: ANGAMALY | B4: ANGLY | C4: =COUNTIF(Booking!#REF!,B4) -> #REF! | D4: =COUNTIF(RETAIL!#REF!,B4) -> #REF! | E4: =COUNTIFS(#REF!,+B4,#REF!,"=DISBURSED") -> #REF! | F4: =COUNTIFS(IH!#REF!,+B4,IH!#REF!,"=DISBURSED") -> #REF! | G4: =COUNTIFS(IH!#REF!,+B4,IH!#REF!,"=LOGIN")+COUNTIFS(IH!#REF!,+B4,IH!#REF!,"=APPROVED") -> #REF! | H4: =COUNTIFS(#REF!,+B4,#REF!,"=LOGIN")+COUNTIFS(#REF!,B4,#REF!,"=APPROVED") -> #REF! | I4: =(E4+F4)/D4 -> #REF! | J4: =COUNTIFS(RETAIL!#REF!,+B4,RETAIL!P:P,"=C/F") -> #REF! | K4: 4
A5: CHAVAKKAD | B5: CHVKD | C5: =COUNTIF(Booking!#REF!,B5) -> #REF! | D5: =COUNTIF(RETAIL!#REF!,B5) -> #REF! | E5: =COUNTIFS(#REF!,+B5,#REF!,"=DISBURSED") -> #REF! | F5: =COUNTIFS(IH!#REF!,+B5,IH!#REF!,"=DISBURSED") -> #REF! | G5: =COUNTIFS(IH!#REF!,+B5,IH!#REF!,"=LOGIN")+COUNTIFS(IH!#REF!,+B5,IH!#REF!,"=APPROVED") -> #REF! | H5: =COUNTIFS(#REF!,+B5,#REF!,"=LOGIN")+COUNTIFS(#REF!,B5,#REF!,"=APPROVED") -> #REF! | I5: =(E5+F5)/D5 -> #REF! | J5: =COUNTIFS(RETAIL!#REF!,+B5,RETAIL!P:P,"=C/F") -> #REF! | K5: 3
A6: EDAPPALLY | B6: EDPLY | C6: =COUNTIF(Booking!#REF!,B6) -> #REF! | D6: =COUNTIF(RETAIL!#REF!,B6) -> #REF! | E6: =COUNTIFS(#REF!,+B6,#REF!,"=DISBURSED") -> #REF! | F6: =COUNTIFS(IH!#REF!,+B6,IH!#REF!,"=DISBURSED") -> #REF! | G6: =COUNTIFS(IH!#REF!,+B6,IH!#REF!,"=LOGIN")+COUNTIFS(IH!#REF!,+B6,IH!#REF!,"=APPROVED") -> #REF! | H6: =COUNTIFS(#REF!,+B6,#REF!,"=LOGIN")+COUNTIFS(#REF!,B6,#REF!,"=APPROVED") -> #REF! | I6: =(E6+F6)/D6 -> #REF! | J6: =COUNTIFS(RETAIL!#REF!,+B6,RETAIL!P:P,"=C/F") -> #REF! | K6: 4
A7: KADAVANTHRA | B7: KDVRA | C7: =COUNTIF(Booking!#REF!,B7) -> #REF! | D7: =COUNTIF(RETAIL!#REF!,B7) -> #REF! | E7: =COUNTIFS(#REF!,+B7,#REF!,"=DISBURSED") -> #REF! | F7: =COUNTIFS(IH!#REF!,+B7,IH!#REF!,"=DISBURSED") -> #REF! | G7: =COUNTIFS(IH!#REF!,+B7,IH!#REF!,"=LOGIN")+COUNTIFS(IH!#REF!,+B7,IH!#REF!,"=APPROVED") -> #REF! | H7: =COUNTIFS(#REF!,+B7,#REF!,"=LOGIN")+COUNTIFS(#REF!,B7,#REF!,"=APPROVED") -> #REF! | I7: =(E7+F7)/D7 -> #REF! | J7: =COUNTIFS(RETAIL!#REF!,+B7,RETAIL!P:P,"=C/F") -> #REF! | K7: 3
A8: KODUNGALLOOR | B8: KDLR | C8: =COUNTIF(Booking!#REF!,B8) -> #REF! | D8: =COUNTIF(RETAIL!#REF!,B8) -> #REF! | E8: =COUNTIFS(#REF!,+B8,#REF!,"=DISBURSED") -> #REF! | F8: =COUNTIFS(IH!#REF!,+B8,IH!#REF!,"=DISBURSED") -> #REF! | G8: =COUNTIFS(IH!#REF!,+B8,IH!#REF!,"=LOGIN")+COUNTIFS(IH!#REF!,+B8,IH!#REF!,"=APPROVED") -> #REF! | H8: =COUNTIFS(#REF!,+B8,#REF!,"=LOGIN")+COUNTIFS(#REF!,B8,#REF!,"=APPROVED") -> #REF! | I8: =(E8+F8)/D8 -> #REF! | J8: =COUNTIFS(RETAIL!#REF!,+B8,RETAIL!P:P,"=C/F") -> #REF! | K8: 1
A9: KAIPAMANGALAM | B9: KPLM | C9: =COUNTIF(Booking!#REF!,B9) -> #REF! | D9: =COUNTIF(RETAIL!#REF!,B9) -> #REF! | E9: =COUNTIFS(#REF!,+B9,#REF!,"=DISBURSED") -> #REF! | F9: =COUNTIFS(IH!#REF!,+B9,IH!#REF!,"=DISBURSED") -> #REF! | G9: =COUNTIFS(IH!#REF!,+B9,IH!#REF!,"=LOGIN")+COUNTIFS(IH!#REF!,+B9,IH!#REF!,"=APPROVED") -> #REF! | H9: =COUNTIFS(#REF!,+B9,#REF!,"=LOGIN")+COUNTIFS(#REF!,B9,#REF!,"=APPROVED") -> #REF! | I9: =(E9+F9)/D9 -> #REF! | J9: =COUNTIFS(RETAIL!#REF!,+B9,RETAIL!P:P,"=C/F") -> #REF! | K9: 5
A10: KOOTHATTUKULAM | B10: KTLM | C10: =COUNTIF(Booking!#REF!,B10) -> #REF! | D10: =COUNTIF(RETAIL!#REF!,B10) -> #REF! | E10: =COUNTIFS(#REF!,+B10,#REF!,"=DISBURSED") -> #REF! | F10: =COUNTIFS(IH!#REF!,+B10,IH!#REF!,"=DISBURSED") -> #REF! | G10: =COUNTIFS(IH!#REF!,+B10,IH!#REF!,"=LOGIN")+COUNTIFS(IH!#REF!,+B10,IH!#REF!,"=APPROVED") -> #REF! | H10: =COUNTIFS(#REF!,+B10,#REF!,"=LOGIN")+COUNTIFS(#REF!,B10,#REF!,"=APPROVED") -> #REF! | I10: =(E10+F10)/D10 -> #REF! | J10: =COUNTIFS(RETAIL!#REF!,+B10,RETAIL!P:P,"=C/F") -> #REF! | K10: 1
A11: KOLENCHERRY | B11: KLY | C11: =COUNTIF(Booking!#REF!,B11) -> #REF! | D11: =COUNTIF(RETAIL!#REF!,B11) -> #REF! | E11: =COUNTIFS(#REF!,+B11,#REF!,"=DISBURSED") -> #REF! | F11: =COUNTIFS(IH!#REF!,+B11,IH!#REF!,"=DISBURSED") -> #REF! | G11: =COUNTIFS(IH!#REF!,+B11,IH!#REF!,"=LOGIN")+COUNTIFS(IH!#REF!,+B11,IH!#REF!,"=APPROVED") -> #REF! | H11: =COUNTIFS(#REF!,+B11,#REF!,"=LOGIN")+COUNTIFS(#REF!,B11,#REF!,"=APPROVED") -> #REF! | I11: =(E11+F11)/D11 -> #REF! | J11: =COUNTIFS(RETAIL!#REF!,+B11,RETAIL!P:P,"=C/F") -> #REF! | K11: 2
A12: PERUMBAVOOR | B12: PMBR | C12: =COUNTIF(Booking!#REF!,B12) -> #REF! | D12: =COUNTIF(RETAIL!#REF!,B12) -> #REF! | E12: =COUNTIFS(#REF!,+B12,#REF!,"=DISBURSED") -> #REF! | F12: =COUNTIFS(IH!#REF!,+B12,IH!#REF!,"=DISBURSED") -> #REF! | G12: =COUNTIFS(IH!#REF!,+B12,IH!#REF!,"=LOGIN")+COUNTIFS(IH!#REF!,+B12,IH!#REF!,"=APPROVED") -> #REF! | H12: =COUNTIFS(#REF!,+B12,#REF!,"=LOGIN")+COUNTIFS(#REF!,B12,#REF!,"=APPROVED") -> #REF! | I12: =(E12+F12)/D12 -> #REF! | J12: =COUNTIFS(RETAIL!#REF!,+B12,RETAIL!P:P,"=C/F") -> #REF! | K12: 4
A13: PALAKKAD | B13: PLKD | C13: =COUNTIF(Booking!#REF!,B13) -> #REF! | D13: =COUNTIF(RETAIL!#REF!,B13) -> #REF! | E13: =COUNTIFS(#REF!,+B13,#REF!,"=DISBURSED") -> #REF! | F13: =COUNTIFS(IH!#REF!,+B13,IH!#REF!,"=DISBURSED") -> #REF! | G13: =COUNTIFS(IH!#REF!,+B13,IH!#REF!,"=LOGIN")+COUNTIFS(IH!#REF!,+B13,IH!#REF!,"=APPROVED") -> #REF! | H13: =COUNTIFS(#REF!,+B13,#REF!,"=LOGIN")+COUNTIFS(#REF!,B13,#REF!,"=APPROVED") -> #REF! | I13: =(E13+F13)/D13 -> #REF! | J13: =COUNTIFS(RETAIL!#REF!,+B13,RETAIL!P:P,"=C/F") -> #REF! | K13: 1
A14: FORTKOCHI | B14: FORTKOCHI | C14: =COUNTIF(Booking!#REF!,B14) -> #REF! | D14: =COUNTIF(RETAIL!#REF!,B14) -> #REF! | E14: =COUNTIFS(#REF!,+B14,#REF!,"=DISBURSED") -> #REF! | F14: =COUNTIFS(IH!#REF!,+B14,IH!#REF!,"=DISBURSED") -> #REF! | G14: =COUNTIFS(IH!#REF!,+B14,IH!#REF!,"=LOGIN")+COUNTIFS(IH!#REF!,+B14,IH!#REF!,"=APPROVED") -> #REF! | H14: =COUNTIFS(#REF!,+B14,#REF!,"=LOGIN")+COUNTIFS(#REF!,B14,#REF!,"=APPROVED") -> #REF! | I14: =(E14+F14)/D14 -> #REF! | J14: =COUNTIFS(RETAIL!#REF!,+B14,RETAIL!P:P,"=C/F") -> #REF! | K14: 1
... A19: NEXA | B19: NEXA | C19: =COUNTIF(Booking!#REF!,B19) -> #REF! | D19: =COUNTIF(RETAIL!#REF!,B19) -> #REF! | E19: =COUNTIFS(#REF!,+B19,#REF!,"=DISBURSED") -> #REF! | F19: =COUNTIFS(IH!#REF!,+B19,IH!#REF!,"=DISBURSED") -> #REF! | G19: =COUNTIFS(IH!#REF!,+B19,IH!#REF!,"=LOGIN")+COUNTIFS(IH!#REF!,+B19,IH!#REF!,"=APPROVED") -> #REF! | H19: =COUNTIFS(#REF!,+B19,#REF!,"=LOGIN")+COUNTIFS(#REF!,B19,#REF!,"=APPROVED") -> #REF! | I19: =(E19+F19)/D19 -> #REF! | J19: =COUNTIFS(RETAIL!#REF!,+B19,RETAIL!P:P,"=C/F") -> #REF! | K19: 3
A20: Total | C20: =SUM(C3:C19) -> #REF! | D20: =SUM(D3:D19) -> #REF! | E20: =SUM(E3:E19) -> #REF! | F20: =SUM(F3:F19) -> #REF! | G20: =SUM(G3:G19) -> #REF! | H20: =SUM(H3:H19) -> #REF! | I20: =(E20+F20)/D20 -> #REF! | J20: =SUM(J3:J19) -> #REF! | K20: 56

Sheet DSE
B1: DSE PERFORMANCE - Mar-26 | E1: ARENA | H1: NEXA | K1: TOTAL
B2: DSE | C2: SRM | D2: OUTLET | E2: RETAIL | F2: IH | G2: PENT% | H2: RETAIL | I2: IH | J2: PENT% | K2: RETAIL | L2: IH | M2: PENT%
B3: SALIH M S | C3: JAYESH | D3: ALUVA | E3: =COUNTIFS(RETAIL!L:L,B3) -> 0 | F3: =COUNTIFS(IH!K:K,B3,IH!S:S,"DISBURSED") -> 0 | G3: =IFERROR((F3/E3),0) -> 0 | H3: =COUNTIFS([1]RETAIL!$L:$L,B3) -> 0 | I3: =COUNTIFS([1]IH!$S:$S,"DISBURSED",[1]IH!$K:$K,B3) -> 0 | J3: =IFERROR((I3/H3),0) -> 0 | K3: =E3+H3 -> 0 | L3: =F3+I3 -> 0 | M3: =IFERROR((L3/K3),0) -> 0
B4: PRAVEEN KUMAR B | C4: ELDHO A JACOB | D4: ANGAMALY | E4: =COUNTIFS(RETAIL!L:L,B4) -> 2 | F4: =COUNTIFS(IH!K:K,B4,IH!S:S,"DISBURSED") -> 1 | G4: =IFERROR((F4/E4),0) -> 0.5 | H4: =COUNTIFS([1]RETAIL!$L:$L,B4) -> 1 | I4: =COUNTIFS([1]IH!$S:$S,"DISBURSED",[1]IH!$K:$K,B4) -> 1 | J4: =IFERROR((I4/H4),0) -> 1 | K4: =E4+H4 -> 3 | L4: =F4+I4 -> 2 | M4: =IFERROR((L4/K4),0) -> 0.66666667
B5: SREEJITH P P | C5: ELDHO A JACOB | D5: ANGAMALY | E5: =COUNTIFS(RETAIL!L:L,B5) -> 0 | F5: =COUNTIFS(IH!K:K,B5,IH!S:S,"DISBURSED") -> 0 | G5: =IFERROR((F5/E5),0) -> 0 | H5: =COUNTIFS([1]RETAIL!$L:$L,B5) -> 0 | I5: =COUNTIFS([1]IH!$S:$S,"DISBURSED",[1]IH!$K:$K,B5) -> 0 | J5: =IFERROR((I5/H5),0) -> 0 | K5: =E5+H5 -> 0 | L5: =F5+I5 -> 0 | M5: =IFERROR((L5/K5),0) -> 0
B6: AMEENSHAH | C6: BHAGIESH | D6: CHAVAKKAD | E6: =COUNTIFS(RETAIL!L:L,B6) -> 0 | F6: =COUNTIFS(IH!K:K,B6,IH!S:S,"DISBURSED") -> 0 | G6: =IFERROR((F6/E6),0) -> 0 | H6: =COUNTIFS([1]RETAIL!$L:$L,B6) -> 0 | I6: =COUNTIFS([1]IH!$S:$S,"DISBURSED",[1]IH!$K:$K,B6) -> 0 | J6: =IFERROR((I6/H6),0) -> 0 | K6: =E6+H6 -> 0 | L6: =F6+I6 -> 0 | M6: =IFERROR((L6/K6),0) -> 0
B7: AKHIL M B | C7: BHAGIESH | D7: CHAVAKKAD | E7: =COUNTIFS(RETAIL!L:L,B7) -> 0 | F7: =COUNTIFS(IH!K:K,B7,IH!S:S,"DISBURSED") -> 0 | G7: =IFERROR((F7/E7),0) -> 0 | H7: =COUNTIFS([1]RETAIL!$L:$L,B7) -> 0 | I7: =COUNTIFS([1]IH!$S:$S,"DISBURSED",[1]IH!$K:$K,B7) -> 0 | J7: =IFERROR((I7/H7),0) -> 0 | K7: =E7+H7 -> 0 | L7: =F7+I7 -> 0 | M7: =IFERROR((L7/K7),0) -> 0
B8: JITHIN CHANDRAN K C | C8: BHAGIESH | D8: CHAVAKKAD | E8: =COUNTIFS(RETAIL!L:L,B8) -> 1 | F8: =COUNTIFS(IH!K:K,B8,IH!S:S,"DISBURSED") -> 1 | G8: =IFERROR((F8/E8),0) -> 1 | H8: =COUNTIFS([1]RETAIL!$L:$L,B8) -> 0 | I8: =COUNTIFS([1]IH!$S:$S,"DISBURSED",[1]IH!$K:$K,B8) -> 0 | J8: =IFERROR((I8/H8),0) -> 0 | K8: =E8+H8 -> 1 | L8: =F8+I8 -> 1 | M8: =IFERROR((L8/K8),0) -> 1
B9: JOHNSON C D | C9: BHAGIESH | D9: CHAVAKKAD | E9: =COUNTIFS(RETAIL!L:L,B9) -> 0 | F9: =COUNTIFS(IH!K:K,B9,IH!S:S,"DISBURSED") -> 0 | G9: =IFERROR((F9/E9),0) -> 0 | H9: =COUNTIFS([1]RETAIL!$L:$L,B9) -> 0 | I9: =COUNTIFS([1]IH!$S:$S,"DISBURSED",[1]IH!$K:$K,B9) -> 0 | J9: =IFERROR((I9/H9),0) -> 0 | K9: =E9+H9 -> 0 | L9: =F9+I9 -> 0 | M9: =IFERROR((L9/K9),0) -> 0
B10: MIDHUL V M | C10: BHAGIESH | D10: CHAVAKKAD | E10: =COUNTIFS(RETAIL!L:L,B10) -> 0 | F10: =COUNTIFS(IH!K:K,B10,IH!S:S,"DISBURSED") -> 0 | G10: =IFERROR((F10/E10),0) -> 0 | H10: =COUNTIFS([1]RETAIL!$L:$L,B10) -> 1 | I10: =COUNTIFS([1]IH!$S:$S,"DISBURSED",[1]IH!$K:$K,B10) -> 0 | J10: =IFERROR((I10/H10),0) -> 0 | K10: =E10+H10 -> 1 | L10: =F10+I10 -> 0 | M10: =IFERROR((L10/K10),0) -> 0
B11: RISHAD K S | C11: BHAGIESH | D11: CHAVAKKAD | E11: =COUNTIFS(RETAIL!L:L,B11) -> 5 | F11: =COUNTIFS(IH!K:K,B11,IH!S:S,"DISBURSED") -> 4 | G11: =IFERROR((F11/E11),0) -> 0.8 | H11: =COUNTIFS([1]RETAIL!$L:$L,B11) -> 3 | I11: =COUNTIFS([1]IH!$S:$S,"DISBURSED",[1]IH!$K:$K,B11) -> 2 | J11: =IFERROR((I11/H11),0) -> 0.66666667 | K11: =E11+H11 -> 8 | L11: =F11+I11 -> 6 | M11: =IFERROR((L11/K11),0) -> 0.75
B12: ABHILASH P C | C12: ABHILASH K P | D12: EDAPPALLY | E12: =COUNTIFS(RETAIL!L:L,B12) -> 10 | F12: =COUNTIFS(IH!K:K,B12,IH!S:S,"DISBURSED") -> 2 | G12: =IFERROR((F12/E12),0) -> 0.2 | H12: =COUNTIFS([1]RETAIL!$L:$L,B12) -> 0 | I12: =COUNTIFS([1]IH!$S:$S,"DISBURSED",[1]IH!$K:$K,B12) -> 0 | J12: =IFERROR((I12/H12),0) -> 0 | K12: =E12+H12 -> 10 | L12: =F12+I12 -> 2 | M12: =IFERROR((L12/K12),0) -> 0.2
B13: MANOJ C S | C13: ABHILASH K P | D13: EDAPPALLY | E13: =COUNTIFS(RETAIL!L:L,B13) -> 3 | F13: =COUNTIFS(IH!K:K,B13,IH!S:S,"DISBURSED") -> 1 | G13: =IFERROR((F13/E13),0) -> 0.33333333 | H13: =COUNTIFS([1]RETAIL!$L:$L,B13) -> 0 | I13: =COUNTIFS([1]IH!$S:$S,"DISBURSED",[1]IH!$K:$K,B13) -> 0 | J13: =IFERROR((I13/H13),0) -> 0 | K13: =E13+H13 -> 3 | L13: =F13+I13 -> 1 | M13: =IFERROR((L13/K13),0) -> 0.33333333
B14: LANEESH A S | C14: MANU SASI | D14: EDAPPALLY | E14: =COUNTIFS(RETAIL!L:L,B14) -> 7 | F14: =COUNTIFS(IH!K:K,B14,IH!S:S,"DISBURSED") -> 6 | G14: =IFERROR((F14/E14),0) -> 0.85714286 | H14: =COUNTIFS([1]RETAIL!$L:$L,B14) -> 3 | I14: =COUNTIFS([1]IH!$S:$S,"DISBURSED",[1]IH!$K:$K,B14) -> 2 | J14: =IFERROR((I14/H14),0) -> 0.66666667 | K14: =E14+H14 -> 10 | L14: =F14+I14 -> 8 | M14: =IFERROR((L14/K14),0) -> 0.8
... B173: EBIN | C173: GEORGE KUTTAN JOY | D173: NEXA COCHIN | E173: =COUNTIFS(RETAIL!L:L,B173) -> 0 | F173: =COUNTIFS(IH!K:K,B173,IH!S:S,"DISBURSED") -> 0 | G173: =IFERROR((F173/E173),0) -> 0 | H173: =COUNTIFS([1]RETAIL!$L:$L,B173) -> 0 | I173: =COUNTIFS([1]IH!$S:$S,"DISBURSED",[1]IH!$K:$K,B173) -> 0 | J173: =IFERROR((I173/H173),0) -> 0 | K173: =E173+H173 -> 0 | L173: =F173+I173 -> 0 | M173: =IFERROR((L173/K173),0) -> 0
B174: TOTAL | E174: =SUM(E3:E173) -> 185 | F174: =SUM(F3:F173) -> 109 | G174: =IFERROR((F174/E174),0) -> 0.58918919 | H174: =SUM(H3:H173) -> 125 | I174: =SUM(I3:I173) -> 88 | J174: =IFERROR(I174/H174,0) -> 0.704 | K174: =E174+H174 -> 310 | L174: =F174+I174 -> 197 | M174: =IFERROR(L174/K174,0) -> 0.63548387

Sheet TL
B1: SRM WISE PERFORMANCE - Mar-26 | H1: NEXA | K1: TOTAL
B2: SRM | C2: OUTLET | D2: RETAIL | E2: IH | F2: PENT% | G2: - | H2: RETAIL | I2: IH | J2: PENT% | K2: RETAIL | L2: IH | M2: PENT%
B3: JAYESH | C3: ALUVA | D3: =COUNTIFS(RETAIL!M:M,+B3) -> 1 | E3: =COUNTIFS(IH!L:L,B3,IH!S:S,"DISBURSED") -> 0 | F3: =IFERROR(E3/D3,0) -> 0 | H3: =COUNTIFS([1]RETAIL!$M:$M,B3) -> 0 | I3: =COUNTIFS([1]IH!$S:$S,"DISBURSED",[1]IH!$L:$L,B3) -> 0 | J3: =IFERROR(I3/H3,0) -> 0 | K3: =D3+H3 -> 1 | L3: =E3+I3 -> 0 | M3: =IFERROR(L3/K3,0) -> 0
B4: ELDHO A JACOB | C4: ANGAMALY | D4: =COUNTIFS(RETAIL!M:M,+B4) -> 5 | E4: =COUNTIFS(IH!L:L,B4,IH!S:S,"DISBURSED") -> 4 | F4: =IFERROR(E4/D4,0) -> 0.8 | H4: =COUNTIFS([1]RETAIL!$M:$M,B4) -> 2 | I4: =COUNTIFS([1]IH!$S:$S,"DISBURSED",[1]IH!$L:$L,B4) -> 2 | J4: =IFERROR(I4/H4,0) -> 1 | K4: =D4+H4 -> 7 | L4: =E4+I4 -> 6 | M4: =IFERROR(L4/K4,0) -> 0.85714286
B5: BHAGIESH | C5: CHAVAKKAD | D5: =COUNTIFS(RETAIL!M:M,+B5) -> 9 | E5: =COUNTIFS(IH!L:L,B5,IH!S:S,"DISBURSED") -> 8 | F5: =IFERROR(E5/D5,0) -> 0.88888889 | H5: =COUNTIFS([1]RETAIL!$M:$M,B5) -> 5 | I5: =COUNTIFS([1]IH!$S:$S,"DISBURSED",[1]IH!$L:$L,B5) -> 3 | J5: =IFERROR(I5/H5,0) -> 0.6 | K5: =D5+H5 -> 14 | L5: =E5+I5 -> 11 | M5: =IFERROR(L5/K5,0) -> 0.78571429
B6: ABHILASH K P | C6: EDAPPALLY | D6: =COUNTIFS(RETAIL!M:M,+B6) -> 13 | E6: =COUNTIFS(IH!L:L,B6,IH!S:S,"DISBURSED") -> 3 | F6: =IFERROR(E6/D6,0) -> 0.23076923 | H6: =COUNTIFS([1]RETAIL!$M:$M,B6) -> 0 | I6: =COUNTIFS([1]IH!$S:$S,"DISBURSED",[1]IH!$L:$L,B6) -> 0 | J6: =IFERROR(I6/H6,0) -> 0 | K6: =D6+H6 -> 13 | L6: =E6+I6 -> 3 | M6: =IFERROR(L6/K6,0) -> 0.23076923
B7: MANU SASI | C7: EDAPPALLY | D7: =COUNTIFS(RETAIL!M:M,+B7) -> 11 | E7: =COUNTIFS(IH!L:L,B7,IH!S:S,"DISBURSED") -> 8 | F7: =IFERROR(E7/D7,0) -> 0.72727273 | H7: =COUNTIFS([1]RETAIL!$M:$M,B7) -> 4 | I7: =COUNTIFS([1]IH!$S:$S,"DISBURSED",[1]IH!$L:$L,B7) -> 2 | J7: =IFERROR(I7/H7,0) -> 0.5 | K7: =D7+H7 -> 15 | L7: =E7+I7 -> 10 | M7: =IFERROR(L7/K7,0) -> 0.66666667
B8: NOUFAL T A | C8: EDAPPALLY | D8: =COUNTIFS(RETAIL!M:M,+B8) -> 7 | E8: =COUNTIFS(IH!L:L,B8,IH!S:S,"DISBURSED") -> 5 | F8: =IFERROR(E8/D8,0) -> 0.71428571 | H8: =COUNTIFS([1]RETAIL!$M:$M,B8) -> 2 | I8: =COUNTIFS([1]IH!$S:$S,"DISBURSED",[1]IH!$L:$L,B8) -> 2 | J8: =IFERROR(I8/H8,0) -> 1 | K8: =D8+H8 -> 9 | L8: =E8+I8 -> 7 | M8: =IFERROR(L8/K8,0) -> 0.77777778
B9: SHEMEER A K | C9: EDAPPALLY | D9: =COUNTIFS(RETAIL!M:M,+B9) -> 4 | E9: =COUNTIFS(IH!L:L,B9,IH!S:S,"DISBURSED") -> 4 | F9: =IFERROR(E9/D9,0) -> 1 | H9: =COUNTIFS([1]RETAIL!$M:$M,B9) -> 1 | I9: =COUNTIFS([1]IH!$S:$S,"DISBURSED",[1]IH!$L:$L,B9) -> 1 | J9: =IFERROR(I9/H9,0) -> 1 | K9: =D9+H9 -> 5 | L9: =E9+I9 -> 5 | M9: =IFERROR(L9/K9,0) -> 1
B10: REJIM GEORGE | C10: FORTKOCHI | D10: =COUNTIFS(RETAIL!M:M,+B10) -> 4 | E10: =COUNTIFS(IH!L:L,B10,IH!S:S,"DISBURSED") -> 3 | F10: =IFERROR(E10/D10,0) -> 0.75 | H10: =COUNTIFS([1]RETAIL!$M:$M,B10) -> 1 | I10: =COUNTIFS([1]IH!$S:$S,"DISBURSED",[1]IH!$L:$L,B10) -> 1 | J10: =IFERROR(I10/H10,0) -> 1 | K10: =D10+H10 -> 5 | L10: =E10+I10 -> 4 | M10: =IFERROR(L10/K10,0) -> 0.8
B11: RATISH K R | C11: KADAVANTHRA | D11: =COUNTIFS(RETAIL!M:M,+B11) -> 8 | E11: =COUNTIFS(IH!L:L,B11,IH!S:S,"DISBURSED") -> 5 | F11: =IFERROR(E11/D11,0) -> 0.625 | H11: =COUNTIFS([1]RETAIL!$M:$M,B11) -> 3 | I11: =COUNTIFS([1]IH!$S:$S,"DISBURSED",[1]IH!$L:$L,B11) -> 3 | J11: =IFERROR(I11/H11,0) -> 1 | K11: =D11+H11 -> 11 | L11: =E11+I11 -> 8 | M11: =IFERROR(L11/K11,0) -> 0.72727273
B12: SMITHIN P S | C12: KAIPAMANGALAM | D12: =COUNTIFS(RETAIL!M:M,+B12) -> 5 | E12: =COUNTIFS(IH!L:L,B12,IH!S:S,"DISBURSED") -> 1 | F12: =IFERROR(E12/D12,0) -> 0.2 | H12: =COUNTIFS([1]RETAIL!$M:$M,B12) -> 1 | I12: =COUNTIFS([1]IH!$S:$S,"DISBURSED",[1]IH!$L:$L,B12) -> 1 | J12: =IFERROR(I12/H12,0) -> 1 | K12: =D12+H12 -> 6 | L12: =E12+I12 -> 2 | M12: =IFERROR(L12/K12,0) -> 0.33333333
B13: VIBIN I B | C13: KAIPAMANGALAM | D13: =COUNTIFS(RETAIL!M:M,+B13) -> 5 | E13: =COUNTIFS(IH!L:L,B13,IH!S:S,"DISBURSED") -> 5 | F13: =IFERROR(E13/D13,0) -> 1 | H13: =COUNTIFS([1]RETAIL!$M:$M,B13) -> 5 | I13: =COUNTIFS([1]IH!$S:$S,"DISBURSED",[1]IH!$L:$L,B13) -> 5 | J13: =IFERROR(I13/H13,0) -> 1 | K13: =D13+H13 -> 10 | L13: =E13+I13 -> 10 | M13: =IFERROR(L13/K13,0) -> 1
B14: KASI VISWANATH | C14: KAIPAMANGALAM | D14: =COUNTIFS(RETAIL!M:M,+B14) -> 9 | E14: =COUNTIFS(IH!L:L,B14,IH!S:S,"DISBURSED") -> 5 | F14: =IFERROR(E14/D14,0) -> 0.55555556 | H14: =COUNTIFS([1]RETAIL!$M:$M,B14) -> 0 | I14: =COUNTIFS([1]IH!$S:$S,"DISBURSED",[1]IH!$L:$L,B14) -> 0 | J14: =IFERROR(I14/H14,0) -> 0 | K14: =D14+H14 -> 9 | L14: =E14+I14 -> 5 | M14: =IFERROR(L14/K14,0) -> 0.55555556
... B32: SACHIN | C32: KODUNGALLUR | D32: =COUNTIFS(RETAIL!M:M,+B32) -> 5 | E32: =COUNTIFS(IH!L:L,B32,IH!S:S,"DISBURSED") -> 3 | F32: =IFERROR(E32/D32,0) -> 0.6 | H32: =COUNTIFS([1]RETAIL!$M:$M,B32) -> 4 | I32: =COUNTIFS([1]IH!$S:$S,"DISBURSED",[1]IH!$L:$L,B32) -> 3 | J32: =IFERROR(I32/H32,0) -> 0.75 | K32: =D32+H32 -> 9 | L32: =E32+I32 -> 6 | M32: =IFERROR(L32/K32,0) -> 0.66666667
C33: TOTAL | D33: =SUM(D3:D32) -> 182 | E33: =SUM(E3:E32) -> 109 | F33: =IFERROR(E33/D33,0) -> 0.5989011 | H33: =SUM(H3:H32) -> 116 | I33: =SUM(I3:I32) -> 85 | J33: =IFERROR(I33/H33,0) -> 0.73275862 | K33: =SUM(K4:K32) -> 297 | L33: =SUM(L3:L32) -> 194 | M33: =IFERROR(L33/K33,0) -> 0.65319865

Sheet Outlet
B1: Arena Outletwise Performance - Mar-26 | L1: Finance Cordinator wise Performance - Mar-26
B2: Outlet Location | C2: Bking | D2: Retail | E2: IH | F2: Login | G2: Pent% | H2: Mssf Login | I2: Mssf Disb | J2: Cordinator | M2: ARENA | P2: NEXA | S2: TOTAL
B3: ALUVA | C3: =COUNTIFS(Booking!C:C,B3) -> 5 | D3: =COUNTIFS(RETAIL!N:N,B3) -> 1 | E3: =COUNTIFS(IH!M:M,B3,IH!S:S,"DISBURSED") -> 0 | F3: =COUNTIFS(IH!M:M,B3,IH!S:S,"LOGIN") -> 0 | G3: =IFERROR((E3/D3),0) -> 0 | H3: =COUNTIFS(IH!M:M,B3,IH!T:T,"MSSF LOGIN") -> 0 | I3: =COUNTIFS(IH!M:M,B3,IH!T:T,"MSSF DISBURSED") -> 0 | J3: SALMAN | L3: COORDINATOR | M3: RETAIL | N3: IH Fin | O3: PENT% | P3: RETAIL | Q3: IH Fin | R3: PENT% | S3: RETAIL | T3: IH Fin | U3: PENT%
B4: ANGAMALY | C4: =COUNTIFS(Booking!C:C,B4) -> 17 | D4: =COUNTIFS(RETAIL!N:N,B4) -> 5 | E4: =COUNTIFS(IH!M:M,B4,IH!S:S,"DISBURSED") -> 4 | F4: =COUNTIFS(IH!M:M,B4,IH!S:S,"LOGIN") -> 3 | G4: =IFERROR((E4/D4),0) -> 0.8 | H4: =COUNTIFS(IH!M:M,B4,IH!T:T,"MSSF LOGIN") -> 5 | I4: =COUNTIFS(IH!M:M,B4,IH!T:T,"MSSF DISBURSED") -> 1 | J4: SALMAN | L4: SIVAPRASAD | M4: =COUNTIFS(RETAIL!X:X,L4) -> 48 | N4: =COUNTIFS(IH!S:S,"Disbursed",IH!U:U,L4) -> 28 | O4: =IFERROR((N4/M4),0) -> 0.58333333 | P4: =COUNTIFS([1]RETAIL!$X:$X,L4) -> 10 | Q4: =COUNTIFS([1]IH!$S:$S,"DISBURSED",[1]IH!$U:$U,L4) -> 7 | R4: =IFERROR((Q4/P4),0) -> 0.7 | S4: =M4+P4 -> 58 | T4: =N4+Q4 -> 35 | U4: =IFERROR((T4/S4),0) -> 0.60344828
B5: CHAVAKKAD | C5: =COUNTIFS(Booking!C:C,B5) -> 31 | D5: =COUNTIFS(RETAIL!N:N,B5) -> 9 | E5: =COUNTIFS(IH!M:M,B5,IH!S:S,"DISBURSED") -> 8 | F5: =COUNTIFS(IH!M:M,B5,IH!S:S,"LOGIN") -> 0 | G5: =IFERROR((E5/D5),0) -> 0.88888889 | H5: =COUNTIFS(IH!M:M,B5,IH!T:T,"MSSF LOGIN") -> 0 | I5: =COUNTIFS(IH!M:M,B5,IH!T:T,"MSSF DISBURSED") -> 4 | J5: SINTO | L5: AMAL | M5: =COUNTIFS(RETAIL!X:X,L5) -> 34 | N5: =COUNTIFS(IH!S:S,"Disbursed",IH!U:U,L5) -> 19 | O5: =IFERROR((N5/M5),0) -> 0.55882353 | P5: =COUNTIFS([1]RETAIL!$X:$X,L5) -> 5 | Q5: =COUNTIFS([1]IH!$S:$S,"DISBURSED",[1]IH!$U:$U,L5) -> 4 | R5: =IFERROR((Q5/P5),0) -> 0.8 | S5: =M5+P5 -> 39 | T5: =N5+Q5 -> 23 | U5: =IFERROR((T5/S5),0) -> 0.58974359
B6: EDAPPALLY | C6: =COUNTIFS(Booking!C:C,B6) -> 57 | D6: =COUNTIFS(RETAIL!N:N,B6) -> 35 | E6: =COUNTIFS(IH!M:M,B6,IH!S:S,"DISBURSED") -> 20 | F6: =COUNTIFS(IH!M:M,B6,IH!S:S,"LOGIN") -> 11 | G6: =IFERROR((E6/D6),0) -> 0.57142857 | H6: =COUNTIFS(IH!M:M,B6,IH!T:T,"MSSF LOGIN") -> 19 | I6: =COUNTIFS(IH!M:M,B6,IH!T:T,"MSSF DISBURSED") -> 11 | J6: SIVAPRASAD | L6: SALMAN | M6: =COUNTIFS(RETAIL!X:X,L6) -> 26 | N6: =COUNTIFS(IH!S:S,"Disbursed",IH!U:U,L6) -> 18 | O6: =IFERROR((N6/M6),0) -> 0.69230769 | P6: =COUNTIFS([1]RETAIL!$X:$X,L6) -> 9 | Q6: =COUNTIFS([1]IH!$S:$S,"DISBURSED",[1]IH!$U:$U,L6) -> 8 | R6: =IFERROR((Q6/P6),0) -> 0.88888889 | S6: =M6+P6 -> 35 | T6: =N6+Q6 -> 26 | U6: =IFERROR((T6/S6),0) -> 0.74285714
B7: FORTKOCHI | C7: =COUNTIFS(Booking!C:C,B7) -> 20 | D7: =COUNTIFS(RETAIL!N:N,B7) -> 4 | E7: =COUNTIFS(IH!M:M,B7,IH!S:S,"DISBURSED") -> 3 | F7: =COUNTIFS(IH!M:M,B7,IH!S:S,"LOGIN") -> 3 | G7: =IFERROR((E7/D7),0) -> 0.75 | H7: =COUNTIFS(IH!M:M,B7,IH!T:T,"MSSF LOGIN") -> 4 | I7: =COUNTIFS(IH!M:M,B7,IH!T:T,"MSSF DISBURSED") -> 2 | J7: SIVAPRASAD | L7: SINTO | M7: =COUNTIFS(RETAIL!X:X,L7) -> 34 | N7: =COUNTIFS(IH!S:S,"Disbursed",IH!U:U,L7) -> 20 | O7: =IFERROR((N7/M7),0) -> 0.58823529 | P7: =COUNTIFS([1]RETAIL!$X:$X,L7) -> 9 | Q7: =COUNTIFS([1]IH!$S:$S,"DISBURSED",[1]IH!$U:$U,L7) -> 6 | R7: =IFERROR((Q7/P7),0) -> 0.66666667 | S7: =M7+P7 -> 43 | T7: =N7+Q7 -> 26 | U7: =IFERROR((T7/S7),0) -> 0.60465116
B8: KADAVANTHRA | C8: =COUNTIFS(Booking!C:C,B8) -> 19 | D8: =COUNTIFS(RETAIL!N:N,B8) -> 8 | E8: =COUNTIFS(IH!M:M,B8,IH!S:S,"DISBURSED") -> 5 | F8: =COUNTIFS(IH!M:M,B8,IH!S:S,"LOGIN") -> 2 | G8: =IFERROR((E8/D8),0) -> 0.625 | H8: =COUNTIFS(IH!M:M,B8,IH!T:T,"MSSF LOGIN") -> 3 | I8: =COUNTIFS(IH!M:M,B8,IH!T:T,"MSSF DISBURSED") -> 4 | J8: SALMAN | L8: JINEESH | M8: =COUNTIFS(RETAIL!X:X,L8) -> 33 | N8: =COUNTIFS(IH!S:S,"Disbursed",IH!U:U,L8) -> 20 | O8: =IFERROR((N8/M8),0) -> 0.60606061 | P8: =COUNTIFS([1]RETAIL!$X:$X,L8) -> 22 | Q8: =COUNTIFS([1]IH!$S:$S,"DISBURSED",[1]IH!$U:$U,L8) -> 18 | R8: =IFERROR((Q8/P8),0) -> 0.81818182 | S8: =M8+P8 -> 55 | T8: =N8+Q8 -> 38 | U8: =IFERROR((T8/S8),0) -> 0.69090909
B9: KAIPAMANGALAM | C9: =COUNTIFS(Booking!C:C,B9) -> 33 | D9: =COUNTIFS(RETAIL!N:N,B9) -> 19 | E9: =COUNTIFS(IH!M:M,B9,IH!S:S,"DISBURSED") -> 11 | F9: =COUNTIFS(IH!M:M,B9,IH!S:S,"LOGIN") -> 0 | G9: =IFERROR((E9/D9),0) -> 0.57894737 | H9: =COUNTIFS(IH!M:M,B9,IH!T:T,"MSSF LOGIN") -> 1 | I9: =COUNTIFS(IH!M:M,B9,IH!T:T,"MSSF DISBURSED") -> 9 | J9: JINEESH | L9: WILSON | M9: =COUNTIFS(RETAIL!X:X,L9) -> 10 | N9: =COUNTIFS(IH!S:S,"Disbursed",IH!U:U,L9) -> 4 | O9: =IFERROR((N9/M9),0) -> 0.4 | P9: =COUNTIFS([1]RETAIL!$X:$X,L9) -> 70 | Q9: =COUNTIFS([1]IH!$S:$S,"DISBURSED",[1]IH!$U:$U,L9) -> 45 | R9: =IFERROR((Q9/P9),0) -> 0.64285714 | S9: =M9+P9 -> 80 | T9: =N9+Q9 -> 49 | U9: =IFERROR((T9/S9),0) -> 0.6125
B10: KODUNGALLUR | C10: =COUNTIFS(Booking!C:C,B10) -> 44 | D10: =COUNTIFS(RETAIL!N:N,B10) -> 13 | E10: =COUNTIFS(IH!M:M,B10,IH!S:S,"DISBURSED") -> 8 | F10: =COUNTIFS(IH!M:M,B10,IH!S:S,"LOGIN") -> 0 | G10: =IFERROR((E10/D10),0) -> 0.61538462 | H10: =COUNTIFS(IH!M:M,B10,IH!T:T,"MSSF LOGIN") -> 2 | I10: =COUNTIFS(IH!M:M,B10,IH!T:T,"MSSF DISBURSED") -> 3 | J10: JINEESH | L10: PRADEEP | M10: 0 | N10: 0 | O10: =IFERROR((N10/M10),0) -> 0 | P10: 0 | Q10: 0 | R10: =IFERROR((Q10/P10),0) -> 0 | S10: =M10+P10 -> 0 | T10: =N10+Q10 -> 0 | U10: =IFERROR((T10/S10),0) -> 0
B11: KOLENCHERY | C11: =COUNTIFS(Booking!C:C,B11) -> 25 | D11: =COUNTIFS(RETAIL!N:N,B11) -> 9 | E11: =COUNTIFS(IH!M:M,B11,IH!S:S,"DISBURSED") -> 7 | F11: =COUNTIFS(IH!M:M,B11,IH!S:S,"LOGIN") -> 1 | G11: =IFERROR((E11/D11),0) -> 0.77777778 | H11: =COUNTIFS(IH!M:M,B11,IH!T:T,"MSSF LOGIN") -> 1 | I11: =COUNTIFS(IH!M:M,B11,IH!T:T,"MSSF DISBURSED") -> 4 | J11: AMAL | L11: ABHIJITH | M11: 0 | N11: 0 | O11: =IFERROR((N11/M11),0) -> 0 | P11: 0 | Q11: 0 | R11: =IFERROR((Q11/P11),0) -> 0 | S11: =M11+P11 -> 0 | T11: =N11+Q11 -> 0 | U11: =IFERROR((T11/S11),0) -> 0
B12: KOOTHATTUKULAM | C12: =COUNTIFS(Booking!C:C,B12) -> 29 | D12: =COUNTIFS(RETAIL!N:N,B12) -> 11 | E12: =COUNTIFS(IH!M:M,B12,IH!S:S,"DISBURSED") -> 6 | F12: =COUNTIFS(IH!M:M,B12,IH!S:S,"LOGIN") -> 1 | G12: =IFERROR((E12/D12),0) -> 0.54545455 | H12: =COUNTIFS(IH!M:M,B12,IH!T:T,"MSSF LOGIN") -> 3 | I12: =COUNTIFS(IH!M:M,B12,IH!T:T,"MSSF DISBURSED") -> 2 | J12: AMAL | L12: ALFY | M12: 0 | N12: 0 | O12: =IFERROR((N12/M12),0) -> 0 | P12: 0 | Q12: 0 | R12: =IFERROR((Q12/P12),0) -> 0 | S12: =M12+P12 -> 0 | T12: =N12+Q12 -> 0 | U12: =IFERROR((T12/S12),0) -> 0
B13: PERUMBAVOOR | C13: =COUNTIFS(Booking!C:C,B13) -> 25 | D13: =COUNTIFS(RETAIL!N:N,B13) -> 12 | E13: =COUNTIFS(IH!M:M,B13,IH!S:S,"DISBURSED") -> 9 | F13: =COUNTIFS(IH!M:M,B13,IH!S:S,"LOGIN") -> 1 | G13: =IFERROR((E13/D13),0) -> 0.75 | H13: =COUNTIFS(IH!M:M,B13,IH!T:T,"MSSF LOGIN") -> 2 | I13: =COUNTIFS(IH!M:M,B13,IH!T:T,"MSSF DISBURSED") -> 7 | J13: SALMAN | L13: TOTAL | M13: =SUM(M4:M12) -> 185 | N13: =SUM(N4:N12) -> 109 | O13: =IFERROR((N13/M13),0) -> 0.58918919 | P13: =SUM(P4:P12) -> 125 | Q13: =SUM(Q4:Q12) -> 88 | R13: =IFERROR((Q13/P13),0) -> 0.704 | S13: =SUM(S4:S12) -> 310 | T13: =SUM(T4:T12) -> 197 | U13: =IFERROR((T13/S13),0) -> 0.63548387
B14: PIRAVOM | C14: =COUNTIFS(Booking!C:C,B14) -> 23 | D14: =COUNTIFS(RETAIL!N:N,B14) -> 14 | E14: =COUNTIFS(IH!M:M,B14,IH!S:S,"DISBURSED") -> 6 | F14: =COUNTIFS(IH!M:M,B14,IH!S:S,"LOGIN") -> 0 | G14: =IFERROR((E14/D14),0) -> 0.42857143 | H14: =COUNTIFS(IH!M:M,B14,IH!T:T,"MSSF LOGIN") -> 1 | I14: =COUNTIFS(IH!M:M,B14,IH!T:T,"MSSF DISBURSED") -> 3 | J14: AMAL | L14: ARENA COCHIN | M14: ='Arena+Nexa'!C24 -> 174 | N14: ='Arena+Nexa'!F24 -> 104 | O14: =IFERROR((N14/M14),0) -> 0.59770115 | P14: ='Arena+Nexa'!D24 -> 49 | Q14: ='Arena+Nexa'!G24 -> 38 | R14: =IFERROR((Q14/P14),0) -> 0.7755102 | S14: =M14+P14 -> 223 | T14: =N14+Q14 -> 142 | U14: =IFERROR((T14/S14),0) -> 0.6367713
B15: THRISSUR | C15: =COUNTIFS(Booking!C:C,B15) -> 36 | D15: =COUNTIFS(RETAIL!N:N,B15) -> 25 | E15: =COUNTIFS(IH!M:M,B15,IH!S:S,"DISBURSED") -> 12 | F15: =COUNTIFS(IH!M:M,B15,IH!S:S,"LOGIN") -> 0 | G15: =IFERROR((E15/D15),0) -> 0.48 | H15: =COUNTIFS(IH!M:M,B15,IH!T:T,"MSSF LOGIN") -> 1 | I15: =COUNTIFS(IH!M:M,B15,IH!T:T,"MSSF DISBURSED") -> 5 | J15: SINTO
B16: TRIPPUNITHURA | C16: =COUNTIFS(Booking!C:C,B16) -> 16 | D16: =COUNTIFS(RETAIL!N:N,B16) -> 9 | E16: =COUNTIFS(IH!M:M,B16,IH!S:S,"DISBURSED") -> 5 | F16: =COUNTIFS(IH!M:M,B16,IH!S:S,"LOGIN") -> 0 | G16: =IFERROR((E16/D16),0) -> 0.55555556 | H16: =COUNTIFS(IH!M:M,B16,IH!T:T,"MSSF LOGIN") -> 4 | I16: =COUNTIFS(IH!M:M,B16,IH!T:T,"MSSF DISBURSED") -> 1 | J16: SIVAPRASAD
B17: NEXA COCHIN | C17: =COUNTIFS(Booking!C:C,B17) -> 16 | D17: =COUNTIFS(RETAIL!N:N,B17) -> 10 | E17: =COUNTIFS(IH!M:M,B17,IH!S:S,"DISBURSED") -> 4 | F17: =COUNTIFS(IH!M:M,B17,IH!S:S,"LOGIN") -> 0 | G17: =IFERROR((E17/D17),0) -> 0.4 | H17: =COUNTIFS(IH!M:M,B17,IH!T:T,"MSSF LOGIN") -> 2 | I17: =COUNTIFS(IH!M:M,B17,IH!T:T,"MSSF DISBURSED") -> 2 | J17: WILSON
B18: STUDIO KDLR | C18: =COUNTIFS(Booking!C:C,B18) -> 0 | D18: =COUNTIFS(RETAIL!N:N,B18) -> 1 | E18: =COUNTIFS(IH!M:M,B18,IH!S:S,"DISBURSED") -> 1 | F18: =COUNTIFS(IH!M:M,B18,IH!S:S,"LOGIN") -> 0 | G18: =IFERROR((E18/D18),0) -> 1 | H18: =COUNTIFS(IH!M:M,B18,IH!T:T,"MSSF LOGIN") -> 0 | I18: =COUNTIFS(IH!M:M,B18,IH!T:T,"MSSF DISBURSED") -> 1 | J18: JINEESH
B19: STUDIO KPLM | C19: =COUNTIFS(Booking!C:C,B19) -> 0 | D19: =COUNTIFS(RETAIL!N:N,B19) -> 0 | E19: =COUNTIFS(IH!M:M,B19,IH!S:S,"DISBURSED") -> 0 | F19: =COUNTIFS(IH!M:M,B19,IH!S:S,"LOGIN") -> 0 | G19: =IFERROR((E19/D19),0) -> 0 | H19: =COUNTIFS(IH!M:M,B19,IH!T:T,"MSSF LOGIN") -> 0 | I19: =COUNTIFS(IH!M:M,B19,IH!T:T,"MSSF DISBURSED") -> 0 | J19: JINEESH
B20: Total | C20: =SUM(C3:C19) -> 396 | D20: =SUM(D3:D19) -> 185 | E20: =SUM(E3:E19) -> 109 | F20: =SUM(F3:F19) -> 22 | G20: =IFERROR((E20/D20),0) -> 0.58918919 | H20: =SUM(H3:H19) -> 48 | I20: =SUM(I3:I19) -> 59 | J20: =IFERROR((I20/D20),0) -> 0.31891892
B22: ARENA | C22: =SUM(C3:C16) -> 380 | D22: =SUM(D3:D16) -> 174 | E22: =SUM(E3:E16) -> 104 | F22: =SUM(F3:F16) -> 22 | G22: =IFERROR((E22/D22),0) -> 0.59770115 | H22: =SUM(H3:H16) -> 46 | I22: =SUM(I3:I16) -> 56
B23: NEXA | C23: =C17 -> 16 | D23: =D17 -> 10 | E23: =E17 -> 4 | F23: =F17 -> 0 | G23: =IFERROR((E23/D23),0) -> 0.4 | H23: =H17 -> 2 | I23: =I17 -> 2
B24: STUDIO | C24: =SUM(C18:C19) -> 0 | D24: =SUM(D18:D19) -> 1 | E24: =SUM(E18:E19) -> 1 | F24: =SUM(F18:F19) -> 0 | G24: =IFERROR((E24/D24),0) -> 1 | H24: =SUM(H18:H19) -> 0 | I24: =SUM(I18:I19) -> 1
C26: Date | D26: Retail | E26: IH | F26: Pent % | H26: MF | I26: MF %
C27: 46109 | D27: 10 | E27: =COUNTIFS(IH!P:P,C27) -> 9 | F27: =IFERROR((E27/D27),0) -> 0.9 | H27: =E27 -> 9 | I27: =H27/D27 -> 0.9
H28: =E20 -> 109 | I28: =G20 -> 0.58918919

Sheet Finance
B1: =CONCATENATE("IH Finance Performance Report as on ",TEXT(TODAY(),"dd-mmm-yy")) -> IH Finance Performance Report as on 30-Mar-26 | L1: =CONCATENATE("Arena Location wise IH Finance Performance as on ",TEXT(TODAY(),"dd-mmm-yy")) -> Arena Location wise IH Finance Performance as on 30-Mar-26
B2: Channel/Location | C2: ARENA | F2: NEXA | J2: GRAND TOTAL | L2: OUTLET | M2: Booking | N2: Bkg IH | O2: Retail | P2: IH | Q2: Pent % | R2: Login | S2: Allot | T2: Allot IH
C3: COCHIN | D3: CGR | E3: TOTAL | F3: COCHIN | G3: KYM | H3: KTM | I3: TOTAL | L3: ALUVA | M3: =COUNTIFS(Booking!C:C,L3) -> 5 | N3: =COUNTIFS(Booking!E:E,"IH",Booking!C:C,L3) -> 0 | O3: =COUNTIFS(RETAIL!N:N,+L3) -> 1 | P3: =COUNTIFS(IH!M:M,L3,IH!S:S,"DISBURSED") -> 0 | Q3: =IFERROR((P3/O3),0) -> 0 | R3: =COUNTIFS(IH!M:M,L3,IH!S:S,"LOGIN") -> 0 | S3: =COUNTIFS(Allotment!D:D,L3) -> 0 | T3: =COUNTIFS(Allotment!F:F,"IH",Allotment!D:D,L3) -> 0
B4: RETAIL | C4: =O20 -> 185 | D4: 46 | E4: =C4+D4 -> 231 | F4: =[1]SRM!$D$10 -> 125 | G4: 51 | H4: 62 | I4: =F4+G4+H4 -> 238 | J4: =E4+I4 -> 469 | L4: ANGAMALY | M4: =COUNTIFS(Booking!C:C,L4) -> 17 | N4: =COUNTIFS(Booking!E:E,"IH",Booking!C:C,L4) -> 7 | O4: =COUNTIFS(RETAIL!N:N,+L4) -> 5 | P4: =COUNTIFS(IH!M:M,L4,IH!S:S,"DISBURSED") -> 4 | Q4: =IFERROR((P4/O4),0) -> 0.8 | R4: =COUNTIFS(IH!M:M,L4,IH!S:S,"LOGIN") -> 3 | S4: =COUNTIFS(Allotment!D:D,L4) -> 0 | T4: =COUNTIFS(Allotment!F:F,"IH",Allotment!D:D,L4) -> 0
B5: IN FIN | C5: =P20 -> 109 | D5: 18 | E5: =C5+D5 -> 127 | F5: =[1]SRM!$E$10 -> 88 | G5: 38 | H5: 38 | I5: =F5+G5+H5 -> 164 | J5: =E5+I5 -> 291 | L5: CHAVAKKAD | M5: =COUNTIFS(Booking!C:C,L5) -> 31 | N5: =COUNTIFS(Booking!E:E,"IH",Booking!C:C,L5) -> 15 | O5: =COUNTIFS(RETAIL!N:N,+L5) -> 9 | P5: =COUNTIFS(IH!M:M,L5,IH!S:S,"DISBURSED") -> 8 | Q5: =IFERROR((P5/O5),0) -> 0.88888889 | R5: =COUNTIFS(IH!M:M,L5,IH!S:S,"LOGIN") -> 0 | S5: =COUNTIFS(Allotment!D:D,L5) -> 2 | T5: =COUNTIFS(Allotment!F:F,"IH",Allotment!D:D,L5) -> 2
B6: IH FIN AMT (Lac) | C6: =D25 -> 646.93841 | D6: 134.61 | E6: =C6+D6 -> 781.54841 | F6: =[1]SRM!$C$17 -> 604.21806 | G6: 280.89 | H6: 252.43 | I6: =F6+G6+H6 -> 1137.5381 | J6: =E6+I6 -> 1919.0865 | L6: EDAPPALLY | M6: =COUNTIFS(Booking!C:C,L6) -> 57 | N6: =COUNTIFS(Booking!E:E,"IH",Booking!C:C,L6) -> 34 | O6: =COUNTIFS(RETAIL!N:N,+L6) -> 35 | P6: =COUNTIFS(IH!M:M,L6,IH!S:S,"DISBURSED") -> 20 | Q6: =IFERROR((P6/O6),0) -> 0.57142857 | R6: =COUNTIFS(IH!M:M,L6,IH!S:S,"LOGIN") -> 11 | S6: =COUNTIFS(Allotment!D:D,L6) -> 21 | T6: =COUNTIFS(Allotment!F:F,"IH",Allotment!D:D,L6) -> 7
B7: IH PENT % | C7: =IFERROR((C5/C4),0) -> 0.58918919 | D7: =IFERROR((D5/D4),0) -> 0.39130435 | E7: =IFERROR((E5/E4),0) -> 0.54978355 | F7: =IFERROR((F5/F4),0) -> 0.704 | G7: =IFERROR((G5/G4),0) -> 0.74509804 | H7: =IFERROR((H5/H4),0) -> 0.61290323 | I7: =IFERROR((I5/I4),0) -> 0.68907563 | J7: =IFERROR((J5/J4),0) -> 0.62046908 | L7: FORTKOCHI | M7: =COUNTIFS(Booking!C:C,L7) -> 20 | N7: =COUNTIFS(Booking!E:E,"IH",Booking!C:C,L7) -> 8 | O7: =COUNTIFS(RETAIL!N:N,+L7) -> 4 | P7: =COUNTIFS(IH!M:M,L7,IH!S:S,"DISBURSED") -> 3 | Q7: =IFERROR((P7/O7),0) -> 0.75 | R7: =COUNTIFS(IH!M:M,L7,IH!S:S,"LOGIN") -> 3 | S7: =COUNTIFS(Allotment!D:D,L7) -> 3 | T7: =COUNTIFS(Allotment!F:F,"IH",Allotment!D:D,L7) -> 2
B8: BOOKING | C8: =Report!F10 -> 396 | D8: 115 | E8: =C8+D8 -> 511 | F8: =[1]Report!$M$17 -> 189 | G8: 128 | H8: 130 | I8: =F8+G8+H8 -> 447 | J8: =E8+I8 -> 958 | L8: KADAVANTHRA | M8: =COUNTIFS(Booking!C:C,L8) -> 19 | N8: =COUNTIFS(Booking!E:E,"IH",Booking!C:C,L8) -> 6 | O8: =COUNTIFS(RETAIL!N:N,+L8) -> 8 | P8: =COUNTIFS(IH!M:M,L8,IH!S:S,"DISBURSED") -> 5 | Q8: =IFERROR((P8/O8),0) -> 0.625 | R8: =COUNTIFS(IH!M:M,L8,IH!S:S,"LOGIN") -> 2 | S8: =COUNTIFS(Allotment!D:D,L8) -> 3 | T8: =COUNTIFS(Allotment!F:F,"IH",Allotment!D:D,L8) -> 2
B9: LOGIN | C9: =Report!H10 -> 79 | D9: 20 | E9: =C9+D9 -> 99 | F9: =[1]Report!$N$17 -> 32 | G9: 10 | H9: 11 | I9: =F9+G9+H9 -> 53 | J9: =E9+I9 -> 152 | L9: KAIPAMANGALAM | M9: =COUNTIFS(Booking!C:C,L9) -> 33 | N9: =COUNTIFS(Booking!E:E,"IH",Booking!C:C,L9) -> 15 | O9: =COUNTIFS(RETAIL!N:N,+L9) -> 19 | P9: =COUNTIFS(IH!M:M,L9,IH!S:S,"DISBURSED") -> 11 | Q9: =IFERROR((P9/O9),0) -> 0.57894737 | R9: =COUNTIFS(IH!M:M,L9,IH!S:S,"LOGIN") -> 0 | S9: =COUNTIFS(Allotment!D:D,L9) -> 6 | T9: =COUNTIFS(Allotment!F:F,"IH",Allotment!D:D,L9) -> 4
B10: PEND. LOGIN | C10: =Report!J10 -> 95 | D10: 62 | E10: =C10+D10 -> 157 | F10: =[1]Report!$O$17 -> 28 | G10: 36 | H10: 19 | I10: =F10+G10+H10 -> 83 | J10: =E10+I10 -> 240 | L10: KODUNGALLUR | M10: =COUNTIFS(Booking!C:C,L10) -> 44 | N10: =COUNTIFS(Booking!E:E,"IH",Booking!C:C,L10) -> 16 | O10: =COUNTIFS(RETAIL!N:N,+L10) -> 13 | P10: =COUNTIFS(IH!M:M,L10,IH!S:S,"DISBURSED") -> 8 | Q10: =IFERROR((P10/O10),0) -> 0.61538462 | R10: =COUNTIFS(IH!M:M,L10,IH!S:S,"LOGIN") -> 0 | S10: =COUNTIFS(Allotment!D:D,L10) -> 8 | T10: =COUNTIFS(Allotment!F:F,"IH",Allotment!D:D,L10) -> 3
B11: BOOKING % | C11: =IFERROR((C9/C8),0) -> 0.19949495 | D11: =IFERROR((D9/D8),0) -> 0.17391304 | E11: =IFERROR((E9/E8),0) -> 0.19373777 | F11: =IFERROR((F9/F8),0) -> 0.16931217 | G11: =IFERROR((G9/G8),0) -> 0.078125 | H11: =IFERROR((H9/H8),0) -> 0.084615385 | I11: =IFERROR((I9/I8),0) -> 0.11856823 | J11: =IFERROR((J9/J8),0) -> 0.15866388 | L11: KOLENCHERY | M11: =COUNTIFS(Booking!C:C,L11) -> 25 | N11: =COUNTIFS(Booking!E:E,"IH",Booking!C:C,L11) -> 12 | O11: =COUNTIFS(RETAIL!N:N,+L11) -> 9 | P11: =COUNTIFS(IH!M:M,L11,IH!S:S,"DISBURSED") -> 7 | Q11: =IFERROR((P11/O11),0) -> 0.77777778 | R11: =COUNTIFS(IH!M:M,L11,IH!S:S,"LOGIN") -> 1 | S11: =COUNTIFS(Allotment!D:D,L11) -> 1 | T11: =COUNTIFS(Allotment!F:F,"IH",Allotment!D:D,L11) -> 1
B12: ALLOTMENTS | C12: =S20 -> 71 | D12: 15 | E12: =C12+D12 -> 86 | F12: =[1]SRM!$U$24 -> 29 | G12: 10 | H12: 13 | I12: =F12+G12+H12 -> 52 | J12: =E12+I12 -> 138 | L12: KOOTHATTUKULAM | M12: =COUNTIFS(Booking!C:C,L12) -> 29 | N12: =COUNTIFS(Booking!E:E,"IH",Booking!C:C,L12) -> 9 | O12: =COUNTIFS(RETAIL!N:N,+L12) -> 11 | P12: =COUNTIFS(IH!M:M,L12,IH!S:S,"DISBURSED") -> 6 | Q12: =IFERROR((P12/O12),0) -> 0.54545455 | R12: =COUNTIFS(IH!M:M,L12,IH!S:S,"LOGIN") -> 1 | S12: =COUNTIFS(Allotment!D:D,L12) -> 5 | T12: =COUNTIFS(Allotment!F:F,"IH",Allotment!D:D,L12) -> 2
B13: ALLOT - IH | C13: =T20 -> 32 | D13: 9 | E13: =C13+D13 -> 41 | F13: =[1]SRM!$V$24 -> 18 | G13: 4 | H13: 7 | I13: =F13+G13+H13 -> 29 | J13: =E13+I13 -> 70 | L13: NEXA COCHIN | M13: =COUNTIFS(Booking!C:C,L13) -> 16 | N13: =COUNTIFS(Booking!E:E,"IH",Booking!C:C,L13) -> 5 | O13: =COUNTIFS(RETAIL!N:N,+L13) -> 10 | P13: =COUNTIFS(IH!M:M,L13,IH!S:S,"DISBURSED") -> 4 | Q13: =IFERROR((P13/O13),0) -> 0.4 | R13: =COUNTIFS(IH!M:M,L13,IH!S:S,"LOGIN") -> 0 | S13: =COUNTIFS(Allotment!D:D,L13) -> 7 | T13: =COUNTIFS(Allotment!F:F,"IH",Allotment!D:D,L13) -> 0
B14: ALLOTMENT - IH % | C14: =IFERROR((C13/C12),0) -> 0.45070423 | D14: =IFERROR((D13/D12),0) -> 0.6 | E14: =IFERROR((E13/E12),0) -> 0.47674419 | F14: =IFERROR((F13/F12),0) -> 0.62068966 | G14: =IFERROR((G13/G12),0) -> 0.4 | H14: =IFERROR((H13/H12),0) -> 0.53846154 | I14: =IFERROR((I13/I12),0) -> 0.55769231 | J14: =IFERROR((J13/J12),0) -> 0.50724638 | L14: PERUMBAVOOR | M14: =COUNTIFS(Booking!C:C,L14) -> 25 | N14: =COUNTIFS(Booking!E:E,"IH",Booking!C:C,L14) -> 10 | O14: =COUNTIFS(RETAIL!N:N,+L14) -> 12 | P14: =COUNTIFS(IH!M:M,L14,IH!S:S,"DISBURSED") -> 9 | Q14: =IFERROR((P14/O14),0) -> 0.75 | R14: =COUNTIFS(IH!M:M,L14,IH!S:S,"LOGIN") -> 1 | S14: =COUNTIFS(Allotment!D:D,L14) -> 4 | T14: =COUNTIFS(Allotment!F:F,"IH",Allotment!D:D,L14) -> 2
B15: RIPS | C15: =C4 -> 185 | D15: =D4 -> 46 | E15: =C15+D15 -> 231 | F15: =F4 -> 125 | G15: =G4 -> 51 | H15: =H4 -> 62 | I15: =F15+G15+H15 -> 238 | J15: =E15+I15 -> 469 | L15: PIRAVOM | M15: =COUNTIFS(Booking!C:C,L15) -> 23 | N15: =COUNTIFS(Booking!E:E,"IH",Booking!C:C,L15) -> 8 | O15: =COUNTIFS(RETAIL!N:N,+L15) -> 14 | P15: =COUNTIFS(IH!M:M,L15,IH!S:S,"DISBURSED") -> 6 | Q15: =IFERROR((P15/O15),0) -> 0.42857143 | R15: =COUNTIFS(IH!M:M,L15,IH!S:S,"LOGIN") -> 0 | S15: =COUNTIFS(Allotment!D:D,L15) -> 2 | T15: =COUNTIFS(Allotment!F:F,"IH",Allotment!D:D,L15) -> 2
B16: MSSF | C16: =Outlet!I20 -> 59 | D16: 13 | E16: =C16+D16 -> 72 | F16: =[1]SRM!$K$10 -> 61 | G16: 34 | H16: 33 | I16: =F16+G16+H16 -> 128 | J16: =E16+I16 -> 200 | L16: THRISSUR | M16: =COUNTIFS(Booking!C:C,L16) -> 36 | N16: =COUNTIFS(Booking!E:E,"IH",Booking!C:C,L16) -> 20 | O16: =COUNTIFS(RETAIL!N:N,+L16) -> 25 | P16: =COUNTIFS(IH!M:M,L16,IH!S:S,"DISBURSED") -> 12 | Q16: =IFERROR((P16/O16),0) -> 0.48 | R16: =COUNTIFS(IH!M:M,L16,IH!S:S,"LOGIN") -> 0 | S16: =COUNTIFS(Allotment!D:D,L16) -> 4 | T16: =COUNTIFS(Allotment!F:F,"IH",Allotment!D:D,L16) -> 2
B17: MSSF% | C17: =IFERROR((C16/C15),0) -> 0.31891892 | D17: =IFERROR((D16/D15),0) -> 0.2826087 | E17: =IFERROR((E16/E15),0) -> 0.31168831 | F17: =IFERROR((F16/F15),0) -> 0.488 | G17: =IFERROR((G16/G15),0) -> 0.66666667 | H17: =IFERROR((H16/H15),0) -> 0.53225806 | I17: =IFERROR((I16/I15),0) -> 0.53781513 | J17: =IFERROR((J16/J15),0) -> 0.42643923 | L17: TRIPPUNITHURA | M17: =COUNTIFS(Booking!C:C,L17) -> 16 | N17: =COUNTIFS(Booking!E:E,"IH",Booking!C:C,L17) -> 9 | O17: =COUNTIFS(RETAIL!N:N,+L17) -> 9 | P17: =COUNTIFS(IH!M:M,L17,IH!S:S,"DISBURSED") -> 5 | Q17: =IFERROR((P17/O17),0) -> 0.55555556 | R17: =COUNTIFS(IH!M:M,L17,IH!S:S,"LOGIN") -> 0 | S17: =COUNTIFS(Allotment!D:D,L17) -> 4 | T17: =COUNTIFS(Allotment!F:F,"IH",Allotment!D:D,L17) -> 3
L18: STUDIO KDLR | M18: =COUNTIFS(Booking!C:C,L18) -> 0 | N18: =COUNTIFS(Booking!E:E,"IH",Booking!C:C,L18) -> 0 | O18: =COUNTIFS(RETAIL!N:N,+L18) -> 1 | P18: =COUNTIFS(IH!M:M,L18,IH!S:S,"DISBURSED") -> 1 | Q18: =IFERROR((P18/O18),0) -> 1 | R18: =COUNTIFS(IH!M:M,L18,IH!S:S,"LOGIN") -> 0 | S18: =COUNTIFS(Allotment!D:D,L18) -> 1 | T18: =COUNTIFS(Allotment!F:F,"IH",Allotment!D:D,L18) -> 0
L19: STUDIO KPLM | M19: =COUNTIFS(Booking!C:C,L19) -> 0 | N19: =COUNTIFS(Booking!E:E,"IH",Booking!C:C,L19) -> 0 | O19: =COUNTIFS(RETAIL!N:N,+L19) -> 0 | P19: =COUNTIFS(IH!M:M,L19,IH!S:S,"DISBURSED") -> 0 | Q19: =IFERROR((P19/O19),0) -> 0 | R19: =COUNTIFS(IH!M:M,L19,IH!S:S,"LOGIN") -> 0 | S19: =COUNTIFS(Allotment!D:D,L19) -> 0 | T19: =COUNTIFS(Allotment!F:F,"IH",Allotment!D:D,L19) -> 0
L20: TOTAL | M20: =SUM(M3:M19) -> 396 | N20: =SUM(N3:N19) -> 174 | O20: =SUM(O3:O19) -> 185 | P20: =SUM(P3:P19) -> 109 | Q20: =IFERROR((P20/O20),0) -> 0.58918919 | R20: =SUM(R3:R19) -> 22 | S20: =SUM(S3:S19) -> 71 | T20: =SUM(T3:T19) -> 32
B21: =CONCATENATE("Arena Report ",TEXT(TODAY(),"dd-mmm-yy")) -> Arena Report 30-Mar-26
B22: Today Login - | C22: =COUNTIFS(IH!O:O,TODAY()) -> 1 | D22: =C22*4 -> 4
B23: Total Login - | C23: =Outlet!F20 -> 22 | D23: =C23*4 -> 88
B24: Today Disb - | C24: =COUNTIFS(IH!P:P,TODAY()) -> 3 | D24: =SUMIFS(IH!H:H,IH!S:S,"DISBURSED",IH!P:P,TODAY())/100000 -> 14.23865
B25: Total Disb - | C25: =Outlet!E20 -> 109 | D25: =SUMIFS(IH!H:H,IH!S:S,"Disbursed")/100000 -> 646.93841
B26: Retail - | C26: =Outlet!D20 -> 185
B27: PENT% - | C27: =IFERROR((C25/C26),0) -> 0.58918919
B28: MSSFLogin - | C28: =Outlet!H20 -> 48
B29: MSSF Disb - | C29: =Outlet!I20 -> 59
B30: PENT% - | C30: =C29/C26 -> 0.31891892

Sheet Arena+Nexa
B1: Arena + Nexa Outletwise Performance - Mar-26 | P1: Arena + Nexa Outletwise Performance - Feb-26
C2: RETAIL | F2: IH FINANCE | I2: IH PENT% | Q2: RETAIL | T2: IH FINANCE | W2: IH PENT%
B3: LOCATION | C3: ARENA | D3: NEXA | E3: TOTAL | F3: ARENA | G3: NEXA | H3: TOTAL | I3: ARENA | J3: NEXA | K3: TOTAL | L3: CORDINATOR | M3: LOC | N3: TOUR | P3: LOCATION | Q3: ARENA | R3: NEXA | S3: TOTAL | T3: ARENA | U3: NEXA | V3: TOTAL | W3: ARENA | X3: NEXA | Y3: TOTAL
B4: ALUVA | C4: =COUNTIFS(RETAIL!N:N,B4) -> 1 | D4: =COUNTIFS([1]RETAIL!$N:$N,B4) -> 0 | E4: =C4+D4 -> 1 | F4: =COUNTIFS(IH!M:M,B4,IH!S:S,"DISBURSED") -> 0 | G4: =COUNTIFS([1]IH!$S:$S,"DISBURSED",[1]IH!$M:$M,B4) -> 0 | H4: =F4+G4 -> 0 | I4: =IFERROR((F4/C4),0) -> 0 | J4: =IFERROR((G4/D4),0) -> 0 | K4: =IFERROR((H4/E4),0) -> 0 | L4: SALMAN | M4: ARENA | N4: =COUNTIFS(RETAIL!K:K,"*TOUR*",RETAIL!N:N,B4) -> 0 | P4: ALUVA | Q4: 2 | R4: 1 | S4: =Q4+R4 -> 3 | T4: 1 | U4: 1 | V4: =T4+U4 -> 2 | W4: =IFERROR((T4/Q4),0) -> 0.5 | X4: =IFERROR((U4/R4),0) -> 1 | Y4: =IFERROR((V4/S4),0) -> 0.66666667
B5: ANGAMALY | C5: =COUNTIFS(RETAIL!N:N,B5) -> 5 | D5: =COUNTIFS([1]RETAIL!$N:$N,B5) -> 2 | E5: =C5+D5 -> 7 | F5: =COUNTIFS(IH!M:M,B5,IH!S:S,"DISBURSED") -> 4 | G5: =COUNTIFS([1]IH!$S:$S,"DISBURSED",[1]IH!$M:$M,B5) -> 2 | H5: =F5+G5 -> 6 | I5: =IFERROR((F5/C5),0) -> 0.8 | J5: =IFERROR((G5/D5),0) -> 1 | K5: =IFERROR((H5/E5),0) -> 0.85714286 | L5: SALMAN | M5: ARENA | N5: =COUNTIFS(RETAIL!K:K,"*TOUR*",RETAIL!N:N,B5) -> 2 | P5: ANGAMALY | Q5: 2 | R5: 0 | S5: =Q5+R5 -> 2 | T5: 0 | U5: 0 | V5: =T5+U5 -> 0 | W5: =IFERROR((T5/Q5),0) -> 0 | X5: =IFERROR((U5/R5),0) -> 0 | Y5: =IFERROR((V5/S5),0) -> 0
B6: CHAVAKKAD | C6: =COUNTIFS(RETAIL!N:N,B6) -> 9 | D6: =COUNTIFS([1]RETAIL!$N:$N,B6) -> 5 | E6: =C6+D6 -> 14 | F6: =COUNTIFS(IH!M:M,B6,IH!S:S,"DISBURSED") -> 8 | G6: =COUNTIFS([1]IH!$S:$S,"DISBURSED",[1]IH!$M:$M,B6) -> 3 | H6: =F6+G6 -> 11 | I6: =IFERROR((F6/C6),0) -> 0.88888889 | J6: =IFERROR((G6/D6),0) -> 0.6 | K6: =IFERROR((H6/E6),0) -> 0.78571429 | L6: SINTO | M6: STUDIO | N6: =COUNTIFS(RETAIL!K:K,"*TOUR*",RETAIL!N:N,B6) -> 2 | P6: CHAVAKKAD | Q6: 17 | R6: 3 | S6: =Q6+R6 -> 20 | T6: 7 | U6: 4 | V6: =T6+U6 -> 11 | W6: =IFERROR((T6/Q6),0) -> 0.41176471 | X6: =IFERROR((U6/R6),0) -> 1.3333333 | Y6: =IFERROR((V6/S6),0) -> 0.55
B7: EDAPPALLY | C7: =COUNTIFS(RETAIL!N:N,B7) -> 35 | D7: =COUNTIFS([1]RETAIL!$N:$N,B7) -> 7 | E7: =C7+D7 -> 42 | F7: =COUNTIFS(IH!M:M,B7,IH!S:S,"DISBURSED") -> 20 | G7: =COUNTIFS([1]IH!$S:$S,"DISBURSED",[1]IH!$M:$M,B7) -> 5 | H7: =F7+G7 -> 25 | I7: =IFERROR((F7/C7),0) -> 0.57142857 | J7: =IFERROR((G7/D7),0) -> 0.71428571 | K7: =IFERROR((H7/E7),0) -> 0.5952381 | L7: SIVAPRASAD | M7: ARENA | N7: =COUNTIFS(RETAIL!K:K,"*TOUR*",RETAIL!N:N,B7) -> 24 | P7: EDAPPALLY | Q7: 48 | R7: 3 | S7: =Q7+R7 -> 51 | T7: 30 | U7: 2 | V7: =T7+U7 -> 32 | W7: =IFERROR((T7/Q7),0) -> 0.625 | X7: =IFERROR((U7/R7),0) -> 0.66666667 | Y7: =IFERROR((V7/S7),0) -> 0.62745098
B8: FORTKOCHI | C8: =COUNTIFS(RETAIL!N:N,B8) -> 4 | D8: =COUNTIFS([1]RETAIL!$N:$N,B8) -> 1 | E8: =C8+D8 -> 5 | F8: =COUNTIFS(IH!M:M,B8,IH!S:S,"DISBURSED") -> 3 | G8: =COUNTIFS([1]IH!$S:$S,"DISBURSED",[1]IH!$M:$M,B8) -> 1 | H8: =F8+G8 -> 4 | I8: =IFERROR((F8/C8),0) -> 0.75 | J8: =IFERROR((G8/D8),0) -> 1 | K8: =IFERROR((H8/E8),0) -> 0.8 | L8: SIVAPRASAD | M8: ARENA | N8: =COUNTIFS(RETAIL!K:K,"*TOUR*",RETAIL!N:N,B8) -> 4 | P8: FORTKOCHI | Q8: 6 | R8: 2 | S8: =Q8+R8 -> 8 | T8: 4 | U8: 2 | V8: =T8+U8 -> 6 | W8: =IFERROR((T8/Q8),0) -> 0.66666667 | X8: =IFERROR((U8/R8),0) -> 1 | Y8: =IFERROR((V8/S8),0) -> 0.75
B9: KADAVANTHRA | C9: =COUNTIFS(RETAIL!N:N,B9) -> 8 | D9: =COUNTIFS([1]RETAIL!$N:$N,B9) -> 3 | E9: =C9+D9 -> 11 | F9: =COUNTIFS(IH!M:M,B9,IH!S:S,"DISBURSED") -> 5 | G9: =COUNTIFS([1]IH!$S:$S,"DISBURSED",[1]IH!$M:$M,B9) -> 3 | H9: =F9+G9 -> 8 | I9: =IFERROR((F9/C9),0) -> 0.625 | J9: =IFERROR((G9/D9),0) -> 1 | K9: =IFERROR((H9/E9),0) -> 0.72727273 | L9: SALMAN | M9: ARENA | N9: =COUNTIFS(RETAIL!K:K,"*TOUR*",RETAIL!N:N,B9) -> 5 | P9: KADAVANTHRA | Q9: 7 | R9: 3 | S9: =Q9+R9 -> 10 | T9: 4 | U9: 1 | V9: =T9+U9 -> 5 | W9: =IFERROR((T9/Q9),0) -> 0.57142857 | X9: =IFERROR((U9/R9),0) -> 0.33333333 | Y9: =IFERROR((V9/S9),0) -> 0.5
B10: KAIPAMANGALAM | C10: =COUNTIFS(RETAIL!N:N,B10) -> 19 | D10: =COUNTIFS([1]RETAIL!$N:$N,B10) -> 6 | E10: =C10+D10 -> 25 | F10: =COUNTIFS(IH!M:M,B10,IH!S:S,"DISBURSED") -> 11 | G10: =COUNTIFS([1]IH!$S:$S,"DISBURSED",[1]IH!$M:$M,B10) -> 6 | H10: =F10+G10 -> 17 | I10: =IFERROR((F10/C10),0) -> 0.57894737 | J10: =IFERROR((G10/D10),0) -> 1 | K10: =IFERROR((H10/E10),0) -> 0.68 | L10: JINEESH | M10: STUDIO | N10: =COUNTIFS(RETAIL!K:K,"*TOUR*",RETAIL!N:N,B10) -> 9 | P10: KAIPAMANGALAM | Q10: 16 | R10: 4 | S10: =Q10+R10 -> 20 | T10: 11 | U10: 3 | V10: =T10+U10 -> 14 | W10: =IFERROR((T10/Q10),0) -> 0.6875 | X10: =IFERROR((U10/R10),0) -> 0.75 | Y10: =IFERROR((V10/S10),0) -> 0.7
B11: KODUNGALLUR | C11: =COUNTIFS(RETAIL!N:N,B11) -> 13 | D11: =COUNTIFS([1]RETAIL!$N:$N,B11) -> 10 | E11: =C11+D11 -> 23 | F11: =COUNTIFS(IH!M:M,B11,IH!S:S,"DISBURSED") -> 8 | G11: =COUNTIFS([1]IH!$S:$S,"DISBURSED",[1]IH!$M:$M,B11) -> 7 | H11: =F11+G11 -> 15 | I11: =IFERROR((F11/C11),0) -> 0.61538462 | J11: =IFERROR((G11/D11),0) -> 0.7 | K11: =IFERROR((H11/E11),0) -> 0.65217391 | L11: JINEESH | M11: STUDIO | N11: =COUNTIFS(RETAIL!K:K,"*TOUR*",RETAIL!N:N,B11) -> 5 | P11: KODUNGALLOOR | Q11: 11 | R11: 5 | S11: =Q11+R11 -> 16 | T11: 11 | U11: 2 | V11: =T11+U11 -> 13 | W11: =IFERROR((T11/Q11),0) -> 1 | X11: =IFERROR((U11/R11),0) -> 0.4 | Y11: =IFERROR((V11/S11),0) -> 0.8125
B12: KOLENCHERY | C12: =COUNTIFS(RETAIL!N:N,B12) -> 9 | D12: =COUNTIFS([1]RETAIL!$N:$N,B12) -> 5 | E12: =C12+D12 -> 14 | F12: =COUNTIFS(IH!M:M,B12,IH!S:S,"DISBURSED") -> 7 | G12: =COUNTIFS([1]IH!$S:$S,"DISBURSED",[1]IH!$M:$M,B12) -> 4 | H12: =F12+G12 -> 11 | I12: =IFERROR((F12/C12),0) -> 0.77777778 | J12: =IFERROR((G12/D12),0) -> 0.8 | K12: =IFERROR((H12/E12),0) -> 0.78571429 | L12: AMAL | M12: ARENA | N12: =COUNTIFS(RETAIL!K:K,"*TOUR*",RETAIL!N:N,B12) -> 0 | P12: KOLENCHERRY | Q12: 11 | R12: 2 | S12: =Q12+R12 -> 13 | T12: 6 | U12: 1 | V12: =T12+U12 -> 7 | W12: =IFERROR((T12/Q12),0) -> 0.54545455 | X12: =IFERROR((U12/R12),0) -> 0.5 | Y12: =IFERROR((V12/S12),0) -> 0.53846154
B13: KOOTHATTUKULAM | C13: =COUNTIFS(RETAIL!N:N,B13) -> 11 | D13: =COUNTIFS([1]RETAIL!$N:$N,B13) -> 0 | E13: =C13+D13 -> 11 | F13: =COUNTIFS(IH!M:M,B13,IH!S:S,"DISBURSED") -> 6 | G13: =COUNTIFS([1]IH!$S:$S,"DISBURSED",[1]IH!$M:$M,B13) -> 0 | H13: =F13+G13 -> 6 | I13: =IFERROR((F13/C13),0) -> 0.54545455 | J13: =IFERROR((G13/D13),0) -> 0 | K13: =IFERROR((H13/E13),0) -> 0.54545455 | L13: AMAL | M13: ARENA | N13: =COUNTIFS(RETAIL!K:K,"*TOUR*",RETAIL!N:N,B13) -> 1 | P13: KOOTHATTUKULAM | Q13: 18 | R13: 13 | S13: =Q13+R13 -> 31 | T13: 8 | U13: 9 | V13: =T13+U13 -> 17 | W13: =IFERROR((T13/Q13),0) -> 0.44444444 | X13: =IFERROR((U13/R13),0) -> 0.69230769 | Y13: =IFERROR((V13/S13),0) -> 0.5483871
B14: PERUMBAVOOR | C14: =COUNTIFS(RETAIL!N:N,B14) -> 12 | D14: =COUNTIFS([1]RETAIL!$N:$N,B14) -> 4 | E14: =C14+D14 -> 16 | F14: =COUNTIFS(IH!M:M,B14,IH!S:S,"DISBURSED") -> 9 | G14: =COUNTIFS([1]IH!$S:$S,"DISBURSED",[1]IH!$M:$M,B14) -> 3 | H14: =F14+G14 -> 12 | I14: =IFERROR((F14/C14),0) -> 0.75 | J14: =IFERROR((G14/D14),0) -> 0.75 | K14: =IFERROR((H14/E14),0) -> 0.75 | L14: SALMAN | M14: ARENA | N14: =COUNTIFS(RETAIL!K:K,"*TOUR*",RETAIL!N:N,B14) -> 0 | P14: PERUMBAVOOR | Q14: 14 | R14: 1 | S14: =Q14+R14 -> 15 | T14: 10 | U14: 1 | V14: =T14+U14 -> 11 | W14: =IFERROR((T14/Q14),0) -> 0.71428571 | X14: =IFERROR((U14/R14),0) -> 1 | Y14: =IFERROR((V14/S14),0) -> 0.73333333
B15: PIRAVOM | C15: =COUNTIFS(RETAIL!N:N,B15) -> 14 | D15: =COUNTIFS([1]RETAIL!$N:$N,B15) -> 0 | E15: =C15+D15 -> 14 | F15: =COUNTIFS(IH!M:M,B15,IH!S:S,"DISBURSED") -> 6 | G15: =COUNTIFS([1]IH!$S:$S,"DISBURSED",[1]IH!$M:$M,B15) -> 0 | H15: =F15+G15 -> 6 | I15: =IFERROR((F15/C15),0) -> 0.42857143 | J15: =IFERROR((G15/D15),0) -> 0 | K15: =IFERROR((H15/E15),0) -> 0.42857143 | L15: AMAL | M15: ARENA | N15: =COUNTIFS(RETAIL!K:K,"*TOUR*",RETAIL!N:N,B15) -> 4 | P15: PIRAVOM | Q15: 10 | R15: 2 | S15: =Q15+R15 -> 12 | T15: 9 | U15: 0 | V15: =T15+U15 -> 9 | W15: =IFERROR((T15/Q15),0) -> 0.9 | X15: =IFERROR((U15/R15),0) -> 0 | Y15: =IFERROR((V15/S15),0) -> 0.75
... B20: STUDIO KPLM | C20: =COUNTIFS(RETAIL!N:N,B20) -> 0 | D20: =COUNTIFS([1]RETAIL!$N:$N,B20) -> 1 | E20: =C20+D20 -> 1 | F20: =COUNTIFS(IH!M:M,B20,IH!S:S,"DISBURSED") -> 0 | G20: =COUNTIFS([1]IH!$S:$S,"DISBURSED",[1]IH!$M:$M,B20) -> 1 | H20: =F20+G20 -> 1 | I20: =IFERROR((F20/C20),0) -> 0 | J20: =IFERROR((G20/D20),0) -> 1 | K20: =IFERROR((H20/E20),0) -> 1 | L20: JINEESH | M20: STUDIO | N20: =COUNTIFS(RETAIL!K:K,"*TOUR*",RETAIL!N:N,B20) -> 0 | P20: STUDIO KPLM | Q20: 0 | R20: 5 | S20: =Q20+R20 -> 5 | T20: 0 | U20: 3 | V20: =T20+U20 -> 3 | W20: =IFERROR((T20/Q20),0) -> 0 | X20: =IFERROR((U20/R20),0) -> 0.6 | Y20: =IFERROR((V20/S20),0) -> 0.6
B21: TOTAL | C21: =SUM(C4:C20) -> 185 | D21: =SUM(D4:D20) -> 125 | E21: =SUM(C21+D21) -> 310 | F21: =SUM(F4:F20) -> 109 | G21: =SUM(G4:G20) -> 88 | H21: =F21+G21 -> 197 | I21: =IFERROR((F21/C21),0) -> 0.58918919 | J21: =IFERROR((G21/D21),0) -> 0.704 | K21: =IFERROR((H21/E21),0) -> 0.63548387 | N21: =SUM(N4:N20) -> 77 | P21: TOTAL | Q21: =SUM(Q4:Q20) -> 200 | R21: =SUM(R4:R20) -> 123 | S21: =Q21+R21 -> 323 | T21: =SUM(T4:T20) -> 123 | U21: =SUM(U4:U20) -> 76 | V21: =T21+U21 -> 199 | W21: =IFERROR((T21/Q21),0) -> 0.615 | X21: =IFERROR((U21/R21),0) -> 0.61788618 | Y21: =IFERROR((V21/S21),0) -> 0.61609907
N22: =N21/C21 -> 0.41621622
B24: ARENA COCHIN | C24: {=SUMPRODUCT(C4:C17)} -> 174 | D24: {=SUMPRODUCT(D4:D17)} -> 49 | E24: =C24+D24 -> 223 | F24: {=SUMPRODUCT(F4:F17)} -> 104 | G24: {=SUMPRODUCT(G4:G17)} -> 38 | H24: =F24+G24 -> 142 | I24: =IFERROR((F24/C24),0) -> 0.59770115 | J24: =IFERROR((G24/D24),0) -> 0.7755102 | K24: =IFERROR((H24/E24),0) -> 0.6367713 | P24: Finance Cordinator wise Performance - Jan-26
B25: NEXA COCHIN | C25: =SUMPRODUCT(C18) -> 10 | D25: =SUMPRODUCT(D18) -> 70 | E25: =C25+D25 -> 80 | F25: =SUMPRODUCT(F18) -> 4 | G25: =SUMPRODUCT(G18) -> 45 | H25: =F25+G25 -> 49 | I25: =IFERROR((F25/C25),0) -> 0.4 | J25: =IFERROR((G25/D25),0) -> 0.64285714 | K25: =IFERROR((H25/E25),0) -> 0.6125 | Q25: ARENA | T25: NEXA | W25: TOTAL
B26: STUDIO | C26: {=SUMPRODUCT(C19:C20)} -> 1 | D26: {=SUMPRODUCT(D19:D20)} -> 6 | E26: =C26+D26 -> 7 | F26: {=SUMPRODUCT(F19:F20)} -> 1 | G26: {=SUMPRODUCT(G19:G20)} -> 5 | H26: =F26+G26 -> 6 | I26: =IFERROR((F26/C26),0) -> 1 | J26: =IFERROR((G26/D26),0) -> 0.83333333 | K26: =IFERROR((H26/E26),0) -> 0.85714286 | P26: COORDINATOR | Q26: RETAIL | R26: IH Fin | S26: PENT% | T26: RETAIL | U26: IH Fin | V26: PENT% | W26: RETAIL | X26: IH Fin | Y26: PENT%
B27: TOTAL | C27: =SUM(C24:C26) -> 185 | D27: =SUM(D24:D26) -> 125 | E27: =C27+D27 -> 310 | F27: =SUM(F24:F26) -> 109 | G27: =SUM(G24:G26) -> 88 | H27: =F27+G27 -> 197 | I27: =IFERROR((F27/C27),0) -> 0.58918919 | J27: =IFERROR((G27/D27),0) -> 0.704 | K27: =IFERROR((H27/E27),0) -> 0.63548387 | P27: SIVAPRASAD | Q27: =SUMIFS($Q$4:$Q$20,$L$4:$L$20,P27) -> 60 | R27: =SUMIFS($T$4:$T$20,$L$4:$L$20,P27) -> 37 | S27: =IFERROR((R27/Q27),0) -> 0.61666667 | T27: =SUMIFS($R$4:$R$20,$L$4:$L$20,P27) -> 10 | U27: =SUMIFS($U$4:$U$20,$L$4:$L$20,P27) -> 9 | V27: =IFERROR((U27/T27),0) -> 0.9 | W27: =Q27+T27 -> 70 | X27: =R27+U27 -> 46 | Y27: =IFERROR((X27/W27),0) -> 0.65714286
P28: AMAL | Q28: =SUMIFS($Q$4:$Q$20,$L$4:$L$20,P28) -> 39 | R28: =SUMIFS($T$4:$T$20,$L$4:$L$20,P28) -> 23 | S28: =IFERROR((R28/Q28),0) -> 0.58974359 | T28: =SUMIFS($R$4:$R$20,$L$4:$L$20,P28) -> 17 | U28: =SUMIFS($U$4:$U$20,$L$4:$L$20,P28) -> 10 | V28: =IFERROR((U28/T28),0) -> 0.58823529 | W28: =Q28+T28 -> 56 | X28: =R28+U28 -> 33 | Y28: =IFERROR((X28/W28),0) -> 0.58928571
P29: SALMAN | Q29: =SUMIFS($Q$4:$Q$20,$L$4:$L$20,P29) -> 25 | R29: =SUMIFS($T$4:$T$20,$L$4:$L$20,P29) -> 15 | S29: =IFERROR((R29/Q29),0) -> 0.6 | T29: =SUMIFS($R$4:$R$20,$L$4:$L$20,P29) -> 5 | U29: =SUMIFS($U$4:$U$20,$L$4:$L$20,P29) -> 3 | V29: =IFERROR((U29/T29),0) -> 0.6 | W29: =Q29+T29 -> 30 | X29: =R29+U29 -> 18 | Y29: =IFERROR((X29/W29),0) -> 0.6
P30: SINTO | Q30: =SUMIFS($Q$4:$Q$20,$L$4:$L$20,P30) -> 35 | R30: =SUMIFS($T$4:$T$20,$L$4:$L$20,P30) -> 18 | S30: =IFERROR((R30/Q30),0) -> 0.51428571 | T30: =SUMIFS($R$4:$R$20,$L$4:$L$20,P30) -> 6 | U30: =SUMIFS($U$4:$U$20,$L$4:$L$20,P30) -> 5 | V30: =IFERROR((U30/T30),0) -> 0.83333333 | W30: =Q30+T30 -> 41 | X30: =R30+U30 -> 23 | Y30: =IFERROR((X30/W30),0) -> 0.56097561
P31: JINEESH | Q31: =SUMIFS($Q$4:$Q$20,$L$4:$L$20,P31) -> 30 | R31: =SUMIFS($T$4:$T$20,$L$4:$L$20,P31) -> 24 | S31: =IFERROR((R31/Q31),0) -> 0.8 | T31: =SUMIFS($R$4:$R$20,$L$4:$L$20,P31) -> 19 | U31: =SUMIFS($U$4:$U$20,$L$4:$L$20,P31) -> 9 | V31: =IFERROR((U31/T31),0) -> 0.47368421 | W31: =Q31+T31 -> 49 | X31: =R31+U31 -> 33 | Y31: =IFERROR((X31/W31),0) -> 0.67346939
P32: WILSON | Q32: =SUMIFS($Q$4:$Q$20,$L$4:$L$20,P32) -> 11 | R32: =SUMIFS($T$4:$T$20,$L$4:$L$20,P32) -> 6 | S32: =IFERROR((R32/Q32),0) -> 0.54545455 | T32: =SUMIFS($R$4:$R$20,$L$4:$L$20,P32) -> 66 | U32: =SUMIFS($U$4:$U$20,$L$4:$L$20,P32) -> 40 | V32: =IFERROR((U32/T32),0) -> 0.60606061 | W32: =Q32+T32 -> 77 | X32: =R32+U32 -> 46 | Y32: =IFERROR((X32/W32),0) -> 0.5974026
P33: TOTAL | Q33: =SUM(Q27:Q32) -> 200 | R33: =SUM(R27:R32) -> 123 | S33: =IFERROR((R33/Q33),0) -> 0.615 | T33: =SUM(T27:T32) -> 123 | U33: =SUM(U27:U32) -> 76 | V33: =IFERROR((U33/T33),0) -> 0.61788618 | W33: =SUM(W27:W32) -> 323 | X33: =SUM(X27:X32) -> 199 | Y33: =IFERROR((X33/W33),0) -> 0.61609907

Sheet RETAIL
A1: SRL | B1: ORDER_NUMBER | C1: Enquiry_No | D1: Chassis | E1: Engine | F1: Inv_No | G1: Inv_dt | H1: Customer_id | I1: Customer_Name | J1: Model | K1: Variant_DESC | L1: DSE | M1: SRM | N1: LOCATION | O1: OUTLET | P1: Hypo | Q1: FINANCE | R1: SOURCE | S1: MSSF | T1: MSSF MAPPED | U1: MSSF STATUS | V1: IH STATUS | W1: DISBURSED DATE | X1: FINANCE CO | Y1: ERP EXECUTIVE NAME | Z1: ERP TEAM LEADER | AA1: MSSF REMARKS
A2: 1 | B2: SOB25000366 | C2: ENQ25002774 | D2: 165115 | E2: K111248 | F2: 72/VSL/25000153 | G2: 46086 | H2: 2567247652 | I2: JOSEPH JESMON | J2: VICTORIS | K2: MARUTI VICTORIS LXI CNG 1.5L 5MT | L2: VISHNU M S | M2: =VLOOKUP($L2,Emp!$A:$F,2,0) -> BINOY RAJ | N2: =VLOOKUP($L2,Emp!$A:$F,3,0) -> KODUNGALLUR | O2: =VLOOKUP($L2,Emp!$A:$F,4,0) -> ARENA | P2: CASH | Q2: CASH | R2: CASH | S2: NO | T2: =IF(_xlfn.XLOOKUP(F2,IH!Y:Y,IH!AA:AA,"")="MAPPED","MAPPED","") | U2: =IFERROR(VLOOKUP(H2,IH!C:T,18,0),"") | V2: =IF(W2<>"","DISBURSED","") | W2: =IFERROR(VLOOKUP(H2,IH!C:X,14,0),"") | X2: =VLOOKUP($L2,Emp!$A:$F,5,0) -> JINEESH | Y2: =VLOOKUP($H2,ERP!$H:$AP,33,0) -> #N/A | Z2: =VLOOKUP($H2,ERP!$H:$AP,34,0) -> #N/A
A3: 2 | B3: SOB25002218 | C3: ENQ25016028 | D3: E54170 | E3: C987571 | F3: 40/VSL/25001411 | G3: 46087 | H3: 2567242037 | I3: RANJITH T | J3: TOUR H3 | K3: MARUTI TOUR H3 CNG 1L 5MT | L3: SARATH P J | M3: =VLOOKUP($L3,Emp!$A:$F,2,0) -> SIVAPRAKASH K S | N3: =VLOOKUP($L3,Emp!$A:$F,3,0) -> THRISSUR | O3: =VLOOKUP($L3,Emp!$A:$F,4,0) -> ARENA | P3: KERALA GRAMEENA BANK | Q3: KGB | R3: IH | S3: YES | T3: =IF(_xlfn.XLOOKUP(F3,IH!Y:Y,IH!AA:AA,"")="MAPPED","MAPPED","") | U3: =IFERROR(VLOOKUP(H3,IH!C:T,18,0),"") | V3: DISBURSED | W3: FEB | X3: =VLOOKUP($L3,Emp!$A:$F,5,0) -> SINTO | Y3: =VLOOKUP($H3,ERP!$H:$AP,33,0) -> NA | Z3: =VLOOKUP($H3,ERP!$H:$AP,34,0) -> NA
A4: 3 | B4: SOB25002263 | C4: ENQ25016266 | D4: E53480 | E4: C986534 | F4: 40/VSL/25001412 | G4: 46087 | H4: 2567344451 | I4: ANSAMMA | J4: TOUR H3 | K4: MARUTI TOUR H3 CNG 1L 5MT | L4: VISHNUDAS P D | M4: =VLOOKUP($L4,Emp!$A:$F,2,0) -> SIVAPRAKASH K S | N4: =VLOOKUP($L4,Emp!$A:$F,3,0) -> THRISSUR | O4: =VLOOKUP($L4,Emp!$A:$F,4,0) -> ARENA | P4: SHRIRAM TRANSPORT FINANCE CO.LTD | Q4: SHRIRAM | R4: SELF | S4: NO | T4: =IF(_xlfn.XLOOKUP(F4,IH!Y:Y,IH!AA:AA,"")="MAPPED","MAPPED","") | U4: =IFERROR(VLOOKUP(H4,IH!C:T,18,0),"") | V4: =IF(W4<>"","DISBURSED","") | W4: =IFERROR(VLOOKUP(H4,IH!C:X,14,0),"") | X4: =VLOOKUP($L4,Emp!$A:$F,5,0) -> SINTO | Y4: =VLOOKUP($H4,ERP!$H:$AP,33,0) -> VISHNUDAS P D (C23106), | Z4: =VLOOKUP($H4,ERP!$H:$AP,34,0) -> RAJEEV (THCR)
A5: 4 | B5: SOB25002308 | C5: ENQ25016526 | D5: E53336 | E5: C986623 | F5: 40/VSL/25001413 | G5: 46087 | H5: 2567447231 | I5: SUDHI | J5: TOUR H3 | K5: MARUTI TOUR H3 CNG 1L 5MT | L5: NIDHIN C D | M5: =VLOOKUP($L5,Emp!$A:$F,2,0) -> SMITHIN P S | N5: =VLOOKUP($L5,Emp!$A:$F,3,0) -> KAIPAMANGALAM | O5: =VLOOKUP($L5,Emp!$A:$F,4,0) -> ARENA | P5: STATE BANK OF INDIA | Q5: SBI | R5: SELF | S5: NO | T5: =IF(_xlfn.XLOOKUP(F5,IH!Y:Y,IH!AA:AA,"")="MAPPED","MAPPED","") | U5: =IFERROR(VLOOKUP(H5,IH!C:T,18,0),"") | V5: =IF(W5<>"","DISBURSED","") | W5: =IFERROR(VLOOKUP(H5,IH!C:X,14,0),"") | X5: =VLOOKUP($L5,Emp!$A:$F,5,0) -> JINEESH | Y5: =VLOOKUP($H5,ERP!$H:$AP,33,0) -> NA | Z5: =VLOOKUP($H5,ERP!$H:$AP,34,0) -> NA
A6: 5 | B6: SOB25002209 | C6: ENQ25015984 | D6: E54492 | E6: C987700 | F6: 40/VSL/25001414 | G6: 46087 | H6: 2567222939 | I6: LIBIN ANTO | J6: TOUR H3 | K6: MARUTI TOUR H3 CNG 1L 5MT | L6: AMALDEV | M6: =VLOOKUP($L6,Emp!$A:$F,2,0) -> SIVAPRAKASH K S | N6: =VLOOKUP($L6,Emp!$A:$F,3,0) -> THRISSUR | O6: =VLOOKUP($L6,Emp!$A:$F,4,0) -> ARENA | P6: CASH | Q6: CASH | R6: CASH | S6: NO | T6: =IF(_xlfn.XLOOKUP(F6,IH!Y:Y,IH!AA:AA,"")="MAPPED","MAPPED","") | U6: =IFERROR(VLOOKUP(H6,IH!C:T,18,0),"") | V6: =IF(W6<>"","DISBURSED","") | W6: =IFERROR(VLOOKUP(H6,IH!C:X,14,0),"") | X6: =VLOOKUP($L6,Emp!$A:$F,5,0) -> SINTO | Y6: =VLOOKUP($H6,ERP!$H:$AP,33,0) -> NA | Z6: =VLOOKUP($H6,ERP!$H:$AP,34,0) -> BHAGIESH P (CHKD)
A7: 6 | B7: SOB25001937 | C7: ENQ25014823 | D7: E54416 | E7: 1427481 | F7: 40/VSL/25001415 | G7: 46087 | H7: 2566746837 | I7: SHIBIN K B | J7: TOUR H3 | K7: MARUTI TOUR H3 CNG 1L 5MT | L7: BINEESH P ANTO | M7: =VLOOKUP($L7,Emp!$A:$F,2,0) -> SIVAPRAKASH K S | N7: =VLOOKUP($L7,Emp!$A:$F,3,0) -> THRISSUR | O7: =VLOOKUP($L7,Emp!$A:$F,4,0) -> ARENA | P7: KERALA GRAMEENA BANK | Q7: KGB | R7: IH | S7: YES | T7: =IF(_xlfn.XLOOKUP(F7,IH!Y:Y,IH!AA:AA,"")="MAPPED","MAPPED","") | U7: =IFERROR(VLOOKUP(H7,IH!C:T,18,0),"") -> NO | V7: =IF(W7<>"","DISBURSED","") -> DISBURSED | W7: =IFERROR(VLOOKUP(H7,IH!C:X,14,0),"") -> 46087 | X7: =VLOOKUP($L7,Emp!$A:$F,5,0) -> SINTO | Y7: =VLOOKUP($H7,ERP!$H:$AP,33,0) -> BINEESH P ANTO (C22936), | Z7: =VLOOKUP($H7,ERP!$H:$AP,34,0) -> RAJEEV (THCR)
A8: 7 | B8: SOB25002150 | C8: ENQ25015563 | D8: E54510 | E8: C987803 | F8: 40/VSL/25001416 | G8: 46087 | H8: 2567087596 | I8: JAMSHEER P A | J8: TOUR H3 | K8: MARUTI TOUR H3 CNG 1L 5MT | L8: SANJAY | M8: =VLOOKUP($L8,Emp!$A:$F,2,0) -> SIVAPRAKASH K S | N8: =VLOOKUP($L8,Emp!$A:$F,3,0) -> THRISSUR | O8: =VLOOKUP($L8,Emp!$A:$F,4,0) -> ARENA | P8: KERALA GRAMEENA BANK | Q8: KGB | R8: IH | S8: NO | T8: =IF(_xlfn.XLOOKUP(F8,IH!Y:Y,IH!AA:AA,"")="MAPPED","MAPPED","") | U8: =IFERROR(VLOOKUP(H8,IH!C:T,18,0),"") -> NO | V8: =IF(W8<>"","DISBURSED","") -> DISBURSED | W8: =IFERROR(VLOOKUP(H8,IH!C:X,14,0),"") -> 46087 | X8: =VLOOKUP($L8,Emp!$A:$F,5,0) -> SINTO | Y8: =VLOOKUP($H8,ERP!$H:$AP,33,0) -> SANJAY.M.G(C26392), | Z8: =VLOOKUP($H8,ERP!$H:$AP,34,0) -> SIVAPRAKASH K.S.(TCR)
A9: 8 | B9: SOB25002176 | C9: ENQ25015701 | D9: E54635 | E9: C987892 | F9: 40/VSL/25001417 | G9: 46087 | H9: 2567161284 | I9: MIDHUN AZEEZ | J9: TOUR H3 | K9: MARUTI TOUR H3 CNG 1L 5MT | L9: SALAS JUDE | M9: =VLOOKUP($L9,Emp!$A:$F,2,0) -> NOUFAL T A | N9: =VLOOKUP($L9,Emp!$A:$F,3,0) -> EDAPPALLY | O9: =VLOOKUP($L9,Emp!$A:$F,4,0) -> ARENA | P9: KOTAK MAHINDRA PRIME LTD | Q9: KOTAK | R9: IH | S9: YES | T9: =IF(_xlfn.XLOOKUP(F9,IH!Y:Y,IH!AA:AA,"")="MAPPED","MAPPED","") | U9: =IFERROR(VLOOKUP(H9,IH!C:T,18,0),"") | V9: DISBURSED | W9: FEB | X9: =VLOOKUP($L9,Emp!$A:$F,5,0) -> SIVAPRASAD | Y9: =VLOOKUP($H9,ERP!$H:$AP,33,0) -> SALAS JUDE (C25782), | Z9: =VLOOKUP($H9,ERP!$H:$AP,34,0) -> NOUFAL T.A
A10: 9 | B10: SOB25002194 | C10: ENQ25015845 | D10: E53597 | E10: 1426622 | F10: 40/VSL/25001418 | G10: 46087 | H10: 2567186125 | I10: RAMESH PATHARI | J10: TOUR H3 | K10: MARUTI TOUR H3 CNG 1L 5MT | L10: MANU JOY | M10: =VLOOKUP($L10,Emp!$A:$F,2,0) -> MANU SASI | N10: =VLOOKUP($L10,Emp!$A:$F,3,0) -> EDAPPALLY | O10: =VLOOKUP($L10,Emp!$A:$F,4,0) -> ARENA | P10: KERALA GRAMIN BANK | Q10: KGB | R10: IH | S10: YES | T10: =IF(_xlfn.XLOOKUP(F10,IH!Y:Y,IH!AA:AA,"")="MAPPED","MAPPED","") | U10: =IFERROR(VLOOKUP(H10,IH!C:T,18,0),"") -> MSSF LOGIN | V10: =IF(W10<>"","DISBURSED","") -> DISBURSED | W10: =IFERROR(VLOOKUP(H10,IH!C:X,14,0),"") -> 46086 | X10: =VLOOKUP($L10,Emp!$A:$F,5,0) -> SIVAPRASAD | Y10: =VLOOKUP($H10,ERP!$H:$AP,33,0) -> MANU JOY (C22591), | Z10: =VLOOKUP($H10,ERP!$H:$AP,34,0) -> MANU SASI
A11: 10 | B11: SOB25002314 | C11: ENQ25016541 | D11: E53434 | E11: 1426830 | F11: 40/VSL/25001419 | G11: 46087 | H11: 2567459895 | I11: JITHIN JOSEPH | J11: TOUR H3 | K11: MARUTI TOUR H3 CNG 1L 5MT | L11: VIPIN K G | M11: =VLOOKUP($L11,Emp!$A:$F,2,0) -> BINOY RAJ | N11: =VLOOKUP($L11,Emp!$A:$F,3,0) -> KODUNGALLUR | O11: =VLOOKUP($L11,Emp!$A:$F,4,0) -> ARENA | P11: INDIAN OVERSEAS BANK | Q11: IOB | R11: SELF | S11: NO | T11: =IF(_xlfn.XLOOKUP(F11,IH!Y:Y,IH!AA:AA,"")="MAPPED","MAPPED","") | U11: =IFERROR(VLOOKUP(H11,IH!C:T,18,0),"") | V11: =IF(W11<>"","DISBURSED","") | W11: =IFERROR(VLOOKUP(H11,IH!C:X,14,0),"") | X11: =VLOOKUP($L11,Emp!$A:$F,5,0) -> JINEESH | Y11: =VLOOKUP($H11,ERP!$H:$AP,33,0) -> NA | Z11: =VLOOKUP($H11,ERP!$H:$AP,34,0) -> NA
A12: 11 | B12: SOB25002318 | C12: ENQ25016625 | D12: E54680 | E12: 1427670 | F12: 40/VSL/25001422 | G12: 46088 | H12: 2567479499 | I12: MAHESH KUMAR P S | J12: TOUR H3 | K12: MARUTI TOUR H3 CNG 1L 5MT | L12: VISHNU T M | M12: =VLOOKUP($L12,Emp!$A:$F,2,0) -> ELDHO A JACOB | N12: =VLOOKUP($L12,Emp!$A:$F,3,0) -> ANGAMALY | O12: =VLOOKUP($L12,Emp!$A:$F,4,0) -> ARENA | P12: KERALA GRAMEENA BANK | Q12: KGB | R12: IH | S12: YES | T12: =IF(_xlfn.XLOOKUP(F12,IH!Y:Y,IH!AA:AA,"")="MAPPED","MAPPED","") | U12: =IFERROR(VLOOKUP(H12,IH!C:T,18,0),"") -> MSSF LOGIN | V12: =IF(W12<>"","DISBURSED","") -> DISBURSED | W12: =IFERROR(VLOOKUP(H12,IH!C:X,14,0),"") -> 46094 | X12: =VLOOKUP($L12,Emp!$A:$F,5,0) -> SALMAN | Y12: =VLOOKUP($H12,ERP!$H:$AP,33,0) -> VISHNU T M (C26466), | Z12: =VLOOKUP($H12,ERP!$H:$AP,34,0) -> ELDHO A JACOB
A13: 12 | B13: SOB25002319 | C13: ENQ25016626 | D13: 474586 | E13: 1427330 | F13: 40/VSL/25001423 | G13: 46088 | H13: 2567480248 | I13: SANUJ JOSEPH | J13: ALTO K10 | K13: MARUTI ALTO K10 LXI 1L 5MT | L13: ELSON JACOB | M13: =VLOOKUP($L13,Emp!$A:$F,2,0) -> ANAND K V | N13: =VLOOKUP($L13,Emp!$A:$F,3,0) -> KOLENCHERY | O13: =VLOOKUP($L13,Emp!$A:$F,4,0) -> ARENA | P13: ICICI BANK LTD | Q13: ICICI | R13: IH | S13: YES | T13: =IF(_xlfn.XLOOKUP(F13,IH!Y:Y,IH!AA:AA,"")="MAPPED","MAPPED","") -> MAPPED | U13: =IFERROR(VLOOKUP(H13,IH!C:T,18,0),"") -> MSSF DISBURSED | V13: =IF(W13<>"","DISBURSED","") -> DISBURSED | W13: =IFERROR(VLOOKUP(H13,IH!C:X,14,0),"") -> 46090 | X13: =VLOOKUP($L13,Emp!$A:$F,5,0) -> AMAL | Y13: =VLOOKUP($H13,ERP!$H:$AP,33,0) -> ELSON JACOB(C23950), | Z13: =VLOOKUP($H13,ERP!$H:$AP,34,0) -> ANAND (KLY)
A14: 13 | B14: SOB25001685 | C14: ENQ25013241 | D14: 410269 | E14: F309114 | F14: 40/VSL/25001424 | G14: 46088 | H14: 2566023466 | I14: AKSHAY SHIBU | J14: TOUR S | K14: MARUTI TOUR S CNG 1.2L 5MT | L14: ALBIN MARTIN | M14: =VLOOKUP($L14,Emp!$A:$F,2,0) -> RATISH K R | N14: =VLOOKUP($L14,Emp!$A:$F,3,0) -> KADAVANTHRA | O14: =VLOOKUP($L14,Emp!$A:$F,4,0) -> ARENA | P14: CASH | Q14: CASH | R14: CASH | S14: NO | T14: =IF(_xlfn.XLOOKUP(F14,IH!Y:Y,IH!AA:AA,"")="MAPPED","MAPPED","") | U14: =IFERROR(VLOOKUP(H14,IH!C:T,18,0),"") | V14: =IF(W14<>"","DISBURSED","") | W14: =IFERROR(VLOOKUP(H14,IH!C:X,14,0),"") | X14: =VLOOKUP($L14,Emp!$A:$F,5,0) -> SALMAN | Y14: =VLOOKUP($H14,ERP!$H:$AP,33,0) -> ALBIN MARTIN (C26561), | Z14: =VLOOKUP($H14,ERP!$H:$AP,34,0) -> RATHEESH.K.R
A15: 14 | B15: SOB25002080 | C15: ENQ25015186 | D15: E55229 | E15: C988619 | F15: 40/VSL/25001421 | G15: 46088 | H15: 2567479837 | I15: SIRAJ N | J15: TOUR H3 | K15: MARUTI TOUR H3 CNG 1L 5MT | L15: JAYESH | M15: =VLOOKUP($L15,Emp!$A:$F,2,0) -> SHEMEER A K | N15: =VLOOKUP($L15,Emp!$A:$F,3,0) -> EDAPPALLY | O15: =VLOOKUP($L15,Emp!$A:$F,4,0) -> ARENA | P15: KERALA GRAMIN BANK | Q15: KGB | R15: IH | S15: YES | T15: =IF(_xlfn.XLOOKUP(F15,IH!Y:Y,IH!AA:AA,"")="MAPPED","MAPPED","") -> MAPPED | U15: =IFERROR(VLOOKUP(H15,IH!C:T,18,0),"") -> MSSF DISBURSED | V15: =IF(W15<>"","DISBURSED","") -> DISBURSED | W15: =IFERROR(VLOOKUP(H15,IH!C:X,14,0),"") -> 46088 | X15: =VLOOKUP($L15,Emp!$A:$F,5,0) -> SIVAPRASAD | Y15: =VLOOKUP($H15,ERP!$H:$AP,33,0) -> MOHAMMED RIYAS (C25510), | Z15: =VLOOKUP($H15,ERP!$H:$AP,34,0) -> SHEMEER.AK
A16: 15 | B16: SOB25002316 | C16: ENQ25016540 | D16: E53507 | E16: 1426949 | F16: 40/VSL/25001420 | G16: 46088 | H16: 2567449123 | I16: SUBHIJITH V S | J16: TOUR H3 | K16: MARUTI TOUR H3 CNG 1L 5MT | L16: JAYAKRISHNAN K V | M16: =VLOOKUP($L16,Emp!$A:$F,2,0) -> BINOY RAJ | N16: =VLOOKUP($L16,Emp!$A:$F,3,0) -> KODUNGALLUR | O16: =VLOOKUP($L16,Emp!$A:$F,4,0) -> ARENA | P16: CHOLAMANDALAM INVS.& FIN.CO.LTD | Q16: CHOLA | R16: IH | S16: YES | T16: =IF(_xlfn.XLOOKUP(F16,IH!Y:Y,IH!AA:AA,"")="MAPPED","MAPPED","") -> MAPPED | U16: =IFERROR(VLOOKUP(H16,IH!C:T,18,0),"") -> MSSF DISBURSED | V16: =IF(W16<>"","DISBURSED","") -> DISBURSED | W16: =IFERROR(VLOOKUP(H16,IH!C:X,14,0),"") -> 46087 | X16: =VLOOKUP($L16,Emp!$A:$F,5,0) -> JINEESH | Y16: =VLOOKUP($H16,ERP!$H:$AP,33,0) -> JAYAKRISHNAN K V (C25293), | Z16: =VLOOKUP($H16,ERP!$H:$AP,34,0) -> LINISH.T.K
A17: 16 | B17: SOB25000379 | C17: ENQ25002996 | D17: 760858 | E17: K110864 | F17: 72/VSL/25000154 | G17: 46088 | H17: 2567473596 | I17: AMBROSE A T | J17: BREZZA | K17: MARUTI BREZZA SMART HYBRID VXI 1.5L 6AT | L17: KRISHNARAJ | M17: =VLOOKUP($L17,Emp!$A:$F,2,0) -> SACHIN | N17: =VLOOKUP($L17,Emp!$A:$F,3,0) -> KODUNGALLUR | O17: =VLOOKUP($L17,Emp!$A:$F,4,0) -> ARENA | P17: BANK OF INDIA | Q17: BOI | R17: IH | S17: NO | T17: =IF(_xlfn.XLOOKUP(F17,IH!Y:Y,IH!AA:AA,"")="MAPPED","MAPPED","") | U17: =IFERROR(VLOOKUP(H17,IH!C:T,18,0),"") -> NO | V17: =IF(W17<>"","DISBURSED","") -> DISBURSED | W17: =IFERROR(VLOOKUP(H17,IH!C:X,14,0),"") -> 46087 | X17: =VLOOKUP($L17,Emp!$A:$F,5,0) -> JINEESH | Y17: =VLOOKUP($H17,ERP!$H:$AP,33,0) -> KRISHNARAJ M R(C26582), | Z17: =VLOOKUP($H17,ERP!$H:$AP,34,0) -> BINOY(KDLR)
A18: 17 | B18: SOB25000226 | C18: ENQ25001947 | D18: 465599 | E18: 1416463 | F18: 126/VSL/25000112 | G18: 46088 | H18: 2567460397 | I18: GOPINADHAN ELAYADAM | J18: ALTO K10 | K18: MARUTI ALTO K10 VXI 1L 5MT | L18: NYGIL GEORGE | M18: =VLOOKUP($L18,Emp!$A:$F,2,0) -> SIJO VARGHESE GEORGE | N18: =VLOOKUP($L18,Emp!$A:$F,3,0) -> PERUMBAVOOR | O18: =VLOOKUP($L18,Emp!$A:$F,4,0) -> ARENA | P18: CASH | Q18: CASH | R18: CASH | S18: NO | T18: =IF(_xlfn.XLOOKUP(F18,IH!Y:Y,IH!AA:AA,"")="MAPPED","MAPPED","") | U18: =IFERROR(VLOOKUP(H18,IH!C:T,18,0),"") | V18: =IF(W18<>"","DISBURSED","") | W18: =IFERROR(VLOOKUP(H18,IH!C:X,14,0),"") | X18: =VLOOKUP($L18,Emp!$A:$F,5,0) -> SALMAN | Y18: =VLOOKUP($H18,ERP!$H:$AP,33,0) -> NIGIL GEORGE(C23881), | Z18: =VLOOKUP($H18,ERP!$H:$AP,34,0) -> SIJO VARGHESE GEORGE (PBVR)
A19: 18 | B19: SOB25000200 | C19: ENQ25002042 | D19: 257240 | E19: F156608 | F19: 118/VSL25000097 | G19: 46088 | H19: 2567435685 | I19: AJEESH MATHEW GEORGE | J19: DZIRE | K19: MARUTI DZIRE ZXI 1.2L ISS AGS | L19: MIRAJ KAREEM | M19: =VLOOKUP($L19,Emp!$A:$F,2,0) -> JESTIN UTHUP JOHN | N19: =VLOOKUP($L19,Emp!$A:$F,3,0) -> PIRAVOM | O19: =VLOOKUP($L19,Emp!$A:$F,4,0) -> ARENA | P19: ICICI BANK LTD | Q19: ICICI | R19: IH | S19: YES | T19: =IF(_xlfn.XLOOKUP(F19,IH!Y:Y,IH!AA:AA,"")="MAPPED","MAPPED","") -> MAPPED | U19: =IFERROR(VLOOKUP(H19,IH!C:T,18,0),"") -> MSSF DISBURSED | V19: =IF(W19<>"","DISBURSED","") -> DISBURSED | W19: =IFERROR(VLOOKUP(H19,IH!C:X,14,0),"") -> 46088 | X19: =VLOOKUP($L19,Emp!$A:$F,5,0) -> AMAL | Y19: =VLOOKUP($H19,ERP!$H:$AP,33,0) -> MIRAJ K KAREEM (C26100), | Z19: =VLOOKUP($H19,ERP!$H:$AP,34,0) -> JUSTIN UTHUP JOHN (PRVM)
A20: 19 | B20: SOB25002265 | C20: ENQ25016272 | D20: E55156 | E20: 1428231 | F20: 40/VSL/25001430 | G20: 46090 | H20: 2567348291 | I20: DEEPAK K U | J20: TOUR H3 | K20: MARUTI TOUR H3 CNG 1L 5MT | L20: VINAY T V | M20: =VLOOKUP($L20,Emp!$A:$F,2,0) -> RATISH K R | N20: =VLOOKUP($L20,Emp!$A:$F,3,0) -> KADAVANTHRA | O20: =VLOOKUP($L20,Emp!$A:$F,4,0) -> ARENA | P20: KERALA GRAMEENA BANK | Q20: KGB | R20: IH | S20: YES | T20: =IF(_xlfn.XLOOKUP(F20,IH!Y:Y,IH!AA:AA,"")="MAPPED","MAPPED","") | U20: MSSF DISBURSED | V20: DISBURSED | W20: FEB | X20: =VLOOKUP($L20,Emp!$A:$F,5,0) -> SALMAN | Y20: =VLOOKUP($H20,ERP!$H:$AP,33,0) -> VINAY T V (C20769), | Z20: =VLOOKUP($H20,ERP!$H:$AP,34,0) -> RATHEESH.K.R
A21: 20 | B21: SOB25002331 | C21: ENQ25016635 | D21: E54905 | E21: 9261102 | F21: 40/VSL/25001431 | G21: 46090 | H21: 2567497252 | I21: AKHIL VINOD | J21: Wagon R | K21: MARUTI WAGON R ZXI+ 1.2L ISS AGS | L21: NIKESHKRISHNA P S | M21: =VLOOKUP($L21,Emp!$A:$F,2,0) -> BINOY RAJ | N21: =VLOOKUP($L21,Emp!$A:$F,3,0) -> KODUNGALLUR | O21: =VLOOKUP($L21,Emp!$A:$F,4,0) -> ARENA | P21: UNION BANK OF INDIA | Q21: UBI | R21: IH | S21: NO | T21: =IF(_xlfn.XLOOKUP(F21,IH!Y:Y,IH!AA:AA,"")="MAPPED","MAPPED","") | U21: =IFERROR(VLOOKUP(H21,IH!C:T,18,0),"") -> NO | V21: =IF(W21<>"","DISBURSED","") -> DISBURSED | W21: =IFERROR(VLOOKUP(H21,IH!C:X,14,0),"") -> 46088 | X21: =VLOOKUP($L21,Emp!$A:$F,5,0) -> JINEESH | Y21: =VLOOKUP($H21,ERP!$H:$AP,33,0) -> NIKESH KRISHNA P S (C25381), | Z21: =VLOOKUP($H21,ERP!$H:$AP,34,0) -> BINOY(KDLR)
A22: 21 | B22: SOB25002219 | C22: ENQ25015986 | D22: E55278 | E22: C988345 | F22: 40/VSL/25001427 | G22: 46090 | H22: 2567243043 | I22: BOAZ B DANIEL | J22: TOUR H3 | K22: MARUTI TOUR H3 CNG 1L 5MT | L22: RATHEESH K B | M22: =VLOOKUP($L22,Emp!$A:$F,2,0) -> PRANOOB V NAIR | N22: =VLOOKUP($L22,Emp!$A:$F,3,0) -> TRIPPUNITHURA | O22: =VLOOKUP($L22,Emp!$A:$F,4,0) -> ARENA | P22: CASH | Q22: CASH | R22: CASH | S22: NO | T22: =IF(_xlfn.XLOOKUP(F22,IH!Y:Y,IH!AA:AA,"")="MAPPED","MAPPED","") | U22: =IFERROR(VLOOKUP(H22,IH!C:T,18,0),"") | V22: =IF(W22<>"","DISBURSED","") | W22: =IFERROR(VLOOKUP(H22,IH!C:X,14,0),"") | X22: =VLOOKUP($L22,Emp!$A:$F,5,0) -> SIVAPRASAD | Y22: =VLOOKUP($H22,ERP!$H:$AP,33,0) -> RATHEESH K B, | Z22: =VLOOKUP($H22,ERP!$H:$AP,34,0) -> PRANOOB V (TPRA)
A23: 22 | B23: SOB25002323 | C23: ENQ25016633 | D23: C39303 | E23: 7934235 | F23: 40/VSL/25001426 | G23: 46090 | H23: 2567483180 | I23: NUSAIBA | J23: ERTIGA | K23: MARUTI ERTIGA SMART HYBRID VXI 1.5L 6AT | L23: RAGIL N R | M23: =VLOOKUP($L23,Emp!$A:$F,2,0) -> VIBIN I B | N23: =VLOOKUP($L23,Emp!$A:$F,3,0) -> KAIPAMANGALAM | O23: =VLOOKUP($L23,Emp!$A:$F,4,0) -> STUDIO | P23: HDFC BANK LTD | Q23: HDFC | R23: IH | S23: YES | T23: =IF(_xlfn.XLOOKUP(F23,IH!Y:Y,IH!AA:AA,"")="MAPPED","MAPPED","") | U23: =IFERROR(VLOOKUP(H23,IH!C:T,18,0),"") -> MSSF DISBURSED | V23: =IF(W23<>"","DISBURSED","") -> DISBURSED | W23: =IFERROR(VLOOKUP(H23,IH!C:X,14,0),"") -> 46087 | X23: =VLOOKUP($L23,Emp!$A:$F,5,0) -> JINEESH | Y23: =VLOOKUP($H23,ERP!$H:$AP,33,0) -> RAGIL N R(C26613), | Z23: =VLOOKUP($H23,ERP!$H:$AP,34,0) -> VIBIN I B(KPLM)
A24: 23 | B24: SOB25002273 | C24: ENQ25016288 | D24: E52994 | E24: C986807 | F24: 40/VSL/25001428 | G24: 46090 | H24: 2567354817 | I24: VINODKUMAR | J24: TOUR H3 | K24: MARUTI TOUR H3 CNG 1L 5MT | L24: SREENATH R PRABHU | M24: =VLOOKUP($L24,Emp!$A:$F,2,0) -> NOUFAL T A | N24: =VLOOKUP($L24,Emp!$A:$F,3,0) -> EDAPPALLY | O24: =VLOOKUP($L24,Emp!$A:$F,4,0) -> ARENA | P24: KERALA GRAMIN BANK | Q24: KGB | R24: IH | S24: YES | T24: =IF(_xlfn.XLOOKUP(F24,IH!Y:Y,IH!AA:AA,"")="MAPPED","MAPPED","") -> MAPPED | U24: =IFERROR(VLOOKUP(H24,IH!C:T,18,0),"") -> MSSF DISBURSED | V24: =IF(W24<>"","DISBURSED","") -> DISBURSED | W24: =IFERROR(VLOOKUP(H24,IH!C:X,14,0),"") -> 46088 | X24: =VLOOKUP($L24,Emp!$A:$F,5,0) -> SIVAPRASAD | Y24: =VLOOKUP($H24,ERP!$H:$AP,33,0) -> SREENATH R PRABHU (C23391), | Z24: =VLOOKUP($H24,ERP!$H:$AP,34,0) -> MANU SASI
A25: 24 | B25: SOB25002088 | C25: ENQ25015217 | D25: E55150 | E25: C989112 | F25: 40/VSL/25001429 | G25: 46090 | H25: 2566948355 | I25: RESMIMOL | J25: Wagon R | K25: MARUTI WAGON R LXI 1L ISS 5MT | L25: ALBIN MARTIN | M25: =VLOOKUP($L25,Emp!$A:$F,2,0) -> RATISH K R | N25: =VLOOKUP($L25,Emp!$A:$F,3,0) -> KADAVANTHRA | O25: =VLOOKUP($L25,Emp!$A:$F,4,0) -> ARENA | P25: CHOLAMANDALAM INVS.& FIN.CO.LTD | Q25: CHOLA | R25: IH | S25: YES | T25: =IF(_xlfn.XLOOKUP(F25,IH!Y:Y,IH!AA:AA,"")="MAPPED","MAPPED","") | U25: =IFERROR(VLOOKUP(H25,IH!C:T,18,0),"") -> MSSF DISBURSED | V25: =IF(W25<>"","DISBURSED","") -> DISBURSED | W25: =IFERROR(VLOOKUP(H25,IH!C:X,14,0),"") -> 46092 | X25: =VLOOKUP($L25,Emp!$A:$F,5,0) -> SALMAN | Y25: =VLOOKUP($H25,ERP!$H:$AP,33,0) -> ALBIN MARTIN (C26561), | Z25: =VLOOKUP($H25,ERP!$H:$AP,34,0) -> RATHEESH.K.R
A26: 25 | B26: SOB25001842 | C26: ENQ25014308 | D26: E56685 | E26: C990361 | F26: 40/VSL/25001425 | G26: 46090 | H26: 2566534647 | I26: BALAKRISHNAN V N | J26: Wagon R | K26: MARUTI WAGON R LXI 1L ISS 5MT | L26: SANJAY | M26: =VLOOKUP($L26,Emp!$A:$F,2,0) -> SIVAPRAKASH K S | N26: =VLOOKUP($L26,Emp!$A:$F,3,0) -> THRISSUR | O26: =VLOOKUP($L26,Emp!$A:$F,4,0) -> ARENA | P26: UNION BANK OF INDIA | Q26: UBI | R26: IH | S26: NO | T26: =IF(_xlfn.XLOOKUP(F26,IH!Y:Y,IH!AA:AA,"")="MAPPED","MAPPED","") | U26: =IFERROR(VLOOKUP(H26,IH!C:T,18,0),"") -> NO | V26: =IF(W26<>"","DISBURSED","") -> DISBURSED | W26: =IFERROR(VLOOKUP(H26,IH!C:X,14,0),"") -> 46087 | X26: =VLOOKUP($L26,Emp!$A:$F,5,0) -> SINTO | Y26: =VLOOKUP($H26,ERP!$H:$AP,33,0) -> SANJAY.M.G(C26392), | Z26: =VLOOKUP($H26,ERP!$H:$AP,34,0) -> SIVAPRAKASH K.S.(TCR)
A27: 26 | B27: SOB25000223 | C27: ENQ25001932 | D27: F86412 | E27: 4578574 | F27: 126/VSL/25000113 | G27: 46090 | H27: 2567445237 | I27: PRAMOD | J27: EECO | K27: MARUTI EECO 5 STR AC CNG 1.2L 5MT | L27: NYGIL GEORGE | M27: =VLOOKUP($L27,Emp!$A:$F,2,0) -> SIJO VARGHESE GEORGE | N27: =VLOOKUP($L27,Emp!$A:$F,3,0) -> PERUMBAVOOR | O27: =VLOOKUP($L27,Emp!$A:$F,4,0) -> ARENA | P27: CHOLAMANDALAM INVS.& FIN.CO.LTD | Q27: CHOLA | R27: IH | S27: YES | T27: =IF(_xlfn.XLOOKUP(F27,IH!Y:Y,IH!AA:AA,"")="MAPPED","MAPPED","") | U27: =IFERROR(VLOOKUP(H27,IH!C:T,18,0),"") -> MSSF DISBURSED | V27: =IF(W27<>"","DISBURSED","") -> DISBURSED | W27: =IFERROR(VLOOKUP(H27,IH!C:X,14,0),"") -> 46088 | X27: =VLOOKUP($L27,Emp!$A:$F,5,0) -> SALMAN | Y27: =VLOOKUP($H27,ERP!$H:$AP,33,0) -> NIGIL GEORGE(C23881), | Z27: =VLOOKUP($H27,ERP!$H:$AP,34,0) -> SIJO VARGHESE GEORGE (PBVR)
A28: 27 | B28: SOB25000241 | C28: ENQ25001995 | D28: F74856 | E28: 4563880 | F28: 255/VSL/25000100 | G28: 46091 | H28: 2567479764 | I28: CHANDRASEKHAR P M | J28: EECO | K28: MARUTI EECO CARGO AC CNG 1.2L 5MT | L28: SOORAJ K S | M28: =VLOOKUP($L28,Emp!$A:$F,2,0) -> ANAND K V | N28: =VLOOKUP($L28,Emp!$A:$F,3,0) -> KOLENCHERY | O28: =VLOOKUP($L28,Emp!$A:$F,4,0) -> ARENA | P28: CHOLAMANDALAM INVESTEMENT & FINANCE COMPANY LTD | Q28: CHOLA | R28: IH | S28: YES | T28: =IF(_xlfn.XLOOKUP(F28,IH!Y:Y,IH!AA:AA,"")="MAPPED","MAPPED","") -> MAPPED | U28: =IFERROR(VLOOKUP(H28,IH!C:T,18,0),"") -> MSSF DISBURSED | V28: =IF(W28<>"","DISBURSED","") -> DISBURSED | W28: =IFERROR(VLOOKUP(H28,IH!C:X,14,0),"") -> 46091 | X28: =VLOOKUP($L28,Emp!$A:$F,5,0) -> AMAL | Y28: =VLOOKUP($H28,ERP!$H:$AP,33,0) -> SOORAJ K S (C24979), | Z28: =VLOOKUP($H28,ERP!$H:$AP,34,0) -> NA
A29: 28 | B29: SOB25002352 | C29: ENQ25016732 | D29: E54628 | E29: C987895 | F29: 40/VSL/25001432 | G29: 46091 | H29: 2567527116 | I29: AKSHAY P P | J29: TOUR H3 | K29: MARUTI TOUR H3 CNG 1L 5MT | L29: JITHIN K ANAND | M29: =VLOOKUP($L29,Emp!$A:$F,2,0) -> KASI VISWANATH | N29: =VLOOKUP($L29,Emp!$A:$F,3,0) -> KAIPAMANGALAM | O29: =VLOOKUP($L29,Emp!$A:$F,4,0) -> ARENA | P29: CASH | Q29: CHOLA | R29: IH | S29: YES | T29: =IF(_xlfn.XLOOKUP(F29,IH!Y:Y,IH!AA:AA,"")="MAPPED","MAPPED","") -> MAPPED | U29: =IFERROR(VLOOKUP(H29,IH!C:T,18,0),"") -> MSSF DISBURSED | V29: =IF(W29<>"","DISBURSED","") -> DISBURSED | W29: =IFERROR(VLOOKUP(H29,IH!C:X,14,0),"") -> 46093 | X29: =VLOOKUP($L29,Emp!$A:$F,5,0) -> JINEESH | Y29: =VLOOKUP($H29,ERP!$H:$AP,33,0) -> JITHIN K ANAND(C26246), | Z29: =VLOOKUP($H29,ERP!$H:$AP,34,0) -> KASI VISWANATH K M
A30: 29 | B30: SOB25002280 | C30: ENQ25016312 | D30: E55597 | E30: 1428539 | F30: 40/VSL/25001433 | G30: 46091 | H30: 2567368472 | I30: SUNIL CHANDRAN P | J30: TOUR H3 | K30: MARUTI TOUR H3 CNG 1L 5MT | L30: VISHNUDAS P D | M30: =VLOOKUP($L30,Emp!$A:$F,2,0) -> SIVAPRAKASH K S | N30: =VLOOKUP($L30,Emp!$A:$F,3,0) -> THRISSUR | O30: =VLOOKUP($L30,Emp!$A:$F,4,0) -> ARENA | P30: TATA CAPITAL LIMITED | Q30: TATA | R30: IH | S30: YES | T30: =IF(_xlfn.XLOOKUP(F30,IH!Y:Y,IH!AA:AA,"")="MAPPED","MAPPED","") -> MAPPED | U30: =IFERROR(VLOOKUP(H30,IH!C:T,18,0),"") -> MSSF DISBURSED | V30: =IF(W30<>"","DISBURSED","") -> DISBURSED | W30: =IFERROR(VLOOKUP(H30,IH!C:X,14,0),"") -> 46092 | X30: =VLOOKUP($L30,Emp!$A:$F,5,0) -> SINTO | Y30: =VLOOKUP($H30,ERP!$H:$AP,33,0) -> NA | Z30: =VLOOKUP($H30,ERP!$H:$AP,34,0) -> NA
A31: 30 | B31: SOB25000303 | C31: ENQ25002131 | D31: F83679 | E31: 4575397 | F31: 77/VSL/25000160 | G31: 46091 | H31: 2566648961 | I31: RAJESH P S | J31: EECO | K31: MARUTI EECO 5 STR AC CNG 1.2L 5MT | L31: ANANDA KRISHNAN P A | M31: =VLOOKUP($L31,Emp!$A:$F,2,0) -> SMITHIN P S | N31: =VLOOKUP($L31,Emp!$A:$F,3,0) -> KAIPAMANGALAM | O31: =VLOOKUP($L31,Emp!$A:$F,4,0) -> ARENA | P31: ICICI BANK LTD | Q31: ICICI | R31: IH | S31: YES | T31: MAPPED | U31: MSSF DISBURSED | V31: DISBURSED | W31: FEB | X31: =VLOOKUP($L31,Emp!$A:$F,5,0) -> JINEESH | Y31: =VLOOKUP($H31,ERP!$H:$AP,33,0) -> ANADAKRISHANAN P A (C25203), | Z31: =VLOOKUP($H31,ERP!$H:$AP,34,0) -> SMITHIN (KPLM)
A32: 31 | B32: SOB25000316 | C32: ENQ25002621 | D32: E46252 | E32: 9259943 | F32: 88/VSL/25000178 | G32: 46091 | H32: 2566876238 | I32: ELDHO ZACHARIA | J32: Wagon R | K32: MARUTI WAGON R ZXI+ 1.2L ISS 5MT | L32: SAJIN T S | M32: =VLOOKUP($L32,Emp!$A:$F,2,0) -> ARUN BABU | N32: =VLOOKUP($L32,Emp!$A:$F,3,0) -> KOOTHATTUKULAM | O32: =VLOOKUP($L32,Emp!$A:$F,4,0) -> ARENA | P32: CASH | Q32: CASH | R32: CASH | S32: NO | T32: =IF(_xlfn.XLOOKUP(F32,IH!Y:Y,IH!AA:AA,"")="MAPPED","MAPPED","") | U32: =IFERROR(VLOOKUP(H32,IH!C:T,18,0),"") | V32: =IF(W32<>"","DISBURSED","") | W32: =IFERROR(VLOOKUP(H32,IH!C:X,14,0),"") | X32: =VLOOKUP($L32,Emp!$A:$F,5,0) -> AMAL | Y32: =VLOOKUP($H32,ERP!$H:$AP,33,0) -> SAJIN T.S.(C20798), | Z32: =VLOOKUP($H32,ERP!$H:$AP,34,0) -> ARUN BABU(KTLM)
A33: 32 | B33: SOB25002356 | C33: ENQ25016736 | D33: 472765 | E33: C983297 | F33: 40/VSL/25001434 | G33: 46092 | H33: 2567529834 | I33: BONY | J33: ALTO K10 | K33: MARUTI ALTO K10 VXI 1L AGS | L33: ANANDA KRISHNAN P A | M33: =VLOOKUP($L33,Emp!$A:$F,2,0) -> SMITHIN P S | N33: =VLOOKUP($L33,Emp!$A:$F,3,0) -> KAIPAMANGALAM | O33: =VLOOKUP($L33,Emp!$A:$F,4,0) -> ARENA | P33: SREERAM FINANCE | Q33: SHRIRAM | R33: SELF | S33: NO | T33: =IF(_xlfn.XLOOKUP(F33,IH!Y:Y,IH!AA:AA,"")="MAPPED","MAPPED","") | U33: =IFERROR(VLOOKUP(H33,IH!C:T,18,0),"") | V33: =IF(W33<>"","DISBURSED","") | W33: =IFERROR(VLOOKUP(H33,IH!C:X,14,0),"") | X33: =VLOOKUP($L33,Emp!$A:$F,5,0) -> JINEESH | Y33: =VLOOKUP($H33,ERP!$H:$AP,33,0) -> ANADAKRISHANAN P A (C25203), | Z33: =VLOOKUP($H33,ERP!$H:$AP,34,0) -> SMITHIN (KPLM)
A34: 33 | B34: SOB25002135 | C34: ENQ25015459 | D34: 413173 | E34: F312038 | F34: 40/VSL/25001435 | G34: 46092 | H34: 2567045600 | I34: JAFAR KHAN | J34: TOUR S | K34: MARUTI TOUR S CNG 1.2L 5MT | L34: LANEESH A S | M34: =VLOOKUP($L34,Emp!$A:$F,2,0) -> MANU SASI | N34: =VLOOKUP($L34,Emp!$A:$F,3,0) -> EDAPPALLY | O34: =VLOOKUP($L34,Emp!$A:$F,4,0) -> ARENA | P34: KERALA GRAMIN BANK | Q34: KGB | R34: IH | S34: NO | T34: =IF(_xlfn.XLOOKUP(F34,IH!Y:Y,IH!AA:AA,"")="MAPPED","MAPPED","") | U34: =IFERROR(VLOOKUP(H34,IH!C:T,18,0),"") -> MSSF LOGIN | V34: =IF(W34<>"","DISBURSED","") -> DISBURSED | W34: =IFERROR(VLOOKUP(H34,IH!C:X,14,0),"") -> 46093 | X34: =VLOOKUP($L34,Emp!$A:$F,5,0) -> SIVAPRASAD | Y34: =VLOOKUP($H34,ERP!$H:$AP,33,0) -> LANEESH A S(C21174), Mr. | Z34: =VLOOKUP($H34,ERP!$H:$AP,34,0) -> MANU SASI
A35: 34 | B35: SOB25002229 | C35: ENQ25016047 | D35: E55244 | E35: C988964 | F35: 40/VSL/25001437 | G35: 46092 | H35: 2567549960 | I35: BENZIR DUTT A S | J35: Wagon R | K35: MARUTI WAGON R LXI 1L ISS 5MT | L35: RATHEESH K B | M35: =VLOOKUP($L35,Emp!$A:$F,2,0) -> PRANOOB V NAIR | N35: =VLOOKUP($L35,Emp!$A:$F,3,0) -> TRIPPUNITHURA | O35: =VLOOKUP($L35,Emp!$A:$F,4,0) -> ARENA | P35: HDFC BANK LTD | Q35: HDFC | R35: IH | S35: YES | T35: =IF(_xlfn.XLOOKUP(F35,IH!Y:Y,IH!AA:AA,"")="MAPPED","MAPPED","") -> MAPPED | U35: =IFERROR(VLOOKUP(H35,IH!C:T,18,0),"") -> MSSF DISBURSED | V35: =IF(W35<>"","DISBURSED","") -> DISBURSED | W35: =IFERROR(VLOOKUP(H35,IH!C:X,14,0),"") -> 46091 | X35: =VLOOKUP($L35,Emp!$A:$F,5,0) -> SIVAPRASAD | Y35: =VLOOKUP($H35,ERP!$H:$AP,33,0) -> RATHEESH K B, | Z35: =VLOOKUP($H35,ERP!$H:$AP,34,0) -> PRANOOB V (TPRA)
A36: 35 | B36: SOB25000232 | C36: ENQ25002424 | D36: E44019 | E36: 9259408 | F36: 28/VSL/25000111 | G36: 46093 | H36: 2567479082 | I36: RAHUL C H | J36: Wagon R | K36: MARUTI WAGON R ZXI+ 1.2L ISS 5MT | L36: RISHAD K S | M36: =VLOOKUP($L36,Emp!$A:$F,2,0) -> BHAGIESH | N36: =VLOOKUP($L36,Emp!$A:$F,3,0) -> CHAVAKKAD | O36: =VLOOKUP($L36,Emp!$A:$F,4,0) -> ARENA | P36: INDUSIND BANK LTD | Q36: IBL | R36: IH | S36: YES | T36: =IF(_xlfn.XLOOKUP(F36,IH!Y:Y,IH!AA:AA,"")="MAPPED","MAPPED","") -> MAPPED | U36: =IFERROR(VLOOKUP(H36,IH!C:T,18,0),"") -> MSSF DISBURSED | V36: =IF(W36<>"","DISBURSED","") -> DISBURSED | W36: =IFERROR(VLOOKUP(H36,IH!C:X,14,0),"") -> 46092 | X36: =VLOOKUP($L36,Emp!$A:$F,5,0) -> SINTO | Y36: =VLOOKUP($H36,ERP!$H:$AP,33,0) -> RISHAD K.S | Z36: =VLOOKUP($H36,ERP!$H:$AP,34,0) -> NA
A37: 36 | B37: SOB25002372 | C37: ENQ25016795 | D37: 410146 | E37: F309183 | F37: 40/VSL/25001438 | G37: 46093 | H37: 2567549813 | I37: DIVYA VALSAN | J37: TOUR S | K37: MARUTI TOUR S CNG 1.2L 5MT | L37: JAYAKRISHNAN K V | M37: =VLOOKUP($L37,Emp!$A:$F,2,0) -> BINOY RAJ | N37: =VLOOKUP($L37,Emp!$A:$F,3,0) -> KODUNGALLUR | O37: =VLOOKUP($L37,Emp!$A:$F,4,0) -> ARENA | P37: SHRIRAM FINANCE LTD | Q37: SHRIRAM | R37: SELF | S37: NO | T37: =IF(_xlfn.XLOOKUP(F37,IH!Y:Y,IH!AA:AA,"")="MAPPED","MAPPED","") | U37: =IFERROR(VLOOKUP(H37,IH!C:T,18,0),"") | V37: =IF(W37<>"","DISBURSED","") | W37: =IFERROR(VLOOKUP(H37,IH!C:X,14,0),"") | X37: =VLOOKUP($L37,Emp!$A:$F,5,0) -> JINEESH | Y37: =VLOOKUP($H37,ERP!$H:$AP,33,0) -> JAYAKRISHNAN K V (C25293), | Z37: =VLOOKUP($H37,ERP!$H:$AP,34,0) -> LINISH.T.K
A38: 37 | B38: SOB25001818 | C38: ENQ25014169 | D38: 412106 | E38: F310861 | F38: 40/VSL/25001439 | G38: 46093 | H38: 2566498468 | I38: SABIL M S | J38: TOUR S | K38: MARUTI TOUR S CNG 1.2L 5MT | L38: SUJEESH P G | M38: =VLOOKUP($L38,Emp!$A:$F,2,0) -> SIVAPRAKASH K S | N38: =VLOOKUP($L38,Emp!$A:$F,3,0) -> THRISSUR | O38: =VLOOKUP($L38,Emp!$A:$F,4,0) -> ARENA | P38: KERALA GRAMEENA BANK | Q38: KGB | R38: IH | S38: YES | T38: =IF(_xlfn.XLOOKUP(F38,IH!Y:Y,IH!AA:AA,"")="MAPPED","MAPPED","") | U38: =IFERROR(VLOOKUP(H38,IH!C:T,18,0),"") -> NO | V38: =IF(W38<>"","DISBURSED","") -> DISBURSED | W38: =IFERROR(VLOOKUP(H38,IH!C:X,14,0),"") -> 46093 | X38: =VLOOKUP($L38,Emp!$A:$F,5,0) -> SINTO | Y38: =VLOOKUP($H38,ERP!$H:$AP,33,0) -> SUJEESH P G (C24887), | Z38: =VLOOKUP($H38,ERP!$H:$AP,34,0) -> RAJEEV (THCR)
A39: 38 | B39: SOB25002358 | C39: ENQ25016764 | D39: 777144 | E39: K124825 | F39: 40/VSL/25001440 | G39: 46093 | H39: 2567538185 | I39: JOSE T D | J39: BREZZA | K39: MARUTI BREZZA SMART HYBRID VXI 1.5L 6AT | L39: SUDHEESH | M39: =VLOOKUP($L39,Emp!$A:$F,2,0) -> SIVAPRAKASH K S | N39: =VLOOKUP($L39,Emp!$A:$F,3,0) -> THRISSUR | O39: =VLOOKUP($L39,Emp!$A:$F,4,0) -> ARENA | P39: CASH | Q39: CASH | R39: CASH | S39: NO | T39: =IF(_xlfn.XLOOKUP(F39,IH!Y:Y,IH!AA:AA,"")="MAPPED","MAPPED","") | U39: =IFERROR(VLOOKUP(H39,IH!C:T,18,0),"") | V39: =IF(W39<>"","DISBURSED","") | W39: =IFERROR(VLOOKUP(H39,IH!C:X,14,0),"") | X39: =VLOOKUP($L39,Emp!$A:$F,5,0) -> SINTO | Y39: =VLOOKUP($H39,ERP!$H:$AP,33,0) -> SUDHEESH.K.S(C26156), | Z39: =VLOOKUP($H39,ERP!$H:$AP,34,0) -> SIVAPRAKASH K.S.(TCR)
A40: 39 | B40: SOB25002146 | C40: ENQ25014531 | D40: 470701 | E40: 1424818 | F40: 40/VSL/25001441 | G40: 46093 | H40: 2567077782 | I40: REETHA MAGDALINE | J40: ALTO K10 | K40: MARUTI ALTO K10 VXI 1L 5MT | L40: MUHAMMED ABOOBACKER | M40: =VLOOKUP($L40,Emp!$A:$F,2,0) -> JAYESH | N40: =VLOOKUP($L40,Emp!$A:$F,3,0) -> ALUVA | O40: =VLOOKUP($L40,Emp!$A:$F,4,0) -> ARENA | P40: BANK OF BARODA | Q40: BOB | R40: SELF | S40: NO | T40: =IF(_xlfn.XLOOKUP(F40,IH!Y:Y,IH!AA:AA,"")="MAPPED","MAPPED","") | U40: =IFERROR(VLOOKUP(H40,IH!C:T,18,0),"") | V40: =IF(W40<>"","DISBURSED","") | W40: =IFERROR(VLOOKUP(H40,IH!C:X,14,0),"") | X40: =VLOOKUP($L40,Emp!$A:$F,5,0) -> SALMAN | Y40: =VLOOKUP($H40,ERP!$H:$AP,33,0) -> MUHAMMED ABOOBACKER(C26570), | Z40: =VLOOKUP($H40,ERP!$H:$AP,34,0) -> JAYESH (ALUVA)
A41: 40 | B41: SOB25002183 | C41: ENQ25015810 | D41: C39385 | E41: A019215 | F41: 40/VSL/25001442 | G41: 46093 | H41: 2567564981 | I41: MATILDA KING GEORGE TANNIPULLY | J41: TOUR M | K41: MARUTI TOUR M CNG 1.5L 5MT | L41: MANU JOY | M41: =VLOOKUP($L41,Emp!$A:$F,2,0) -> MANU SASI | N41: =VLOOKUP($L41,Emp!$A:$F,3,0) -> EDAPPALLY | O41: =VLOOKUP($L41,Emp!$A:$F,4,0) -> ARENA | P41: CASH | Q41: CASH | R41: CASH | S41: NO | T41: =IF(_xlfn.XLOOKUP(F41,IH!Y:Y,IH!AA:AA,"")="MAPPED","MAPPED","") | U41: =IFERROR(VLOOKUP(H41,IH!C:T,18,0),"") | V41: =IF(W41<>"","DISBURSED","") | W41: =IFERROR(VLOOKUP(H41,IH!C:X,14,0),"") | X41: =VLOOKUP($L41,Emp!$A:$F,5,0) -> SIVAPRASAD | Y41: =VLOOKUP($H41,ERP!$H:$AP,33,0) -> MANU JOY (C22591), | Z41: =VLOOKUP($H41,ERP!$H:$AP,34,0) -> MANU SASI
A42: 41 | B42: SOB25002344 | C42: ENQ25016703 | D42: F97898 | E42: 4593757 | F42: 40/VSL/25001443 | G42: 46093 | H42: 2567515064 | I42: SANTHOSHKUMAR E K | J42: EECO | K42: MARUTI EECO 5 STR AC CNG 1.2L 5MT | L42: RISHAD K S | M42: =VLOOKUP($L42,Emp!$A:$F,2,0) -> BHAGIESH | N42: =VLOOKUP($L42,Emp!$A:$F,3,0) -> CHAVAKKAD | O42: =VLOOKUP($L42,Emp!$A:$F,4,0) -> ARENA | P42: KERALA GRAMEENA BANK | Q42: KGB | R42: IH | S42: YES | T42: =IF(_xlfn.XLOOKUP(F42,IH!Y:Y,IH!AA:AA,"")="MAPPED","MAPPED","") | U42: =IFERROR(VLOOKUP(H42,IH!C:T,18,0),"") -> NO | V42: =IF(W42<>"","DISBURSED","") -> DISBURSED | W42: =IFERROR(VLOOKUP(H42,IH!C:X,14,0),"") -> 46087 | X42: =VLOOKUP($L42,Emp!$A:$F,5,0) -> SINTO | Y42: =VLOOKUP($H42,ERP!$H:$AP,33,0) -> RISHAD K.S | Z42: =VLOOKUP($H42,ERP!$H:$AP,34,0) -> NA
A43: 42 | B43: SOB25002315 | C43: ENQ25016583 | D43: 165583 | E43: K111826 | F43: 40/VSL/25001444 | G43: 46093 | H43: 2567565813 | I43: KALLAYIL VISWANATHAN SANJITH | J43: VICTORIS | K43: MARUTI VICTORIS LXI 1.5L 5MT | L43: SUJEESH P G | M43: =VLOOKUP($L43,Emp!$A:$F,2,0) -> SIVAPRAKASH K S | N43: =VLOOKUP($L43,Emp!$A:$F,3,0) -> THRISSUR | O43: =VLOOKUP($L43,Emp!$A:$F,4,0) -> ARENA | P43: FEDERAL BANK LTD. | Q43: FBL | R43: SELF | S43: NO | T43: =IF(_xlfn.XLOOKUP(F43,IH!Y:Y,IH!AA:AA,"")="MAPPED","MAPPED","") | U43: =IFERROR(VLOOKUP(H43,IH!C:T,18,0),"") | V43: =IF(W43<>"","DISBURSED","") | W43: =IFERROR(VLOOKUP(H43,IH!C:X,14,0),"") | X43: =VLOOKUP($L43,Emp!$A:$F,5,0) -> SINTO | Y43: =VLOOKUP($H43,ERP!$H:$AP,33,0) -> SUJEESH P G (C24887), | Z43: =VLOOKUP($H43,ERP!$H:$AP,34,0) -> RAJEEV (THCR)
A44: 43 | B44: SOB25000297 | C44: ENQ25002077 | D44: F97512 | E44: 4593164 | F44: 77/VSL/25000161 | G44: 46093 | H44: 2567561397 | I44: A R MANIKANDAN | J44: TOUR V | K44: MARUTI TOUR V 5 STR AC CNG 1.2L 5MT | L44: JITHIN K ANAND | M44: =VLOOKUP($L44,Emp!$A:$F,2,0) -> KASI VISWANATH | N44: =VLOOKUP($L44,Emp!$A:$F,3,0) -> KAIPAMANGALAM | O44: =VLOOKUP($L44,Emp!$A:$F,4,0) -> ARENA | P44: KERALA GRAMEENA BANK | Q44: KGB | R44: IH | S44: YES | T44: =IF(_xlfn.XLOOKUP(F44,IH!Y:Y,IH!AA:AA,"")="MAPPED","MAPPED","") | U44: =IFERROR(VLOOKUP(H44,IH!C:T,18,0),"") -> NO | V44: =IF(W44<>"","DISBURSED","") -> DISBURSED | W44: =IFERROR(VLOOKUP(H44,IH!C:X,14,0),"") -> 46092 | X44: =VLOOKUP($L44,Emp!$A:$F,5,0) -> JINEESH | Y44: =VLOOKUP($H44,ERP!$H:$AP,33,0) -> JITHIN K ANAND(C26246), | Z44: =VLOOKUP($H44,ERP!$H:$AP,34,0) -> KASI VISWANATH K M
A45: 44 | B45: SOB25000207 | C45: ENQ25002093 | D45: 158633 | E45: K103193 | F45: 118/VSL25000100 | G45: 46094 | H45: 2567533245 | I45: SHAJU P C | J45: VICTORIS | K45: MARUTI VICTORIS ZXI+ 1.5L 6AT | L45: ALFIYA ASHRAF | M45: =VLOOKUP($L45,Emp!$A:$F,2,0) -> JESTIN UTHUP JOHN | N45: =VLOOKUP($L45,Emp!$A:$F,3,0) -> PIRAVOM | O45: =VLOOKUP($L45,Emp!$A:$F,4,0) -> ARENA | P45: BAJAJ FINANCE LTD | Q45: BAJAJ | R45: IH | S45: YES | T45: =IF(_xlfn.XLOOKUP(F45,IH!Y:Y,IH!AA:AA,"")="MAPPED","MAPPED","") | U45: =IFERROR(VLOOKUP(H45,IH!C:T,18,0),"") -> NO | V45: =IF(W45<>"","DISBURSED","") -> DISBURSED | W45: =IFERROR(VLOOKUP(H45,IH!C:X,14,0),"") -> 46092 | X45: =VLOOKUP($L45,Emp!$A:$F,5,0) -> AMAL | Y45: =VLOOKUP($H45,ERP!$H:$AP,33,0) -> ALFIYA ASHRAF (C26586), | Z45: =VLOOKUP($H45,ERP!$H:$AP,34,0) -> JUSTIN UTHUP JOHN (PRVM)
A46: 45 | B46: SOB25000229 | C46: ENQ25001972 | D46: E41298 | E46: 9259013 | F46: 126/VSL/25000114 | G46: 46094 | H46: 2567528747 | I46: USHAKUMARI K P | J46: Wagon R | K46: MARUTI WAGON R ZXI 1.2L ISS AGS | L46: JINTO THOMAS | M46: =VLOOKUP($L46,Emp!$A:$F,2,0) -> SIJO VARGHESE GEORGE | N46: =VLOOKUP($L46,Emp!$A:$F,3,0) -> PERUMBAVOOR | O46: =VLOOKUP($L46,Emp!$A:$F,4,0) -> ARENA | P46: CASH | Q46: CASH | R46: CASH | S46: NO | T46: =IF(_xlfn.XLOOKUP(F46,IH!Y:Y,IH!AA:AA,"")="MAPPED","MAPPED","") | U46: =IFERROR(VLOOKUP(H46,IH!C:T,18,0),"") | V46: =IF(W46<>"","DISBURSED","") | W46: =IFERROR(VLOOKUP(H46,IH!C:X,14,0),"") | X46: =VLOOKUP($L46,Emp!$A:$F,5,0) -> SALMAN | Y46: =VLOOKUP($H46,ERP!$H:$AP,33,0) -> NA | Z46: =VLOOKUP($H46,ERP!$H:$AP,34,0) -> NA
A47: 46 | B47: SOB25000181 | C47: ENQ25001370 | D47: E55208 | E47: C988576 | F47: 27/VSL/25000072 | G47: 46094 | H47: 2567423729 | I47: MANIKANDAN N A | J47: TOUR H3 | K47: MARUTI TOUR H3 CNG 1L 5MT | L47: CHANCHAL K G | M47: =VLOOKUP($L47,Emp!$A:$F,2,0) -> REJIM GEORGE | N47: =VLOOKUP($L47,Emp!$A:$F,3,0) -> FORTKOCHI | O47: =VLOOKUP($L47,Emp!$A:$F,4,0) -> ARENA | P47: CASH | Q47: CASH | R47: CASH | S47: NO | T47: =IF(_xlfn.XLOOKUP(F47,IH!Y:Y,IH!AA:AA,"")="MAPPED","MAPPED","") | U47: =IFERROR(VLOOKUP(H47,IH!C:T,18,0),"") | V47: =IF(W47<>"","DISBURSED","") | W47: =IFERROR(VLOOKUP(H47,IH!C:X,14,0),"") | X47: =VLOOKUP($L47,Emp!$A:$F,5,0) -> SIVAPRASAD | Y47: =VLOOKUP($H47,ERP!$H:$AP,33,0) -> NA | Z47: =VLOOKUP($H47,ERP!$H:$AP,34,0) -> NA
A48: 47 | B48: SOB25002341 | C48: ENQ25016679 | D48: 248442 | E48: F148013 | F48: 40/VSL/25001446 | G48: 46094 | H48: 2567505758 | I48: RAVI NARAYAN NAIR | J48: Dzire | K48: MARUTI DZIRE ZXI+ 1.2L ISS 5MT | L48: JERRIN ROY | M48: =VLOOKUP($L48,Emp!$A:$F,2,0) -> PRANOOB V NAIR | N48: =VLOOKUP($L48,Emp!$A:$F,3,0) -> TRIPPUNITHURA | O48: =VLOOKUP($L48,Emp!$A:$F,4,0) -> ARENA | P48: CASH | Q48: CASH | R48: CASH | S48: NO | T48: =IF(_xlfn.XLOOKUP(F48,IH!Y:Y,IH!AA:AA,"")="MAPPED","MAPPED","") | U48: =IFERROR(VLOOKUP(H48,IH!C:T,18,0),"") | V48: =IF(W48<>"","DISBURSED","") | W48: =IFERROR(VLOOKUP(H48,IH!C:X,14,0),"") | X48: =VLOOKUP($L48,Emp!$A:$F,5,0) -> SIVAPRASAD | Y48: =VLOOKUP($H48,ERP!$H:$AP,33,0) -> JERRIN ROY (C22200), | Z48: =VLOOKUP($H48,ERP!$H:$AP,34,0) -> PRANOOB V (TPRA)
A49: 48 | B49: SOB25002364 | C49: ENQ25016777 | D49: E56405 | E49: F083513 | F49: 40/VSL/25001447 | G49: 46094 | H49: 2567544011 | I49: SREELAKSHMI K C | J49: Wagon R | K49: MARUTI WAGON R LXI 1L ISS 5MT | L49: RAGIL N R | M49: =VLOOKUP($L49,Emp!$A:$F,2,0) -> VIBIN I B | N49: =VLOOKUP($L49,Emp!$A:$F,3,0) -> KAIPAMANGALAM | O49: =VLOOKUP($L49,Emp!$A:$F,4,0) -> STUDIO | P49: HDFC BANK LTD | Q49: HDFC | R49: IH | S49: YES | T49: =IF(_xlfn.XLOOKUP(F49,IH!Y:Y,IH!AA:AA,"")="MAPPED","MAPPED","") | U49: =IFERROR(VLOOKUP(H49,IH!C:T,18,0),"") -> MSSF DISBURSED | V49: =IF(W49<>"","DISBURSED","") -> DISBURSED | W49: =IFERROR(VLOOKUP(H49,IH!C:X,14,0),"") -> 46093 | X49: =VLOOKUP($L49,Emp!$A:$F,5,0) -> JINEESH | Y49: =VLOOKUP($H49,ERP!$H:$AP,33,0) -> RAGIL N R(C26613), | Z49: =VLOOKUP($H49,ERP!$H:$AP,34,0) -> VIBIN I B(KPLM)
A50: 49 | B50: SOB25002359 | C50: ENQ25016769 | D50: 412967 | E50: F312297 | F50: 40/VSL/25001448 | G50: 46094 | H50: 2567540924 | I50: M N JAYAN | J50: TOUR S | K50: MARUTI TOUR S CNG 1.2L 5MT | L50: JITHIN K ANAND | M50: =VLOOKUP($L50,Emp!$A:$F,2,0) -> KASI VISWANATH | N50: =VLOOKUP($L50,Emp!$A:$F,3,0) -> KAIPAMANGALAM | O50: =VLOOKUP($L50,Emp!$A:$F,4,0) -> ARENA | P50: CASH | Q50: CASH | R50: CASH | S50: NO | T50: =IF(_xlfn.XLOOKUP(F50,IH!Y:Y,IH!AA:AA,"")="MAPPED","MAPPED","") | U50: =IFERROR(VLOOKUP(H50,IH!C:T,18,0),"") | V50: =IF(W50<>"","DISBURSED","") | W50: =IFERROR(VLOOKUP(H50,IH!C:X,14,0),"") | X50: =VLOOKUP($L50,Emp!$A:$F,5,0) -> JINEESH | Y50: =VLOOKUP($H50,ERP!$H:$AP,33,0) -> JITHIN K ANAND(C26246), | Z50: =VLOOKUP($H50,ERP!$H:$AP,34,0) -> KASI VISWANATH K M
A51: 50 | B51: SOB25002383 | C51: ENQ25016840 | D51: 539279 | E51: 1434030 | F51: 40/VSL/25001449 | G51: 46094 | H51: 2567570167 | I51: SHEEBA OOMMEN | J51: SWIFT | K51: MARUTI SWIFT VXI 1.2L ISS AGS | L51: SOORAJ K S | M51: =VLOOKUP($L51,Emp!$A:$F,2,0) -> ANAND K V | N51: =VLOOKUP($L51,Emp!$A:$F,3,0) -> KOLENCHERY | O51: =VLOOKUP($L51,Emp!$A:$F,4,0) -> ARENA | P51: HDFC BANK LTD | Q51: HDFC | R51: SELF | S51: NO | T51: =IF(_xlfn.XLOOKUP(F51,IH!Y:Y,IH!AA:AA,"")="MAPPED","MAPPED","") | U51: =IFERROR(VLOOKUP(H51,IH!C:T,18,0),"") | V51: =IF(W51<>"","DISBURSED","") | W51: =IFERROR(VLOOKUP(H51,IH!C:X,14,0),"") | X51: =VLOOKUP($L51,Emp!$A:$F,5,0) -> AMAL | Y51: =VLOOKUP($H51,ERP!$H:$AP,33,0) -> SOORAJ K S (C24979), | Z51: =VLOOKUP($H51,ERP!$H:$AP,34,0) -> NA
A52: 51 | B52: SOB25002347 | C52: ENQ25016716 | D52: 537738 | E52: 1432481 | F52: 40/VSL/25001450 | G52: 46094 | H52: 2567518660 | I52: SAIFULLA PUTHIYAVEETTIL KOTTUPARAMBIL | J52: SWIFT | K52: MARUTI SWIFT VXI 1.2L ISS 5MT | L52: RISHAD K S | M52: =VLOOKUP($L52,Emp!$A:$F,2,0) -> BHAGIESH | N52: =VLOOKUP($L52,Emp!$A:$F,3,0) -> CHAVAKKAD | O52: =VLOOKUP($L52,Emp!$A:$F,4,0) -> ARENA | P52: CASH | Q52: CASH | R52: CASH | S52: NO | T52: =IF(_xlfn.XLOOKUP(F52,IH!Y:Y,IH!AA:AA,"")="MAPPED","MAPPED","") | U52: =IFERROR(VLOOKUP(H52,IH!C:T,18,0),"") | V52: =IF(W52<>"","DISBURSED","") | W52: =IFERROR(VLOOKUP(H52,IH!C:X,14,0),"") | X52: =VLOOKUP($L52,Emp!$A:$F,5,0) -> SINTO | Y52: =VLOOKUP($H52,ERP!$H:$AP,33,0) -> RISHAD K.S | Z52: =VLOOKUP($H52,ERP!$H:$AP,34,0) -> NA
A53: 52 | B53: SOB25002236 | C53: ENQ25016106 | D53: E55239 | E53: 1428245 | F53: 40/VSL/25001451 | G53: 46094 | H53: 2567274675 | I53: MIDHUN SURESH | J53: TOUR H3 | K53: MARUTI TOUR H3 CNG 1L 5MT | L53: LANEESH A S | M53: =VLOOKUP($L53,Emp!$A:$F,2,0) -> MANU SASI | N53: =VLOOKUP($L53,Emp!$A:$F,3,0) -> EDAPPALLY | O53: =VLOOKUP($L53,Emp!$A:$F,4,0) -> ARENA | P53: KERALA GRAMIN BANK | Q53: KGB | R53: IH | S53: YES | T53: =IF(_xlfn.XLOOKUP(F53,IH!Y:Y,IH!AA:AA,"")="MAPPED","MAPPED","") -> MAPPED | U53: =IFERROR(VLOOKUP(H53,IH!C:T,18,0),"") -> MSSF DISBURSED | V53: =IF(W53<>"","DISBURSED","") -> DISBURSED | W53: =IFERROR(VLOOKUP(H53,IH!C:X,14,0),"") -> 46091 | X53: =VLOOKUP($L53,Emp!$A:$F,5,0) -> SIVAPRASAD | Y53: =VLOOKUP($H53,ERP!$H:$AP,33,0) -> LANEESH A S(C21174), Mr. | Z53: =VLOOKUP($H53,ERP!$H:$AP,34,0) -> MANU SASI
A54: 53 | B54: SOB25002129 | C54: ENQ25015423 | D54: E58249 | E54: 1430949 | F54: 40/VSL/25001452 | G54: 46094 | H54: 2567029223 | I54: MUHAMMED FARIS | J54: TOUR H3 | K54: MARUTI TOUR H3 CNG 1L 5MT | L54: SANJAY | M54: =VLOOKUP($L54,Emp!$A:$F,2,0) -> SIVAPRAKASH K S | N54: =VLOOKUP($L54,Emp!$A:$F,3,0) -> THRISSUR | O54: =VLOOKUP($L54,Emp!$A:$F,4,0) -> ARENA | P54: CASH | Q54: CASH | R54: CASH | S54: NO | T54: =IF(_xlfn.XLOOKUP(F54,IH!Y:Y,IH!AA:AA,"")="MAPPED","MAPPED","") | U54: =IFERROR(VLOOKUP(H54,IH!C:T,18,0),"") | V54: =IF(W54<>"","DISBURSED","") | W54: =IFERROR(VLOOKUP(H54,IH!C:X,14,0),"") | X54: =VLOOKUP($L54,Emp!$A:$F,5,0) -> SINTO | Y54: =VLOOKUP($H54,ERP!$H:$AP,33,0) -> SANJAY.M.G(C26392), | Z54: =VLOOKUP($H54,ERP!$H:$AP,34,0) -> SIVAPRAKASH K.S.(TCR)
A55: 54 | B55: SOB25002354 | C55: ENQ25016738 | D55: E55086 | E55: C988969 | F55: 40/VSL/25001453 | G55: 46094 | H55: 2567530237 | I55: BIBIN BABY | J55: Wagon R | K55: MARUTI WAGON R LXI 1L ISS 5MT | L55: ELSON JACOB | M55: =VLOOKUP($L55,Emp!$A:$F,2,0) -> ANAND K V | N55: =VLOOKUP($L55,Emp!$A:$F,3,0) -> KOLENCHERY | O55: =VLOOKUP($L55,Emp!$A:$F,4,0) -> ARENA | P55: BAJAJ FINANCE LIMITED | Q55: BAJAJ | R55: IH | S55: YES | T55: =IF(_xlfn.XLOOKUP(F55,IH!Y:Y,IH!AA:AA,"")="MAPPED","MAPPED","") | U55: =IFERROR(VLOOKUP(H55,IH!C:T,18,0),"") -> NO | V55: =IF(W55<>"","DISBURSED","") -> DISBURSED | W55: =IFERROR(VLOOKUP(H55,IH!C:X,14,0),"") -> 46097 | X55: =VLOOKUP($L55,Emp!$A:$F,5,0) -> AMAL | Y55: =VLOOKUP($H55,ERP!$H:$AP,33,0) -> NA | Z55: =VLOOKUP($H55,ERP!$H:$AP,34,0) -> NA
A56: 55 | B56: SOB25002249 | C56: ENQ25016207 | D56: C25648 | E56: A002514 | F56: 40/VSL/25001454 | G56: 46094 | H56: 2567319592 | I56: MITHUN T U | J56: ERTIGA | K56: MARUTI ERTIGA VXI CNG 1.5L 5MT | L56: MANU JOY | M56: =VLOOKUP($L56,Emp!$A:$F,2,0) -> MANU SASI | N56: =VLOOKUP($L56,Emp!$A:$F,3,0) -> EDAPPALLY | O56: =VLOOKUP($L56,Emp!$A:$F,4,0) -> ARENA | P56: CASH | Q56: CASH | R56: CASH | S56: NO | T56: =IF(_xlfn.XLOOKUP(F56,IH!Y:Y,IH!AA:AA,"")="MAPPED","MAPPED","") | U56: =IFERROR(VLOOKUP(H56,IH!C:T,18,0),"") | V56: =IF(W56<>"","DISBURSED","") | W56: =IFERROR(VLOOKUP(H56,IH!C:X,14,0),"") | X56: =VLOOKUP($L56,Emp!$A:$F,5,0) -> SIVAPRASAD | Y56: =VLOOKUP($H56,ERP!$H:$AP,33,0) -> MANU JOY (C22591), | Z56: =VLOOKUP($H56,ERP!$H:$AP,34,0) -> MANU SASI
A57: 56 | B57: SOB25002295 | C57: ENQ25016422 | D57: E58688 | E57: 1431529 | F57: 40/VSL/25001455 | G57: 46094 | H57: 2567580598 | I57: SHARLET SHAMY VIVERA | J57: TOUR H3 | K57: MARUTI TOUR H3 CNG 1L 5MT | L57: MANU JOY | M57: =VLOOKUP($L57,Emp!$A:$F,2,0) -> MANU SASI | N57: =VLOOKUP($L57,Emp!$A:$F,3,0) -> EDAPPALLY | O57: =VLOOKUP($L57,Emp!$A:$F,4,0) -> ARENA | P57: KERALA GRAMIN BANK | Q57: KGB | R57: IH | S57: YES | T57: =IF(_xlfn.XLOOKUP(F57,IH!Y:Y,IH!AA:AA,"")="MAPPED","MAPPED","") | U57: =IFERROR(VLOOKUP(H57,IH!C:T,18,0),"") -> MSSF LOGIN | V57: =IF(W57<>"","DISBURSED","") -> DISBURSED | W57: =IFERROR(VLOOKUP(H57,IH!C:X,14,0),"") -> 46094 | X57: =VLOOKUP($L57,Emp!$A:$F,5,0) -> SIVAPRASAD | Y57: =VLOOKUP($H57,ERP!$H:$AP,33,0) -> MANU JOY (C22591), | Z57: =VLOOKUP($H57,ERP!$H:$AP,34,0) -> MANU SASI
A58: 57 | B58: SOB25002382 | C58: ENQ25016841 | D58: E58022 | E58: 1430855 | F58: 40/VSL/25001456 | G58: 46094 | H58: 2567570592 | I58: VIBIN VARGHESE | J58: TOUR H3 | K58: MARUTI TOUR H3 CNG 1L 5MT | L58: BINEESH P ANTO | M58: =VLOOKUP($L58,Emp!$A:$F,2,0) -> SIVAPRAKASH K S | N58: =VLOOKUP($L58,Emp!$A:$F,3,0) -> THRISSUR | O58: =VLOOKUP($L58,Emp!$A:$F,4,0) -> ARENA | P58: KERALA GRAMEENA BANK | Q58: KGB | R58: IH | S58: YES | T58: =IF(_xlfn.XLOOKUP(F58,IH!Y:Y,IH!AA:AA,"")="MAPPED","MAPPED","") | U58: =IFERROR(VLOOKUP(H58,IH!C:T,18,0),"") -> NO | V58: =IF(W58<>"","DISBURSED","") -> DISBURSED | W58: =IFERROR(VLOOKUP(H58,IH!C:X,14,0),"") -> 46094 | X58: =VLOOKUP($L58,Emp!$A:$F,5,0) -> SINTO | Y58: =VLOOKUP($H58,ERP!$H:$AP,33,0) -> NA | Z58: =VLOOKUP($H58,ERP!$H:$AP,34,0) -> NA
A59: 58 | B59: SOB25000167 | C59: ENQ25001814 | D59: C38930 | E59: 7934281 | F59: 118/VSL25000101 | G59: 46095 | H59: 2566855716 | I59: DEEPTHY RAJAN | J59: TOUR M | K59: MARUTI TOUR M 1.5L 5MT | L59: AJITH C M | M59: =VLOOKUP($L59,Emp!$A:$F,2,0) -> JESTIN UTHUP JOHN | N59: =VLOOKUP($L59,Emp!$A:$F,3,0) -> PIRAVOM | O59: =VLOOKUP($L59,Emp!$A:$F,4,0) -> ARENA | P59: SHRIRAM FINANCE LTD | Q59: SHRIRAM | R59: SELF | S59: NO | T59: =IF(_xlfn.XLOOKUP(F59,IH!Y:Y,IH!AA:AA,"")="MAPPED","MAPPED","") | U59: =IFERROR(VLOOKUP(H59,IH!C:T,18,0),"") | V59: =IF(W59<>"","DISBURSED","") | W59: =IFERROR(VLOOKUP(H59,IH!C:X,14,0),"") | X59: =VLOOKUP($L59,Emp!$A:$F,5,0) -> AMAL | Y59: =VLOOKUP($H59,ERP!$H:$AP,33,0) -> AJITH.C.M, | Z59: =VLOOKUP($H59,ERP!$H:$AP,34,0) -> JUSTIN UTHUP JOHN (PRVM)
A60: 59 | B60: SOB25000189 | C60: ENQ25001963 | D60: 372646 | E60: C988431 | F60: 118/VSL25000102 | G60: 46095 | H60: 2567247485 | I60: LIJU JACOB | J60: CELERIO | K60: MARUTI CELERIO VXI 1L ISS AGS | L60: ALFIYA ASHRAF | M60: =VLOOKUP($L60,Emp!$A:$F,2,0) -> JESTIN UTHUP JOHN | N60: =VLOOKUP($L60,Emp!$A:$F,3,0) -> PIRAVOM | O60: =VLOOKUP($L60,Emp!$A:$F,4,0) -> ARENA | P60: CASH | Q60: CASH | R60: CASH | S60: NO | T60: =IF(_xlfn.XLOOKUP(F60,IH!Y:Y,IH!AA:AA,"")="MAPPED","MAPPED","") | U60: =IFERROR(VLOOKUP(H60,IH!C:T,18,0),"") | V60: =IF(W60<>"","DISBURSED","") | W60: =IFERROR(VLOOKUP(H60,IH!C:X,14,0),"") | X60: =VLOOKUP($L60,Emp!$A:$F,5,0) -> AMAL | Y60: =VLOOKUP($H60,ERP!$H:$AP,33,0) -> ALFIYA ASHRAF (C26586), | Z60: =VLOOKUP($H60,ERP!$H:$AP,34,0) -> JUSTIN UTHUP JOHN (PRVM)
A61: 60 | B61: SOB25000230 | C61: ENQ25002404 | D61: E28587 | E61: 9256911 | F61: 28/VSL/25000112 | G61: 46095 | H61: 2567431225 | I61: ABDUL NASEER | J61: Wagon R | K61: MARUTI WAGON R ZXI 1.2L ISS 5MT | L61: RISHAD K S | M61: =VLOOKUP($L61,Emp!$A:$F,2,0) -> BHAGIESH | N61: =VLOOKUP($L61,Emp!$A:$F,3,0) -> CHAVAKKAD | O61: =VLOOKUP($L61,Emp!$A:$F,4,0) -> ARENA | P61: BAJAJ FINANCE LIMTED | Q61: BAJAJ | R61: IH | S61: YES | T61: =IF(_xlfn.XLOOKUP(F61,IH!Y:Y,IH!AA:AA,"")="MAPPED","MAPPED","") | U61: =IFERROR(VLOOKUP(H61,IH!C:T,18,0),"") -> NO | V61: =IF(W61<>"","DISBURSED","") -> DISBURSED | W61: =IFERROR(VLOOKUP(H61,IH!C:X,14,0),"") -> 46097 | X61: =VLOOKUP($L61,Emp!$A:$F,5,0) -> SINTO | Y61: =VLOOKUP($H61,ERP!$H:$AP,33,0) -> RISHAD K.S | Z61: =VLOOKUP($H61,ERP!$H:$AP,34,0) -> NA
A62: 61 | B62: SOB25002381 | C62: ENQ25016839 | D62: 411649 | E62: F311138 | F62: 40/VSL/25001457 | G62: 46095 | H62: 2567569469 | I62: RAHUL N R | J62: TOUR S | K62: MARUTI TOUR S CNG 1.2L 5MT | L62: NIDHIN K U | M62: =VLOOKUP($L62,Emp!$A:$F,2,0) -> SACHIN | N62: =VLOOKUP($L62,Emp!$A:$F,3,0) -> KODUNGALLUR | O62: =VLOOKUP($L62,Emp!$A:$F,4,0) -> ARENA | P62: HDB FINANCIAL SERVICES LIMITED | Q62: HDB | R62: SELF | S62: NO | T62: =IF(_xlfn.XLOOKUP(F62,IH!Y:Y,IH!AA:AA,"")="MAPPED","MAPPED","") | U62: =IFERROR(VLOOKUP(H62,IH!C:T,18,0),"") | V62: =IF(W62<>"","DISBURSED","") | W62: =IFERROR(VLOOKUP(H62,IH!C:X,14,0),"") | X62: =VLOOKUP($L62,Emp!$A:$F,5,0) -> JINEESH | Y62: =VLOOKUP($H62,ERP!$H:$AP,33,0) -> NA | Z62: =VLOOKUP($H62,ERP!$H:$AP,34,0) -> NA
A63: 62 | B63: SOB25002311 | C63: ENQ25016524 | D63: E51742 | E63: 9260672 | F63: 40/VSL/25001458 | G63: 46095 | H63: 2567447050 | I63: SIYAD T M | J63: Wagon R | K63: MARUTI WAGON R ZXI 1.2L ISS AGS | L63: RIYAS | M63: =VLOOKUP($L63,Emp!$A:$F,2,0) -> SHEMEER A K | N63: =VLOOKUP($L63,Emp!$A:$F,3,0) -> EDAPPALLY | O63: =VLOOKUP($L63,Emp!$A:$F,4,0) -> ARENA | P63: ICICI BANK LTD | Q63: ICICI | R63: IH | S63: YES | T63: =IF(_xlfn.XLOOKUP(F63,IH!Y:Y,IH!AA:AA,"")="MAPPED","MAPPED","") -> MAPPED | U63: =IFERROR(VLOOKUP(H63,IH!C:T,18,0),"") -> MSSF DISBURSED | V63: =IF(W63<>"","DISBURSED","") -> DISBURSED | W63: =IFERROR(VLOOKUP(H63,IH!C:X,14,0),"") -> 46095 | X63: =VLOOKUP($L63,Emp!$A:$F,5,0) -> SIVAPRASAD | Y63: =VLOOKUP($H63,ERP!$H:$AP,33,0) -> MOHAMMED RIYAS (C25510), | Z63: =VLOOKUP($H63,ERP!$H:$AP,34,0) -> SHEMEER.AK
A64: 63 | B64: SOB25002179 | C64: ENQ25015735 | D64: 757971 | E64: 7916153 | F64: 40/VSL/25001459 | G64: 46095 | H64: 2567608985 | I64: AREAMANAGER CSD/ KISHORE | J64: BREZZA | K64: MARUTI BREZZA VXI 1.5L 5MT | L64: ABHILASH P C | M64: =VLOOKUP($L64,Emp!$A:$F,2,0) -> ABHILASH K P | N64: =VLOOKUP($L64,Emp!$A:$F,3,0) -> EDAPPALLY | O64: =VLOOKUP($L64,Emp!$A:$F,4,0) -> ARENA | P64: STATE BANK OF INDIA | Q64: SBI | R64: IH | S64: YES | T64: =IF(_xlfn.XLOOKUP(F64,IH!Y:Y,IH!AA:AA,"")="MAPPED","MAPPED","") | U64: =IFERROR(VLOOKUP(H64,IH!C:T,18,0),"") -> MSSF LOGIN | V64: =IF(W64<>"","DISBURSED","") -> DISBURSED | W64: =IFERROR(VLOOKUP(H64,IH!C:X,14,0),"") -> 46093 | X64: =VLOOKUP($L64,Emp!$A:$F,5,0) -> SIVAPRASAD | Y64: =VLOOKUP($H64,ERP!$H:$AP,33,0) -> NA | Z64: =VLOOKUP($H64,ERP!$H:$AP,34,0) -> NA
A65: 64 | B65: SOB25000251 | C65: ENQ25001765 | D65: 396569 | E65: F293772 | F65: 77/VSL/25000162 | G65: 46095 | H65: 2567602958 | I65: MOHAMED GAZZALI | J65: TOUR S | K65: MARUTI TOUR S CNG 1.2L 5MT | L65: VISHNU K R | M65: =VLOOKUP($L65,Emp!$A:$F,2,0) -> KASI VISWANATH | N65: =VLOOKUP($L65,Emp!$A:$F,3,0) -> KAIPAMANGALAM | O65: =VLOOKUP($L65,Emp!$A:$F,4,0) -> ARENA | P65: CHOLAMANDALAM INVS.& FIN.CO.LTD | Q65: CHOLA | R65: IH | S65: YES | T65: =IF(_xlfn.XLOOKUP(F65,IH!Y:Y,IH!AA:AA,"")="MAPPED","MAPPED","") -> MAPPED | U65: =IFERROR(VLOOKUP(H65,IH!C:T,18,0),"") -> MSSF DISBURSED | V65: =IF(W65<>"","DISBURSED","") -> DISBURSED | W65: =IFERROR(VLOOKUP(H65,IH!C:X,14,0),"") -> 46094 | X65: =VLOOKUP($L65,Emp!$A:$F,5,0) -> JINEESH | Y65: =VLOOKUP($H65,ERP!$H:$AP,33,0) -> NA | Z65: =VLOOKUP($H65,ERP!$H:$AP,34,0) -> NA
A66: 65 | B66: SOB25000346 | C66: ENQ25002853 | D66: 167199 | E66: K113922 | F66: 88/VSL/25000179 | G66: 46095 | H66: 2567412643 | I66: ANIL KUMAR | J66: VICTORIS | K66: MARUTI VICTORIS LXI 1.5L 5MT | L66: SATHEESH A V | M66: =VLOOKUP($L66,Emp!$A:$F,2,0) -> ARUN BABU | N66: =VLOOKUP($L66,Emp!$A:$F,3,0) -> KOOTHATTUKULAM | O66: =VLOOKUP($L66,Emp!$A:$F,4,0) -> ARENA | P66: CASH | Q66: CASH | R66: CASH | S66: NO | T66: =IF(_xlfn.XLOOKUP(F66,IH!Y:Y,IH!AA:AA,"")="MAPPED","MAPPED","") | U66: =IFERROR(VLOOKUP(H66,IH!C:T,18,0),"") | V66: =IF(W66<>"","DISBURSED","") | W66: =IFERROR(VLOOKUP(H66,IH!C:X,14,0),"") | X66: =VLOOKUP($L66,Emp!$A:$F,5,0) -> AMAL | Y66: =VLOOKUP($H66,ERP!$H:$AP,33,0) -> SATHEESH A.V. (C20658), | Z66: =VLOOKUP($H66,ERP!$H:$AP,34,0) -> ARUN BABU(KTLM)
A67: 66 | B67: SOB25000355 | C67: ENQ25002885 | D67: E40725 | E67: 9258855 | F67: 88/VSL/25000180 | G67: 46095 | H67: 2567474135 | I67: VIJAYAN T S | J67: Wagon R | K67: MARUTI WAGON R ZXI 1.2L ISS 5MT | L67: SATHEESH A V | M67: =VLOOKUP($L67,Emp!$A:$F,2,0) -> ARUN BABU | N67: =VLOOKUP($L67,Emp!$A:$F,3,0) -> KOOTHATTUKULAM | O67: =VLOOKUP($L67,Emp!$A:$F,4,0) -> ARENA | P67: SUNDARAM FINANCE LTD | Q67: SFL | R67: IH | S67: YES | T67: =IF(_xlfn.XLOOKUP(F67,IH!Y:Y,IH!AA:AA,"")="MAPPED","MAPPED","") | U67: =IFERROR(VLOOKUP(H67,IH!C:T,18,0),"") -> MSSF LOGIN | V67: =IF(W67<>"","DISBURSED","") -> DISBURSED | W67: =IFERROR(VLOOKUP(H67,IH!C:X,14,0),"") -> 46097 | X67: =VLOOKUP($L67,Emp!$A:$F,5,0) -> AMAL | Y67: =VLOOKUP($H67,ERP!$H:$AP,33,0) -> SATHEESH A.V. (C20658), | Z67: =VLOOKUP($H67,ERP!$H:$AP,34,0) -> ARUN BABU(KTLM)
A68: 67 | B68: SOB25000195 | C68: ENQ25001738 | D68: E55019 | E68: F083392 | F68: 126/VSL/25000115 | G68: 46097 | H68: 2566867952 | I68: DINESH R | J68: Wagon R | K68: MARUTI WAGON R VXI 1L ISS 5MT | L68: NYGIL GEORGE | M68: =VLOOKUP($L68,Emp!$A:$F,2,0) -> SIJO VARGHESE GEORGE | N68: =VLOOKUP($L68,Emp!$A:$F,3,0) -> PERUMBAVOOR | O68: =VLOOKUP($L68,Emp!$A:$F,4,0) -> ARENA | P68: BANK OF BARODA | Q68: BOB | R68: IH | S68: YES | T68: =IF(_xlfn.XLOOKUP(F68,IH!Y:Y,IH!AA:AA,"")="MAPPED","MAPPED","") | U68: =IFERROR(VLOOKUP(H68,IH!C:T,18,0),"") -> MSSF DISBURSED | V68: =IF(W68<>"","DISBURSED","") -> DISBURSED | W68: =IFERROR(VLOOKUP(H68,IH!C:X,14,0),"") -> 46098 | X68: =VLOOKUP($L68,Emp!$A:$F,5,0) -> SALMAN | Y68: =VLOOKUP($H68,ERP!$H:$AP,33,0) -> NIGIL GEORGE(C23881), | Z68: =VLOOKUP($H68,ERP!$H:$AP,34,0) -> SIJO VARGHESE GEORGE (PBVR)
A69: 68 | B69: SOB25000231 | C69: ENQ25001986 | D69: 412411 | E69: F311639 | F69: 126/VSL/25000116 | G69: 46097 | H69: 2567569135 | I69: A M SHAJAHAN | J69: Dzire | K69: MARUTI DZIRE ZXI+ 1.2L ISS AGS | L69: VISHNU RAJU | M69: =VLOOKUP($L69,Emp!$A:$F,2,0) -> SIJO VARGHESE GEORGE | N69: =VLOOKUP($L69,Emp!$A:$F,3,0) -> PERUMBAVOOR | O69: =VLOOKUP($L69,Emp!$A:$F,4,0) -> ARENA | P69: BAJAJ FINANCE LIMITED | Q69: BAJAJ | R69: IH | S69: YES | T69: =IF(_xlfn.XLOOKUP(F69,IH!Y:Y,IH!AA:AA,"")="MAPPED","MAPPED","") | U69: =IFERROR(VLOOKUP(H69,IH!C:T,18,0),"") -> MSSF LOGIN | V69: =IF(W69<>"","DISBURSED","") -> DISBURSED | W69: =IFERROR(VLOOKUP(H69,IH!C:X,14,0),"") -> 46094 | X69: =VLOOKUP($L69,Emp!$A:$F,5,0) -> SALMAN | Y69: =VLOOKUP($H69,ERP!$H:$AP,33,0) -> VISHNU RAJU (C25990), | Z69: =VLOOKUP($H69,ERP!$H:$AP,34,0) -> SIJO VARGHESE GEORGE (PBVR)
A70: 69 | B70: SOB25000231 | C70: ENQ25002417 | D70: 537926 | E70: 1433993 | F70: 28/VSL/25000113 | G70: 46097 | H70: 2567458364 | I70: ANEESHA | J70: SWIFT | K70: MARUTI SWIFT ZXI+ 1.2L ISS AGS | L70: NABEEL | M70: =VLOOKUP($L70,Emp!$A:$F,2,0) -> BHAGIESH | N70: =VLOOKUP($L70,Emp!$A:$F,3,0) -> CHAVAKKAD | O70: =VLOOKUP($L70,Emp!$A:$F,4,0) -> ARENA | P70: SOUTH INDIAN BANK LTD. | Q70: SIB | R70: SELF | S70: NO | T70: =IF(_xlfn.XLOOKUP(F70,IH!Y:Y,IH!AA:AA,"")="MAPPED","MAPPED","") | U70: =IFERROR(VLOOKUP(H70,IH!C:T,18,0),"") | V70: =IF(W70<>"","DISBURSED","") | W70: =IFERROR(VLOOKUP(H70,IH!C:X,14,0),"") | X70: =VLOOKUP($L70,Emp!$A:$F,5,0) -> SINTO | Y70: =VLOOKUP($H70,ERP!$H:$AP,33,0) -> NABEEL P A (C26239), | Z70: =VLOOKUP($H70,ERP!$H:$AP,34,0) -> BHAGIESH P (CHKD)
A71: 70 | B71: SOB25001861 | C71: ENQ25014423 | D71: E54022 | E71: 1426712 | F71: 40/VSL/25001460 | G71: 46097 | H71: 2566580634 | I71: RINSON FRANCIS | J71: Wagon R | K71: MARUTI WAGON R LXI 1L ISS 5MT | L71: LANEESH A S | M71: =VLOOKUP($L71,Emp!$A:$F,2,0) -> MANU SASI | N71: =VLOOKUP($L71,Emp!$A:$F,3,0) -> EDAPPALLY | O71: =VLOOKUP($L71,Emp!$A:$F,4,0) -> ARENA | P71: CASH | Q71: CASH | R71: CASH | S71: NO | T71: =IF(_xlfn.XLOOKUP(F71,IH!Y:Y,IH!AA:AA,"")="MAPPED","MAPPED","") | U71: =IFERROR(VLOOKUP(H71,IH!C:T,18,0),"") | V71: =IF(W71<>"","DISBURSED","") | W71: =IFERROR(VLOOKUP(H71,IH!C:X,14,0),"") | X71: =VLOOKUP($L71,Emp!$A:$F,5,0) -> SIVAPRASAD | Y71: =VLOOKUP($H71,ERP!$H:$AP,33,0) -> LANEESH A S(C21174), Mr. | Z71: =VLOOKUP($H71,ERP!$H:$AP,34,0) -> MANU SASI
A72: 71 | B72: SOB25001883 | C72: ENQ25013698 | D72: 158777 | E72: K103279 | F72: 40/VSL/25001461 | G72: 46097 | H72: 2567578977 | I72: FRANCIS N J | J72: VICTORIS | K72: MARUTI VICTORIS VXI 1.5L 6AT | L72: CHANCHAL JOSE ANTONY | M72: =VLOOKUP($L72,Emp!$A:$F,2,0) -> PRANOOB V NAIR | N72: =VLOOKUP($L72,Emp!$A:$F,3,0) -> TRIPPUNITHURA | O72: =VLOOKUP($L72,Emp!$A:$F,4,0) -> ARENA | P72: CASH | Q72: CASH | R72: CASH | S72: NO | T72: =IF(_xlfn.XLOOKUP(F72,IH!Y:Y,IH!AA:AA,"")="MAPPED","MAPPED","") | U72: =IFERROR(VLOOKUP(H72,IH!C:T,18,0),"") | V72: =IF(W72<>"","DISBURSED","") | W72: =IFERROR(VLOOKUP(H72,IH!C:X,14,0),"") | X72: =VLOOKUP($L72,Emp!$A:$F,5,0) -> SIVAPRASAD | Y72: =VLOOKUP($H72,ERP!$H:$AP,33,0) -> CHANCHAL JOS ANTONY (C25630), | Z72: =VLOOKUP($H72,ERP!$H:$AP,34,0) -> PRANOOB V (TPRA)
A73: 72 | B73: SOB25002304 | C73: ENQ25016515 | D73: F91940 | E73: 4585999 | F73: 40/VSL/25001462 | G73: 46097 | H73: 2567441049 | I73: SALY SAJAN | J73: EECO | K73: MARUTI EECO 5 STR AC 1.2L 5MT | L73: SREENATH R PRABHU | M73: =VLOOKUP($L73,Emp!$A:$F,2,0) -> NOUFAL T A | N73: =VLOOKUP($L73,Emp!$A:$F,3,0) -> EDAPPALLY | O73: =VLOOKUP($L73,Emp!$A:$F,4,0) -> ARENA | P73: KOTAK MAHINDRA PRIME LTD | Q73: KOTAK | R73: IH | S73: YES | T73: =IF(_xlfn.XLOOKUP(F73,IH!Y:Y,IH!AA:AA,"")="MAPPED","MAPPED","") | U73: =IFERROR(VLOOKUP(H73,IH!C:T,18,0),"") -> MSSF DISBURSED | V73: =IF(W73<>"","DISBURSED","") -> DISBURSED | W73: =IFERROR(VLOOKUP(H73,IH!C:X,14,0),"") -> 46098 | X73: =VLOOKUP($L73,Emp!$A:$F,5,0) -> SIVAPRASAD | Y73: =VLOOKUP($H73,ERP!$H:$AP,33,0) -> SREENATH R PRABHU (C23391), | Z73: =VLOOKUP($H73,ERP!$H:$AP,34,0) -> MANU SASI
A74: 73 | B74: SOB25002407 | C74: ENQ25016385 | D74: 646337 | E74: K010264 | F74: 40/VSL/25001463 | G74: 46097 | H74: 2567639079 | I74: CHITHRA P | J74: BREZZA | K74: MARUTI BREZZA VXI CNG 1.5L 5MT | L74: ABHILASH P C | M74: =VLOOKUP($L74,Emp!$A:$F,2,0) -> ABHILASH K P | N74: =VLOOKUP($L74,Emp!$A:$F,3,0) -> EDAPPALLY | O74: =VLOOKUP($L74,Emp!$A:$F,4,0) -> ARENA | P74: BANK OF BARODA | Q74: BOB | R74: IH | S74: YES | T74: =IF(_xlfn.XLOOKUP(F74,IH!Y:Y,IH!AA:AA,"")="MAPPED","MAPPED","") | U74: =IFERROR(VLOOKUP(H74,IH!C:T,18,0),"") -> MSSF LOGIN | V74: =IF(W74<>"","DISBURSED","") -> DISBURSED | W74: =IFERROR(VLOOKUP(H74,IH!C:X,14,0),"") -> 46094 | X74: =VLOOKUP($L74,Emp!$A:$F,5,0) -> SIVAPRASAD | Y74: =VLOOKUP($H74,ERP!$H:$AP,33,0) -> ABHILASH P.C (C21931), | Z74: =VLOOKUP($H74,ERP!$H:$AP,34,0) -> ABHILASH K P (C21618)
A75: 74 | B75: SOB25000318 | C75: ENQ25002574 | D75: F97919 | E75: 4593670 | F75: 72/VSL/25000155 | G75: 46097 | H75: 2566736333 | I75: MISIRI P A | J75: TOUR V | K75: MARUTI TOUR V 5 STR AC CNG 1.2L 5MT | L75: ANVAR SADATH | M75: =VLOOKUP($L75,Emp!$A:$F,2,0) -> RIJITH | N75: =VLOOKUP($L75,Emp!$A:$F,3,0) -> STUDIO KDLR | O75: =VLOOKUP($L75,Emp!$A:$F,4,0) -> STUDIO | P75: SUNDARAM FINANCE LTD | Q75: SFL | R75: IH | S75: YES | T75: =IF(_xlfn.XLOOKUP(F75,IH!Y:Y,IH!AA:AA,"")="MAPPED","MAPPED","") -> MAPPED | U75: =IFERROR(VLOOKUP(H75,IH!C:T,18,0),"") -> MSSF DISBURSED | V75: =IF(W75<>"","DISBURSED","") -> DISBURSED | W75: =IFERROR(VLOOKUP(H75,IH!C:X,14,0),"") -> 46098 | X75: =VLOOKUP($L75,Emp!$A:$F,5,0) -> JINEESH | Y75: =VLOOKUP($H75,ERP!$H:$AP,33,0) -> ANVAR SADATH A A (C25984), | Z75: =VLOOKUP($H75,ERP!$H:$AP,34,0) -> BINOY MOHANDAS (NEXA STUDIO)
A76: 75 | B76: SOB25000196 | C76: ENQ25002041 | D76: 162530 | E76: K107840 | F76: 118/VSL25000103 | G76: 46098 | H76: 2567538439 | I76: MUGIB RAHMAN VM | J76: VICTORIS | K76: MARUTI VICTORIS LXI 1.5L 5MT | L76: LIPIN P PAUL | M76: =VLOOKUP($L76,Emp!$A:$F,2,0) -> JESTIN UTHUP JOHN | N76: =VLOOKUP($L76,Emp!$A:$F,3,0) -> PIRAVOM | O76: =VLOOKUP($L76,Emp!$A:$F,4,0) -> ARENA | P76: BANK OF MAHARASHTRA | Q76: BOM | R76: SELF | S76: NO | T76: =IF(_xlfn.XLOOKUP(F76,IH!Y:Y,IH!AA:AA,"")="MAPPED","MAPPED","") | U76: =IFERROR(VLOOKUP(H76,IH!C:T,18,0),"") | V76: =IF(W76<>"","DISBURSED","") | W76: =IFERROR(VLOOKUP(H76,IH!C:X,14,0),"") | X76: =VLOOKUP($L76,Emp!$A:$F,5,0) -> AMAL | Y76: =VLOOKUP($H76,ERP!$H:$AP,33,0) -> LIPIN P PAUL (C22876), | Z76: =VLOOKUP($H76,ERP!$H:$AP,34,0) -> JUSTIN UTHUP JOHN (PRVM)
A77: 76 | B77: SOB25000174 | C77: ENQ25001834 | D77: E54131 | E77: C978873 | F77: 118/VSL25000104 | G77: 46098 | H77: 2566966863 | I77: SAJAN K M | J77: TOUR H3 | K77: MARUTI TOUR H3 CNG 1L 5MT | L77: MIRAJ KAREEM | M77: =VLOOKUP($L77,Emp!$A:$F,2,0) -> JESTIN UTHUP JOHN | N77: =VLOOKUP($L77,Emp!$A:$F,3,0) -> PIRAVOM | O77: =VLOOKUP($L77,Emp!$A:$F,4,0) -> ARENA | P77: CASH | Q77: CASH | R77: CASH | S77: NO | T77: =IF(_xlfn.XLOOKUP(F77,IH!Y:Y,IH!AA:AA,"")="MAPPED","MAPPED","") | U77: =IFERROR(VLOOKUP(H77,IH!C:T,18,0),"") | V77: =IF(W77<>"","DISBURSED","") | W77: =IFERROR(VLOOKUP(H77,IH!C:X,14,0),"") | X77: =VLOOKUP($L77,Emp!$A:$F,5,0) -> AMAL | Y77: =VLOOKUP($H77,ERP!$H:$AP,33,0) -> MIRAJ K KAREEM (C26100), | Z77: =VLOOKUP($H77,ERP!$H:$AP,34,0) -> JUSTIN UTHUP JOHN (PRVM)
A78: 77 | B78: SOB25000197 | C78: ENQ25002046 | D78: C41551 | E78: A018954 | F78: 118/VSL25000105 | G78: 46098 | H78: 2567412371 | I78: PRASANTH MOHANAN | J78: TOUR M | K78: MARUTI TOUR M CNG 1.5L 5MT | L78: AJITH C M | M78: =VLOOKUP($L78,Emp!$A:$F,2,0) -> JESTIN UTHUP JOHN | N78: =VLOOKUP($L78,Emp!$A:$F,3,0) -> PIRAVOM | O78: =VLOOKUP($L78,Emp!$A:$F,4,0) -> ARENA | P78: SHRIRAM FINANCE LTD | Q78: SHRIRAM | R78: SELF | S78: NO | T78: =IF(_xlfn.XLOOKUP(F78,IH!Y:Y,IH!AA:AA,"")="MAPPED","MAPPED","") | U78: =IFERROR(VLOOKUP(H78,IH!C:T,18,0),"") | V78: =IF(W78<>"","DISBURSED","") | W78: =IFERROR(VLOOKUP(H78,IH!C:X,14,0),"") | X78: =VLOOKUP($L78,Emp!$A:$F,5,0) -> AMAL | Y78: =VLOOKUP($H78,ERP!$H:$AP,33,0) -> AJITH.C.M, | Z78: =VLOOKUP($H78,ERP!$H:$AP,34,0) -> JUSTIN UTHUP JOHN (PRVM)
A79: 78 | B79: SOB25000213 | C79: ENQ25001784 | D79: 538886 | E79: 1433572 | F79: 255/VSL/25000101 | G79: 46098 | H79: 2566843334 | I79: APARNA RENJAN | J79: SWIFT | K79: MARUTI SWIFT VXI 1.2L ISS AGS | L79: AMAL K SAJU | M79: =VLOOKUP($L79,Emp!$A:$F,2,0) -> ANAND K V | N79: =VLOOKUP($L79,Emp!$A:$F,3,0) -> KOLENCHERY | O79: =VLOOKUP($L79,Emp!$A:$F,4,0) -> ARENA | P79: HDFC BANK LTD | Q79: HDFC | R79: SELF | S79: NO | T79: =IF(_xlfn.XLOOKUP(F79,IH!Y:Y,IH!AA:AA,"")="MAPPED","MAPPED","") | U79: =IFERROR(VLOOKUP(H79,IH!C:T,18,0),"") | V79: =IF(W79<>"","DISBURSED","") | W79: =IFERROR(VLOOKUP(H79,IH!C:X,14,0),"") | X79: =VLOOKUP($L79,Emp!$A:$F,5,0) -> AMAL | Y79: =VLOOKUP($H79,ERP!$H:$AP,33,0) -> AMAL K SAJU (C26180), | Z79: =VLOOKUP($H79,ERP!$H:$AP,34,0) -> ANAND (KLY)
A80: 79 | B80: SOB25002281 | C80: ENQ25016309 | D80: 175019 | E80: K124375 | F80: 40/VSL/25001464 | G80: 46098 | H80: 2567368230 | I80: SMIJO JOSE | J80: VICTORIS | K80: MARUTI VICTORIS VXI 1.5L 5MT | L80: ALBIN MARTIN | M80: =VLOOKUP($L80,Emp!$A:$F,2,0) -> RATISH K R | N80: =VLOOKUP($L80,Emp!$A:$F,3,0) -> KADAVANTHRA | O80: =VLOOKUP($L80,Emp!$A:$F,4,0) -> ARENA | P80: BANK OF BARODA | Q80: BOB | R80: IH | S80: YES | T80: =IF(_xlfn.XLOOKUP(F80,IH!Y:Y,IH!AA:AA,"")="MAPPED","MAPPED","") -> MAPPED | U80: =IFERROR(VLOOKUP(H80,IH!C:T,18,0),"") -> MSSF DISBURSED | V80: =IF(W80<>"","DISBURSED","") -> DISBURSED | W80: =IFERROR(VLOOKUP(H80,IH!C:X,14,0),"") -> 46099 | X80: =VLOOKUP($L80,Emp!$A:$F,5,0) -> SALMAN | Y80: =VLOOKUP($H80,ERP!$H:$AP,33,0) -> ALBIN MARTIN (C26561), | Z80: =VLOOKUP($H80,ERP!$H:$AP,34,0) -> RATHEESH.K.R
A81: 80 | B81: SOB25002335 | C81: ENQ25016637 | D81: C45422 | E81: A023177 | F81: 40/VSL/25001465 | G81: 46098 | H81: 2567485885 | I81: SREEVIDYA S | J81: TOUR M | K81: MARUTI TOUR M CNG 1.5L 5MT | L81: MANOJ C S | M81: =VLOOKUP($L81,Emp!$A:$F,2,0) -> ABHILASH K P | N81: =VLOOKUP($L81,Emp!$A:$F,3,0) -> EDAPPALLY | O81: =VLOOKUP($L81,Emp!$A:$F,4,0) -> ARENA | P81: MAHINDRA& MAHINDRA FINANCIAL SERVICES LTD | Q81: MAHINDRA | R81: IH | S81: YES | T81: =IF(_xlfn.XLOOKUP(F81,IH!Y:Y,IH!AA:AA,"")="MAPPED","MAPPED","") -> MAPPED | U81: =IFERROR(VLOOKUP(H81,IH!C:T,18,0),"") -> MSSF DISBURSED | V81: =IF(W81<>"","DISBURSED","") -> DISBURSED | W81: =IFERROR(VLOOKUP(H81,IH!C:X,14,0),"") -> 46098 | X81: =VLOOKUP($L81,Emp!$A:$F,5,0) -> SIVAPRASAD | Y81: =VLOOKUP($H81,ERP!$H:$AP,33,0) -> MANOJ C S (C20619), Mr. | Z81: =VLOOKUP($H81,ERP!$H:$AP,34,0) -> ABHILASH K P (C21618)
A82: 81 | B82: SOB25002167 | C82: ENQ25015602 | D82: E58527 | E82: 1431340 | F82: 40/VSL/25001466 | G82: 46098 | H82: 2567136986 | I82: MANOJ M N | J82: TOUR H3 | K82: MARUTI TOUR H3 CNG 1L 5MT | L82: LANEESH A S | M82: =VLOOKUP($L82,Emp!$A:$F,2,0) -> MANU SASI | N82: =VLOOKUP($L82,Emp!$A:$F,3,0) -> EDAPPALLY | O82: =VLOOKUP($L82,Emp!$A:$F,4,0) -> ARENA | P82: KERALA GRAMEENA BANK | Q82: KGB | R82: IH | S82: YES | T82: =IF(_xlfn.XLOOKUP(F82,IH!Y:Y,IH!AA:AA,"")="MAPPED","MAPPED","") | U82: =IFERROR(VLOOKUP(H82,IH!C:T,18,0),"") -> MSSF LOGIN | V82: =IF(W82<>"","DISBURSED","") -> DISBURSED | W82: =IFERROR(VLOOKUP(H82,IH!C:X,14,0),"") -> 46098 | X82: =VLOOKUP($L82,Emp!$A:$F,5,0) -> SIVAPRASAD | Y82: =VLOOKUP($H82,ERP!$H:$AP,33,0) -> LANEESH A S(C21174), Mr. | Z82: =VLOOKUP($H82,ERP!$H:$AP,34,0) -> MANU SASI
A83: 82 | B83: SOB25000228 | C83: ENQ25001968 | D83: 384061 | E83: F279300 | F83: 126/VSL/25000117 | G83: 46099 | H83: 2567522339 | I83: NOUFAL MAJEED | J83: Dzire | K83: MARUTI DZIRE ZXI+ 1.2L ISS 5MT | L83: BIJO JOY | M83: =VLOOKUP($L83,Emp!$A:$F,2,0) -> SIJO VARGHESE GEORGE | N83: =VLOOKUP($L83,Emp!$A:$F,3,0) -> PERUMBAVOOR | O83: =VLOOKUP($L83,Emp!$A:$F,4,0) -> ARENA | P83: ICICI BANK LTD | Q83: ICICI | R83: IH | S83: YES | T83: =IF(_xlfn.XLOOKUP(F83,IH!Y:Y,IH!AA:AA,"")="MAPPED","MAPPED","") -> MAPPED | U83: =IFERROR(VLOOKUP(H83,IH!C:T,18,0),"") -> MSSF DISBURSED | V83: =IF(W83<>"","DISBURSED","") -> DISBURSED | W83: =IFERROR(VLOOKUP(H83,IH!C:X,14,0),"") -> 46099 | X83: =VLOOKUP($L83,Emp!$A:$F,5,0) -> SALMAN | Y83: =VLOOKUP($H83,ERP!$H:$AP,33,0) -> BIJO JOY (C23459), | Z83: =VLOOKUP($H83,ERP!$H:$AP,34,0) -> SIJO VARGHESE GEORGE (PBVR)
A84: 83 | B84: SOB25002128 | C84: ENQ25015417 | D84: E57859 | E84: 1430696 | F84: 40/VSL/25001467 | G84: 46099 | H84: 2567027980 | I84: DINURAJ D R | J84: TOUR H3 | K84: MARUTI TOUR H3 CNG 1L 5MT | L84: RATHEESH K B | M84: =VLOOKUP($L84,Emp!$A:$F,2,0) -> PRANOOB V NAIR | N84: =VLOOKUP($L84,Emp!$A:$F,3,0) -> TRIPPUNITHURA | O84: =VLOOKUP($L84,Emp!$A:$F,4,0) -> ARENA | P84: KERALA GRAMEENA BANK | Q84: KGB | R84: IH | S84: YES | T84: =IF(_xlfn.XLOOKUP(F84,IH!Y:Y,IH!AA:AA,"")="MAPPED","MAPPED","") | U84: =IFERROR(VLOOKUP(H84,IH!C:T,18,0),"") -> MSSF LOGIN | V84: =IF(W84<>"","DISBURSED","") -> DISBURSED | W84: =IFERROR(VLOOKUP(H84,IH!C:X,14,0),"") -> 46099 | X84: =VLOOKUP($L84,Emp!$A:$F,5,0) -> SIVAPRASAD | Y84: =VLOOKUP($H84,ERP!$H:$AP,33,0) -> RATHEESH K B, | Z84: =VLOOKUP($H84,ERP!$H:$AP,34,0) -> PRANOOB V (TPRA)
A85: 84 | B85: SOB25002391 | C85: ENQ25016902 | D85: E52755 | E85: C986553 | F85: 40/VSL/25001468 | G85: 46099 | H85: 2567583828 | I85: FAIZAL C M | J85: TOUR H3 | K85: MARUTI TOUR H3 CNG 1L 5MT | L85: VINAY T V | M85: =VLOOKUP($L85,Emp!$A:$F,2,0) -> RATISH K R | N85: =VLOOKUP($L85,Emp!$A:$F,3,0) -> KADAVANTHRA | O85: =VLOOKUP($L85,Emp!$A:$F,4,0) -> ARENA | P85: KOTAK MAHINDRA PRIME LTD | Q85: KOTAK | R85: IH | S85: YES | T85: =IF(_xlfn.XLOOKUP(F85,IH!Y:Y,IH!AA:AA,"")="MAPPED","MAPPED","") -> MAPPED | U85: =IFERROR(VLOOKUP(H85,IH!C:T,18,0),"") -> MSSF DISBURSED | V85: =IF(W85<>"","DISBURSED","") -> DISBURSED | W85: =IFERROR(VLOOKUP(H85,IH!C:X,14,0),"") -> 46100 | X85: =VLOOKUP($L85,Emp!$A:$F,5,0) -> SALMAN | Y85: =VLOOKUP($H85,ERP!$H:$AP,33,0) -> VINAY T V (C20769), | Z85: =VLOOKUP($H85,ERP!$H:$AP,34,0) -> RATHEESH.K.R
A86: 85 | B86: SOB25002287 | C86: ENQ25016356 | D86: E61032 | E86: 9262002 | F86: 40/VSL/25001469 | G86: 46099 | H86: 2567397863 | I86: RAJAN K V | J86: Wagon R | K86: MARUTI WAGON R ZXI+ 1.2L ISS AGS | L86: PRAMOD K | M86: =VLOOKUP($L86,Emp!$A:$F,2,0) -> SIVAPRAKASH K S | N86: =VLOOKUP($L86,Emp!$A:$F,3,0) -> THRISSUR | O86: =VLOOKUP($L86,Emp!$A:$F,4,0) -> ARENA | P86: CASH | Q86: CASH | R86: CASH | S86: NO | T86: =IF(_xlfn.XLOOKUP(F86,IH!Y:Y,IH!AA:AA,"")="MAPPED","MAPPED","") | U86: =IFERROR(VLOOKUP(H86,IH!C:T,18,0),"") | V86: =IF(W86<>"","DISBURSED","") | W86: =IFERROR(VLOOKUP(H86,IH!C:X,14,0),"") | X86: =VLOOKUP($L86,Emp!$A:$F,5,0) -> SINTO | Y86: =VLOOKUP($H86,ERP!$H:$AP,33,0) -> PRAMOD K ( C21230), | Z86: =VLOOKUP($H86,ERP!$H:$AP,34,0) -> RAJEEV (THCR)
A87: 86 | B87: SOB25002246 | C87: ENQ25016194 | D87: 476037 | E87: C988791 | F87: 40/VSL/25001470 | G87: 46099 | H87: 2567314828 | I87: RATHEESHKUMAR M | J87: ALTO K10 | K87: MARUTI ALTO K10 VXI+ 1L AGS | L87: PRAMOD K | M87: =VLOOKUP($L87,Emp!$A:$F,2,0) -> SIVAPRAKASH K S | N87: =VLOOKUP($L87,Emp!$A:$F,3,0) -> THRISSUR | O87: =VLOOKUP($L87,Emp!$A:$F,4,0) -> ARENA | P87: INDUSIND BANK LTD | Q87: IBL | R87: IH | S87: YES | T87: =IF(_xlfn.XLOOKUP(F87,IH!Y:Y,IH!AA:AA,"")="MAPPED","MAPPED","") | U87: =IFERROR(VLOOKUP(H87,IH!C:T,18,0),"") -> MSSF DISBURSED | V87: =IF(W87<>"","DISBURSED","") -> DISBURSED | W87: =IFERROR(VLOOKUP(H87,IH!C:X,14,0),"") -> 46100 | X87: =VLOOKUP($L87,Emp!$A:$F,5,0) -> SINTO | Y87: =VLOOKUP($H87,ERP!$H:$AP,33,0) -> PRAMOD K ( C21230), | Z87: =VLOOKUP($H87,ERP!$H:$AP,34,0) -> RAJEEV (THCR)
A88: 87 | B88: SOB25002378 | C88: ENQ25016790 | D88: 411950 | E88: F310705 | F88: 40/VSL/25001471 | G88: 46099 | H88: 2567547876 | I88: KRISHNAPRIYA K B | J88: TOUR S | K88: MARUTI TOUR S CNG 1.2L 5MT | L88: SAJITH V S | M88: =VLOOKUP($L88,Emp!$A:$F,2,0) -> VIBIN I B | N88: =VLOOKUP($L88,Emp!$A:$F,3,0) -> KAIPAMANGALAM | O88: =VLOOKUP($L88,Emp!$A:$F,4,0) -> ARENA | P88: CHOLAMANDALAM INVS.& FIN.CO.LTD | Q88: CHOLA | R88: IH | S88: YES | T88: =IF(_xlfn.XLOOKUP(F88,IH!Y:Y,IH!AA:AA,"")="MAPPED","MAPPED","") -> MAPPED | U88: =IFERROR(VLOOKUP(H88,IH!C:T,18,0),"") -> MSSF DISBURSED | V88: =IF(W88<>"","DISBURSED","") -> DISBURSED | W88: =IFERROR(VLOOKUP(H88,IH!C:X,14,0),"") -> 46092 | X88: =VLOOKUP($L88,Emp!$A:$F,5,0) -> JINEESH | Y88: =VLOOKUP($H88,ERP!$H:$AP,33,0) -> SAJITH V S (C25610), | Z88: =VLOOKUP($H88,ERP!$H:$AP,34,0) -> NA
A89: 88 | B89: SOB25002413 | C89: ENQ25017055 | D89: C45325 | E89: A027339 | F89: 40/VSL/25001472 | G89: 46099 | H89: 2567669378 | I89: MELBY MICHEAL | J89: ERTIGA | K89: MARUTI ERTIGA SMART HYBRID VXI 1.5L 5MT | L89: ELSON JACOB | M89: =VLOOKUP($L89,Emp!$A:$F,2,0) -> ANAND K V | N89: =VLOOKUP($L89,Emp!$A:$F,3,0) -> KOLENCHERY | O89: =VLOOKUP($L89,Emp!$A:$F,4,0) -> ARENA | P89: HDFC BANK LTD | Q89: HDFC | R89: IH | S89: YES | T89: =IF(_xlfn.XLOOKUP(F89,IH!Y:Y,IH!AA:AA,"")="MAPPED","MAPPED","") | U89: =IFERROR(VLOOKUP(H89,IH!C:T,18,0),"") -> MSSF DISBURSED | V89: =IF(W89<>"","DISBURSED","") -> DISBURSED | W89: =IFERROR(VLOOKUP(H89,IH!C:X,14,0),"") -> 46099 | X89: =VLOOKUP($L89,Emp!$A:$F,5,0) -> AMAL | Y89: =VLOOKUP($H89,ERP!$H:$AP,33,0) -> ELSON JACOB(C23950), | Z89: =VLOOKUP($H89,ERP!$H:$AP,34,0) -> ANAND (KLY)
A90: 89 | B90: SOB25000347 | C90: ENQ25002854 | D90: E55943 | E90: F083444 | F90: 88/VSL/25000181 | G90: 46099 | H90: 2567412820 | I90: ANS THOMAS | J90: Wagon R | K90: MARUTI WAGON R LXI 1L ISS 5MT | L90: IBIN JOSE | M90: =VLOOKUP($L90,Emp!$A:$F,2,0) -> ARUN BABU | N90: =VLOOKUP($L90,Emp!$A:$F,3,0) -> KOOTHATTUKULAM | O90: =VLOOKUP($L90,Emp!$A:$F,4,0) -> ARENA | P90: HDFC BANK LTD | Q90: HDFC | R90: IH | S90: YES | T90: =IF(_xlfn.XLOOKUP(F90,IH!Y:Y,IH!AA:AA,"")="MAPPED","MAPPED","") | U90: =IFERROR(VLOOKUP(H90,IH!C:T,18,0),"") -> NO | V90: =IF(W90<>"","DISBURSED","") -> DISBURSED | W90: =IFERROR(VLOOKUP(H90,IH!C:X,14,0),"") -> 46100 | X90: =VLOOKUP($L90,Emp!$A:$F,5,0) -> AMAL | Y90: =VLOOKUP($H90,ERP!$H:$AP,33,0) -> IBIN JOSE, Mr. | Z90: =VLOOKUP($H90,ERP!$H:$AP,34,0) -> NA
A91: 90 | B91: SOB25000233 | C91: ENQ25001977 | D91: F96933 | E91: 4592708 | F91: 126/VSL/25000118 | G91: 46100 | H91: 2567550041 | I91: HASNA BASHEER | J91: EECO | K91: MARUTI EECO CARGO AC CNG 1.2L 5MT | L91: BIJO JOY | M91: =VLOOKUP($L91,Emp!$A:$F,2,0) -> SIJO VARGHESE GEORGE | N91: =VLOOKUP($L91,Emp!$A:$F,3,0) -> PERUMBAVOOR | O91: =VLOOKUP($L91,Emp!$A:$F,4,0) -> ARENA | P91: INDUSIND BANK LTD | Q91: IBL | R91: IH | S91: NO | T91: =IF(_xlfn.XLOOKUP(F91,IH!Y:Y,IH!AA:AA,"")="MAPPED","MAPPED","") | U91: =IFERROR(VLOOKUP(H91,IH!C:T,18,0),"") -> NO | V91: =IF(W91<>"","DISBURSED","") -> DISBURSED | W91: =IFERROR(VLOOKUP(H91,IH!C:X,14,0),"") -> 46098 | X91: =VLOOKUP($L91,Emp!$A:$F,5,0) -> SALMAN | Y91: =VLOOKUP($H91,ERP!$H:$AP,33,0) -> JINTO THOMAS (C26210), | Z91: =VLOOKUP($H91,ERP!$H:$AP,34,0) -> SIJO VARGHESE GEORGE (PBVR)
A92: 91 | B92: SOB25000242 | C92: ENQ25002463 | D92: C25028 | E92: 9999363 | F92: 28/VSL/25000114 | G92: 46100 | H92: 2567586386 | I92: NOUFAL VELUTHAPARAMBIL | J92: ERTIGA | K92: MARUTI ERTIGA ZXI CNG 1.5L 5MT | L92: RISHAD K S | M92: =VLOOKUP($L92,Emp!$A:$F,2,0) -> BHAGIESH | N92: =VLOOKUP($L92,Emp!$A:$F,3,0) -> CHAVAKKAD | O92: =VLOOKUP($L92,Emp!$A:$F,4,0) -> ARENA | P92: HDFC BANK LTD | Q92: HDFC | R92: IH | S92: YES | T92: =IF(_xlfn.XLOOKUP(F92,IH!Y:Y,IH!AA:AA,"")="MAPPED","MAPPED","") -> MAPPED | U92: =IFERROR(VLOOKUP(H92,IH!C:T,18,0),"") -> MSSF DISBURSED | V92: =IF(W92<>"","DISBURSED","") -> DISBURSED | W92: =IFERROR(VLOOKUP(H92,IH!C:X,14,0),"") -> 46100 | X92: =VLOOKUP($L92,Emp!$A:$F,5,0) -> SINTO | Y92: =VLOOKUP($H92,ERP!$H:$AP,33,0) -> RISHAD K.S | Z92: =VLOOKUP($H92,ERP!$H:$AP,34,0) -> NA
A93: 92 | B93: SOB25000204 | C93: ENQ25002172 | D93: F96180 | E93: 4591470 | F93: 28/VSL/25000115 | G93: 46100 | H93: 2566911359 | I93: SAHU | J93: TOUR V | K93: MARUTI TOUR V 5 STR AC CNG 1.2L 5MT | L93: ABHIJITH K P | M93: =VLOOKUP($L93,Emp!$A:$F,2,0) -> BHAGIESH | N93: =VLOOKUP($L93,Emp!$A:$F,3,0) -> CHAVAKKAD | O93: =VLOOKUP($L93,Emp!$A:$F,4,0) -> ARENA | P93: KERALA GRAMIN BANK | Q93: KGB | R93: IH | S93: YES | T93: =IF(_xlfn.XLOOKUP(F93,IH!Y:Y,IH!AA:AA,"")="MAPPED","MAPPED","") | U93: =IFERROR(VLOOKUP(H93,IH!C:T,18,0),"") -> NO | V93: =IF(W93<>"","DISBURSED","") -> DISBURSED | W93: =IFERROR(VLOOKUP(H93,IH!C:X,14,0),"") -> 46105 | X93: =VLOOKUP($L93,Emp!$A:$F,5,0) -> SINTO | Y93: =VLOOKUP($H93,ERP!$H:$AP,33,0) -> ABHIJITH K P (C26532), | Z93: =VLOOKUP($H93,ERP!$H:$AP,34,0) -> BHAGIESH P (CHKD)
A94: 93 | B94: SOB25002427 | C94: ENQ25017107 | D94: E58319 | E94: C993024 | F94: 40/VSL/25001474 | G94: 46100 | H94: 2567692920 | I94: TINCY BABU | J94: Wagon R | K94: MARUTI WAGON R VXI 1L ISS AGS | L94: AMITH JACOB | M94: =VLOOKUP($L94,Emp!$A:$F,2,0) -> ANAND K V | N94: =VLOOKUP($L94,Emp!$A:$F,3,0) -> KOLENCHERY | O94: =VLOOKUP($L94,Emp!$A:$F,4,0) -> ARENA | P94: FEDERAL BANK LTD. | Q94: FBL | R94: IH | S94: YES | T94: =IF(_xlfn.XLOOKUP(F94,IH!Y:Y,IH!AA:AA,"")="MAPPED","MAPPED","") | U94: =IFERROR(VLOOKUP(H94,IH!C:T,18,0),"") -> NO | V94: =IF(W94<>"","DISBURSED","") -> DISBURSED | W94: =IFERROR(VLOOKUP(H94,IH!C:X,14,0),"") -> 46102 | X94: =VLOOKUP($L94,Emp!$A:$F,5,0) -> AMAL | Y94: =VLOOKUP($H94,ERP!$H:$AP,33,0) -> AMITH YACOB(C24679), | Z94: =VLOOKUP($H94,ERP!$H:$AP,34,0) -> ANAND (KLY)
A95: 94 | B95: SOB25002406 | C95: ENQ25016999 | D95: E52934 | E95: C986961 | F95: 40/VSL/25001475 | G95: 46100 | H95: 2567637892 | I95: MONCY JOY | J95: TOUR H3 | K95: MARUTI TOUR H3 CNG 1L 5MT | L95: AMAL RAJ ANTHONY | M95: =VLOOKUP($L95,Emp!$A:$F,2,0) -> RATISH K R | N95: =VLOOKUP($L95,Emp!$A:$F,3,0) -> KADAVANTHRA | O95: =VLOOKUP($L95,Emp!$A:$F,4,0) -> ARENA | P95: MAHINDRA& MAHINDRA FINANCIAL SERVICES LTD | Q95: MAHINDRA | R95: SELF | S95: NO | T95: =IF(_xlfn.XLOOKUP(F95,IH!Y:Y,IH!AA:AA,"")="MAPPED","MAPPED","") | U95: =IFERROR(VLOOKUP(H95,IH!C:T,18,0),"") | V95: =IF(W95<>"","DISBURSED","") | W95: =IFERROR(VLOOKUP(H95,IH!C:X,14,0),"") | X95: =VLOOKUP($L95,Emp!$A:$F,5,0) -> SALMAN | Y95: =VLOOKUP($H95,ERP!$H:$AP,33,0) -> AMAL RAJ ANTHONY (C22567), | Z95: =VLOOKUP($H95,ERP!$H:$AP,34,0) -> RATHEESH.K.R
A96: 95 | B96: SOB25002424 | C96: ENQ25017105 | D96: E59289 | E96: C978429 | F96: 40/VSL/25001476 | G96: 46100 | H96: 2567692716 | I96: FEBEEJA BEEVI | J96: Wagon R | K96: MARUTI WAGON R LXI 1L ISS 5MT | L96: ARUN DAS | M96: =VLOOKUP($L96,Emp!$A:$F,2,0) -> KASI VISWANATH | N96: =VLOOKUP($L96,Emp!$A:$F,3,0) -> KAIPAMANGALAM | O96: =VLOOKUP($L96,Emp!$A:$F,4,0) -> ARENA | P96: CHOLAMANDALAM INVS.& FIN.CO.LTD | Q96: CHOLA | R96: IH | S96: YES | T96: =IF(_xlfn.XLOOKUP(F96,IH!Y:Y,IH!AA:AA,"")="MAPPED","MAPPED","") | U96: =IFERROR(VLOOKUP(H96,IH!C:T,18,0),"") -> MSSF DISBURSED | V96: =IF(W96<>"","DISBURSED","") -> DISBURSED | W96: =IFERROR(VLOOKUP(H96,IH!C:X,14,0),"") -> 46095 | X96: =VLOOKUP($L96,Emp!$A:$F,5,0) -> JINEESH | Y96: =VLOOKUP($H96,ERP!$H:$AP,33,0) -> ARUN DAS K A (C26238), | Z96: =VLOOKUP($H96,ERP!$H:$AP,34,0) -> KASI VISWANATH K M
A97: 96 | B97: SOB25002339 | C97: ENQ25016669 | D97: E53601 | E97: C986974 | F97: 40/VSL/25001477 | G97: 46100 | H97: 2567546544 | I97: LINU JOSEPH M J | J97: TOUR H3 | K97: MARUTI TOUR H3 CNG 1L 5MT | L97: DINU S | M97: =VLOOKUP($L97,Emp!$A:$F,2,0) -> REJIM GEORGE | N97: =VLOOKUP($L97,Emp!$A:$F,3,0) -> FORTKOCHI | O97: =VLOOKUP($L97,Emp!$A:$F,4,0) -> ARENA | P97: CHOLAMANDALAM INVS.& FIN.CO.LTD | Q97: CHOLA | R97: IH | S97: YES | T97: =IF(_xlfn.XLOOKUP(F97,IH!Y:Y,IH!AA:AA,"")="MAPPED","MAPPED","") -> MAPPED | U97: =IFERROR(VLOOKUP(H97,IH!C:T,18,0),"") -> MSSF DISBURSED | V97: =IF(W97<>"","DISBURSED","") -> DISBURSED | W97: =IFERROR(VLOOKUP(H97,IH!C:X,14,0),"") -> 46093 | X97: =VLOOKUP($L97,Emp!$A:$F,5,0) -> SIVAPRASAD | Y97: =VLOOKUP($H97,ERP!$H:$AP,33,0) -> DINU S (C24913), | Z97: =VLOOKUP($H97,ERP!$H:$AP,34,0) -> REGIM GEORGE
A98: 97 | B98: SOB25002431 | C98: ENQ25016609 | D98: 160011 | E98: K104721 | F98: 40/VSL/25001478 | G98: 46100 | H98: 2567700889 | I98: SHAIJO THOMAS A J | J98: VICTORIS | K98: MARUTI VICTORIS ZXI 1.5L 5MT | L98: ANUKUTTAN K R | M98: =VLOOKUP($L98,Emp!$A:$F,2,0) -> NOUFAL T A | N98: =VLOOKUP($L98,Emp!$A:$F,3,0) -> EDAPPALLY | O98: =VLOOKUP($L98,Emp!$A:$F,4,0) -> ARENA | P98: CASH | Q98: FBL | R98: IH | S98: YES | T98: =IF(_xlfn.XLOOKUP(F98,IH!Y:Y,IH!AA:AA,"")="MAPPED","MAPPED","") -> MAPPED | U98: =IFERROR(VLOOKUP(H98,IH!C:T,18,0),"") -> MSSF DISBURSED | V98: =IF(W98<>"","DISBURSED","") -> DISBURSED | W98: =IFERROR(VLOOKUP(H98,IH!C:X,14,0),"") -> 46100 | X98: =VLOOKUP($L98,Emp!$A:$F,5,0) -> SIVAPRASAD | Y98: =VLOOKUP($H98,ERP!$H:$AP,33,0) -> NA | Z98: =VLOOKUP($H98,ERP!$H:$AP,34,0) -> NA
A99: 98 | B99: SOB25002241 | C99: ENQ25016130 | D99: E62523 | E99: 1435121 | F99: 40/VSL/25001479 | G99: 46100 | H99: 2567286964 | I99: AJMAL MOHAMMED | J99: TOUR H3 | K99: MARUTI TOUR H3 CNG 1L 5MT | L99: SALAS JUDE | M99: =VLOOKUP($L99,Emp!$A:$F,2,0) -> NOUFAL T A | N99: =VLOOKUP($L99,Emp!$A:$F,3,0) -> EDAPPALLY | O99: =VLOOKUP($L99,Emp!$A:$F,4,0) -> ARENA | P99: MAHINDRA& MAHINDRA FINANCIAL SERVICES LTD | Q99: MAHINDRA | R99: IH | S99: YES | T99: =IF(_xlfn.XLOOKUP(F99,IH!Y:Y,IH!AA:AA,"")="MAPPED","MAPPED","") -> MAPPED | U99: =IFERROR(VLOOKUP(H99,IH!C:T,18,0),"") -> MSSF DISBURSED | V99: =IF(W99<>"","DISBURSED","") -> DISBURSED | W99: =IFERROR(VLOOKUP(H99,IH!C:X,14,0),"") -> 46100 | X99: =VLOOKUP($L99,Emp!$A:$F,5,0) -> SIVAPRASAD | Y99: =VLOOKUP($H99,ERP!$H:$AP,33,0) -> NA | Z99: =VLOOKUP($H99,ERP!$H:$AP,34,0) -> NA
A100: 99 | B100: SOB25000398 | C100: ENQ25003159 | D100: E55420 | E100: 1428443 | F100: 72/VSL/25000156 | G100: 46100 | H100: 2567545752 | I100: AKHIL KUMAR | J100: TOUR H3 | K100: MARUTI TOUR H3 CNG 1L 5MT | L100: JAYAKRISHNAN K V | M100: =VLOOKUP($L100,Emp!$A:$F,2,0) -> BINOY RAJ | N100: =VLOOKUP($L100,Emp!$A:$F,3,0) -> KODUNGALLUR | O100: =VLOOKUP($L100,Emp!$A:$F,4,0) -> ARENA | P100: TATA CAPITAL L;IMITED | Q100: TATA | R100: IH | S100: YES | T100: =IF(_xlfn.XLOOKUP(F100,IH!Y:Y,IH!AA:AA,"")="MAPPED","MAPPED","") | U100: =IFERROR(VLOOKUP(H100,IH!C:T,18,0),"") -> MSSF LOGIN | V100: =IF(W100<>"","DISBURSED","") -> DISBURSED | W100: =IFERROR(VLOOKUP(H100,IH!C:X,14,0),"") -> 46102 | X100: =VLOOKUP($L100,Emp!$A:$F,5,0) -> JINEESH | Y100: =VLOOKUP($H100,ERP!$H:$AP,33,0) -> NA | Z100: =VLOOKUP($H100,ERP!$H:$AP,34,0) -> NA
...

Sheet IH
A1: SRL | B1: SOB NUMBER | C1: CUSTOMER ID | D1: MSSF ID | E1: DO NUMBER | F1: CUSTOMER NAME | G1: VEHICLE | H1: LOAN AMOUNT | I1: FINANCE | J1: BRANCH | K1: DSE | L1: SRM | M1: LOCATION | N1: OUTLET | O1: LOGIN DATE | P1: DISBURSED DATE | Q1: PAYOUT | R1: PAYOUT % | S1: IH STATUS | T1: MSSF STATUS | U1: CORDINATOR | V1: GST BENEFIT | W1: ADDL PAYOUT | X1: TOTAL PAYOUT | Y1: Inv_Number | Z1: Inv_Date | AA1: MAPPING STATUS | AB1: MSSF DUMP
A2: 1 | D2: 168702654 | F2: JORBIN JOSEPH | G2: ALTO K10 | H2: 400000 | I2: HDFC | K2: PRAVEEN KUMAR B | L2: =VLOOKUP($K2,Emp!$A$2:$E$347,2,0) -> ELDHO A JACOB | M2: =VLOOKUP($K2,Emp!$A$2:$E$347,3,0) -> ANGAMALY | N2: =VLOOKUP($K2,Emp!$A$2:$E$347,4,0) -> ARENA | O2: 46067 | S2: LOGIN | T2: MSSF LOGIN | U2: =VLOOKUP($K2,Emp!$A$2:$E$347,5,0) -> SALMAN | Y2: {=INDEX(RETAIL!$F:$F,MATCH(1,(RETAIL!$B:$B=B2)*(RETAIL!$N:$N=M2),0))} -> #N/A | Z2: =_xlfn.XLOOKUP(Y2,RETAIL!F:F,RETAIL!G:G) -> #N/A | AB2: =_xlfn.XLOOKUP(D2,[2]MAR!$F:$F,[2]MAR!$H:$H) -> REJECTED
A3: 2 | D3: 47439161 | F3: MARIA SHOMA MENDEZ | G3: VICTORIS | H3: 400000 | I3: SBI | K3: MANOJ C S | L3: =VLOOKUP($K3,Emp!$A$2:$E$347,2,0) -> ABHILASH K P | M3: =VLOOKUP($K3,Emp!$A$2:$E$347,3,0) -> EDAPPALLY | N3: =VLOOKUP($K3,Emp!$A$2:$E$347,4,0) -> ARENA | O3: 46069 | S3: LOGIN | T3: MSSF LOGIN | U3: =VLOOKUP($K3,Emp!$A$2:$E$347,5,0) -> SIVAPRASAD | Y3: {=INDEX(RETAIL!$F:$F,MATCH(1,(RETAIL!$B:$B=B3)*(RETAIL!$N:$N=M3),0))} -> #N/A | Z3: =_xlfn.XLOOKUP(Y3,RETAIL!F:F,RETAIL!G:G) -> #N/A | AB3: =_xlfn.XLOOKUP(D3,[2]MAR!$F:$F,[2]MAR!$H:$H) -> #N/A
A4: 3 | D4: 168762808 | F4: VALSA KURIAKOSE | G4: ERTIGA | H4: 400000 | I4: HDFC | K4: ROMINS GEORGE | L4: =VLOOKUP($K4,Emp!$A$2:$E$347,2,0) -> ARUN BABU | M4: =VLOOKUP($K4,Emp!$A$2:$E$347,3,0) -> KOOTHATTUKULAM | N4: =VLOOKUP($K4,Emp!$A$2:$E$347,4,0) -> ARENA | O4: 46070 | S4: LOGIN | T4: MSSF LOGIN | U4: =VLOOKUP($K4,Emp!$A$2:$E$347,5,0) -> AMAL | Y4: {=INDEX(RETAIL!$F:$F,MATCH(1,(RETAIL!$B:$B=B4)*(RETAIL!$N:$N=M4),0))} -> #N/A | Z4: =_xlfn.XLOOKUP(Y4,RETAIL!F:F,RETAIL!G:G) -> #N/A | AB4: =_xlfn.XLOOKUP(D4,[2]MAR!$F:$F,[2]MAR!$H:$H) -> REJECTED
A5: 4 | B5: SOB25000172 | C5: 2567691174 | D5: 260264881415 | E5: APPL16943514 | F5: SIJU P OMMEN | G5: TOUR M | H5: 996351 | I5: TATA | K5: FAIZAL K N | L5: =VLOOKUP($K5,Emp!$A$2:$E$347,2,0) -> REJIM GEORGE | M5: =VLOOKUP($K5,Emp!$A$2:$E$347,3,0) -> FORTKOCHI | N5: =VLOOKUP($K5,Emp!$A$2:$E$347,4,0) -> ARENA | O5: 46072 | P5: 46100 | S5: DISBURSED | T5: MSSF LOGIN | U5: =VLOOKUP($K5,Emp!$A$2:$E$347,5,0) -> SIVAPRASAD | Y5: {=INDEX(RETAIL!$F:$F,MATCH(1,(RETAIL!$B:$B=B5)*(RETAIL!$N:$N=M5),0))} -> 27/VSL/25000073 | Z5: =_xlfn.XLOOKUP(Y5,RETAIL!F:F,RETAIL!G:G) -> 46102 | AB5: =_xlfn.XLOOKUP(D5,[2]MAR!$F:$F,[2]MAR!$H:$H) -> #N/A
A6: 5 | D6: 260264912901 | F6: SUJITH P | G6: TOUR H3 | H6: 400000 | I6: TATA | K6: NIJIN THOMAS | L6: =VLOOKUP($K6,Emp!$A$2:$E$347,2,0) -> NOUFAL T A | M6: =VLOOKUP($K6,Emp!$A$2:$E$347,3,0) -> EDAPPALLY | N6: =VLOOKUP($K6,Emp!$A$2:$E$347,4,0) -> ARENA | O6: 46073 | S6: LOGIN | T6: MSSF LOGIN | U6: =VLOOKUP($K6,Emp!$A$2:$E$347,5,0) -> SIVAPRASAD | Y6: {=INDEX(RETAIL!$F:$F,MATCH(1,(RETAIL!$B:$B=B6)*(RETAIL!$N:$N=M6),0))} -> #N/A | Z6: =_xlfn.XLOOKUP(Y6,RETAIL!F:F,RETAIL!G:G) -> #N/A | AB6: =_xlfn.XLOOKUP(D6,[2]MAR!$F:$F,[2]MAR!$H:$H) -> REJECTED
A7: 6 | B7: SOB25000335 | C7: 2567141624 | D7: KGB_40535_0000059 | E7: KLGBH26078826371 | F7: AJITH P R | G7: ERTIGA | H7: 1000000 | I7: KGB | J7: ETTUMANOOR | K7: ARUN MATHEW | L7: =VLOOKUP($K7,Emp!$A$2:$E$347,2,0) -> ARUN BABU | M7: =VLOOKUP($K7,Emp!$A$2:$E$347,3,0) -> KOOTHATTUKULAM | N7: =VLOOKUP($K7,Emp!$A$2:$E$347,4,0) -> ARENA | O7: 46073 | P7: 46106 | Q7: =H7*R7 -> 13000 | R7: 0.013 | S7: DISBURSED | T7: MSSF LOGIN | U7: =VLOOKUP($K7,Emp!$A$2:$E$347,5,0) -> AMAL | Y7: {=INDEX(RETAIL!$F:$F,MATCH(1,(RETAIL!$B:$B=B7)*(RETAIL!$N:$N=M7),0))} -> 88/VSL/25000185 | Z7: =_xlfn.XLOOKUP(Y7,RETAIL!F:F,RETAIL!G:G) -> 46105 | AB7: =_xlfn.XLOOKUP(D7,[2]MAR!$F:$F,[2]MAR!$H:$H) -> APPLIED
A8: 7 | D8: M0033645 | F8: K P THOMAS | G8: Wagon R | H8: 400000 | I8: CANARA | K8: LANEESH A S | L8: =VLOOKUP($K8,Emp!$A$2:$E$347,2,0) -> MANU SASI | M8: =VLOOKUP($K8,Emp!$A$2:$E$347,3,0) -> EDAPPALLY | N8: =VLOOKUP($K8,Emp!$A$2:$E$347,4,0) -> ARENA | O8: 46073 | S8: LOGIN | T8: MSSF LOGIN | U8: =VLOOKUP($K8,Emp!$A$2:$E$347,5,0) -> SIVAPRASAD | Y8: {=INDEX(RETAIL!$F:$F,MATCH(1,(RETAIL!$B:$B=B8)*(RETAIL!$N:$N=M8),0))} -> #N/A | Z8: =_xlfn.XLOOKUP(Y8,RETAIL!F:F,RETAIL!G:G) -> #N/A | AB8: =_xlfn.XLOOKUP(D8,[2]MAR!$F:$F,[2]MAR!$H:$H) -> APPLIED
A9: 8 | B9: SOB25002088 | C9: 2566948355 | D9: 19174523 | E9: 17223571 | F9: RESMIMOL R | G9: Wagon R | H9: 471466 | I9: CHOLA | K9: ALBIN MARTIN | L9: =VLOOKUP($K9,Emp!$A$2:$E$347,2,0) -> RATISH K R | M9: =VLOOKUP($K9,Emp!$A$2:$E$347,3,0) -> KADAVANTHRA | N9: =VLOOKUP($K9,Emp!$A$2:$E$347,4,0) -> ARENA | O9: 46076 | P9: 46092 | S9: DISBURSED | T9: MSSF DISBURSED | U9: =VLOOKUP($K9,Emp!$A$2:$E$347,5,0) -> SALMAN | Y9: {=INDEX(RETAIL!$F:$F,MATCH(1,(RETAIL!$B:$B=B9)*(RETAIL!$N:$N=M9),0))} -> 40/VSL/25001429 | Z9: =_xlfn.XLOOKUP(Y9,RETAIL!F:F,RETAIL!G:G) -> 46090 | AA9: NAME CHANGE | AB9: DISBURSED
A10: 9 | B10: SOB25002179 | C10: 2567608985 | D10: 47689647 | E10: 44993804822 | F10: KISHORE KUMAR S MENON | G10: BREZZA | H10: 768500 | I10: SBI | J10: LISSIE HOSPITAL | K10: ABHILASH P C | L10: =VLOOKUP($K10,Emp!$A$2:$E$347,2,0) -> ABHILASH K P | M10: =VLOOKUP($K10,Emp!$A$2:$E$347,3,0) -> EDAPPALLY | N10: =VLOOKUP($K10,Emp!$A$2:$E$347,4,0) -> ARENA | O10: 46078 | P10: 46093 | Q10: =H10*R10 -> 15370 | R10: 0.02 | S10: DISBURSED | T10: MSSF LOGIN | U10: =VLOOKUP($K10,Emp!$A$2:$E$347,5,0) -> SIVAPRASAD | Y10: {=INDEX(RETAIL!$F:$F,MATCH(1,(RETAIL!$B:$B=B10)*(RETAIL!$N:$N=M10),0))} -> 40/VSL/25001459 | Z10: =_xlfn.XLOOKUP(Y10,RETAIL!F:F,RETAIL!G:G) -> 46095 | AB10: =_xlfn.XLOOKUP(D10,[2]MAR!$F:$F,[2]MAR!$H:$H) -> UNDER PROCESS
A11: 10 | D11: 260265068367 | F11: BINI | G11: TOUR S | H11: 400000 | I11: TATA | K11: ANUKUTTAN K R | L11: =VLOOKUP($K11,Emp!$A$2:$E$347,2,0) -> NOUFAL T A | M11: =VLOOKUP($K11,Emp!$A$2:$E$347,3,0) -> EDAPPALLY | N11: =VLOOKUP($K11,Emp!$A$2:$E$347,4,0) -> ARENA | O11: 46079 | S11: LOGIN | T11: MSSF LOGIN | U11: =VLOOKUP($K11,Emp!$A$2:$E$347,5,0) -> SIVAPRASAD | Y11: {=INDEX(RETAIL!$F:$F,MATCH(1,(RETAIL!$B:$B=B11)*(RETAIL!$N:$N=M11),0))} -> #N/A | Z11: =_xlfn.XLOOKUP(Y11,RETAIL!F:F,RETAIL!G:G) -> #N/A | AB11: =_xlfn.XLOOKUP(D11,[2]MAR!$F:$F,[2]MAR!$H:$H) -> #N/A
A12: 11 | D12: UBI1772435790558 | F12: SUNITHA | G12: Wagon R | H12: 400000 | I12: UBI | K12: SREENATH R PRABHU | L12: =VLOOKUP($K12,Emp!$A$2:$E$347,2,0) -> NOUFAL T A | M12: =VLOOKUP($K12,Emp!$A$2:$E$347,3,0) -> EDAPPALLY | N12: =VLOOKUP($K12,Emp!$A$2:$E$347,4,0) -> ARENA | O12: 46086 | S12: LOGIN | T12: MSSF LOGIN | U12: =VLOOKUP($K12,Emp!$A$2:$E$347,5,0) -> SIVAPRASAD | Y12: {=INDEX(RETAIL!$F:$F,MATCH(1,(RETAIL!$B:$B=B12)*(RETAIL!$N:$N=M12),0))} -> #N/A | Z12: =_xlfn.XLOOKUP(Y12,RETAIL!F:F,RETAIL!G:G) -> #N/A | AB12: =_xlfn.XLOOKUP(D12,[2]MAR!$F:$F,[2]MAR!$H:$H) -> APPLIED
A13: 12 | B13: SOB25002236 | C13: 2567274675 | D13: KGB_40670_0000109 | E13: KLGBH26069815694 | F13: MIDHUN SURESH | G13: TOUR H3 | H13: 544000 | I13: KGB | J13: CHERANALLUR | K13: LANEESH A S | L13: =VLOOKUP($K13,Emp!$A$2:$E$347,2,0) -> MANU SASI | M13: =VLOOKUP($K13,Emp!$A$2:$E$347,3,0) -> EDAPPALLY | N13: =VLOOKUP($K13,Emp!$A$2:$E$347,4,0) -> ARENA | O13: 46086 | P13: 46091 | Q13: =H13*R13 -> 7072 | R13: 0.013 | S13: DISBURSED | T13: MSSF DISBURSED | U13: =VLOOKUP($K13,Emp!$A$2:$E$347,5,0) -> SIVAPRASAD | Y13: {=INDEX(RETAIL!$F:$F,MATCH(1,(RETAIL!$B:$B=B13)*(RETAIL!$N:$N=M13),0))} -> 40/VSL/25001451 | Z13: =_xlfn.XLOOKUP(Y13,RETAIL!F:F,RETAIL!G:G) -> 46094 | AA13: MAPPED | AB13: =_xlfn.XLOOKUP(D13,[2]MAR!$F:$F,[2]MAR!$H:$H) -> DISBURSED
A14: 13 | B14: SOB25002194 | C14: 2567186125 | D14: KGB_40266_0000110 | E14: KLGBH26064809418 | F14: RAMESH PATHARI | G14: TOUR H3 | H14: 550000 | I14: KGB | J14: PUTHUR PALAKKAD | K14: MANU JOY | L14: =VLOOKUP($K14,Emp!$A$2:$E$347,2,0) -> MANU SASI | M14: =VLOOKUP($K14,Emp!$A$2:$E$347,3,0) -> EDAPPALLY | N14: =VLOOKUP($K14,Emp!$A$2:$E$347,4,0) -> ARENA | O14: 46086 | P14: 46086 | Q14: =H14*R14 -> 7150 | R14: 0.013 | S14: DISBURSED | T14: MSSF LOGIN | U14: =VLOOKUP($K14,Emp!$A$2:$E$347,5,0) -> SIVAPRASAD | Y14: {=INDEX(RETAIL!$F:$F,MATCH(1,(RETAIL!$B:$B=B14)*(RETAIL!$N:$N=M14),0))} -> 40/VSL/25001418 | Z14: =_xlfn.XLOOKUP(Y14,RETAIL!F:F,RETAIL!G:G) -> 46087 | AB14: =_xlfn.XLOOKUP(D14,[2]MAR!$F:$F,[2]MAR!$H:$H) -> REJECTED
A15: 14 | D15: 260365211203 | F15: GEORGY JAMES | G15: TOUR H3 | H15: 400000 | I15: TATA | K15: RIYAS | L15: =VLOOKUP($K15,Emp!$A$2:$E$347,2,0) -> SHEMEER A K | M15: =VLOOKUP($K15,Emp!$A$2:$E$347,3,0) -> EDAPPALLY | N15: =VLOOKUP($K15,Emp!$A$2:$E$347,4,0) -> ARENA | O15: 46086 | S15: LOGIN | T15: MSSF LOGIN | U15: =VLOOKUP($K15,Emp!$A$2:$E$347,5,0) -> SIVAPRASAD | Y15: {=INDEX(RETAIL!$F:$F,MATCH(1,(RETAIL!$B:$B=B15)*(RETAIL!$N:$N=M15),0))} -> #N/A | Z15: =_xlfn.XLOOKUP(Y15,RETAIL!F:F,RETAIL!G:G) -> #N/A | AB15: =_xlfn.XLOOKUP(D15,[2]MAR!$F:$F,[2]MAR!$H:$H) -> #N/A
A16: 15 | B16: SOB25002080 | C16: 2567479837 | D16: KGB_40634_0000112 | E16: KLGBH26066812497 | F16: SIRAJ N | G16: TOUR H3 | H16: 540186 | I16: KGB | J16: THRIKKAKKARA | K16: JAYESH | L16: =VLOOKUP($K16,Emp!$A$2:$E$347,2,0) -> SHEMEER A K | M16: =VLOOKUP($K16,Emp!$A$2:$E$347,3,0) -> EDAPPALLY | N16: =VLOOKUP($K16,Emp!$A$2:$E$347,4,0) -> ARENA | O16: 46086 | P16: 46088 | Q16: =H16*R16 -> 7022.418 | R16: 0.013 | S16: DISBURSED | T16: MSSF DISBURSED | U16: =VLOOKUP($K16,Emp!$A$2:$E$347,5,0) -> SIVAPRASAD | Y16: {=INDEX(RETAIL!$F:$F,MATCH(1,(RETAIL!$B:$B=B16)*(RETAIL!$N:$N=M16),0))} -> 40/VSL/25001421 | Z16: =_xlfn.XLOOKUP(Y16,RETAIL!F:F,RETAIL!G:G) -> 46088 | AA16: MAPPED | AB16: =_xlfn.XLOOKUP(D16,[2]MAR!$F:$F,[2]MAR!$H:$H) -> DISBURSED
A17: 16 | B17: SOB25002229 | C17: 2567549960 | D17: 169077417 | E17: 169077417 | F17: BENZIR DUTT A S | G17: Wagon R | H17: 498536 | I17: HDFC | K17: RATHEESH K B | L17: =VLOOKUP($K17,Emp!$A$2:$E$347,2,0) -> PRANOOB V NAIR | M17: =VLOOKUP($K17,Emp!$A$2:$E$347,3,0) -> TRIPPUNITHURA | N17: =VLOOKUP($K17,Emp!$A$2:$E$347,4,0) -> ARENA | O17: 46087 | P17: 46091 | S17: DISBURSED | T17: MSSF DISBURSED | U17: =VLOOKUP($K17,Emp!$A$2:$E$347,5,0) -> SIVAPRASAD | Y17: {=INDEX(RETAIL!$F:$F,MATCH(1,(RETAIL!$B:$B=B17)*(RETAIL!$N:$N=M17),0))} -> 40/VSL/25001437 | Z17: =_xlfn.XLOOKUP(Y17,RETAIL!F:F,RETAIL!G:G) -> 46092 | AA17: MAPPED | AB17: =_xlfn.XLOOKUP(D17,[2]MAR!$F:$F,[2]MAR!$H:$H) -> DISBURSED
A18: 17 | B18: SOB25001842 | C18: 2566534647 | D18: NIL | E18: UBINR22026030501592844 | F18: BALAKRISHNAN N V | G18: Wagon R | H18: 563446 | I18: UBI | J18: PATTURAIKKAL | K18: SANJAY | L18: =VLOOKUP($K18,Emp!$A$2:$E$347,2,0) -> SIVAPRAKASH K S | M18: =VLOOKUP($K18,Emp!$A$2:$E$347,3,0) -> THRISSUR | N18: =VLOOKUP($K18,Emp!$A$2:$E$347,4,0) -> ARENA | O18: 46087 | P18: 46087 | S18: DISBURSED | T18: NO | U18: =VLOOKUP($K18,Emp!$A$2:$E$347,5,0) -> SINTO | Y18: {=INDEX(RETAIL!$F:$F,MATCH(1,(RETAIL!$B:$B=B18)*(RETAIL!$N:$N=M18),0))} -> 40/VSL/25001425 | Z18: =_xlfn.XLOOKUP(Y18,RETAIL!F:F,RETAIL!G:G) -> 46090 | AB18: =_xlfn.XLOOKUP(D18,[2]MAR!$F:$F,[2]MAR!$H:$H) -> #N/A
A19: 18 | B19: SOB25002316 | C19: 2567449123 | D19: 19471203 | E19: 17677305 | F19: SUBHIJITH V S | G19: Wagon R | H19: 500000 | I19: CHOLA | K19: JAYAKRISHNAN K V | L19: =VLOOKUP($K19,Emp!$A$2:$E$347,2,0) -> BINOY RAJ | M19: =VLOOKUP($K19,Emp!$A$2:$E$347,3,0) -> KODUNGALLUR | N19: =VLOOKUP($K19,Emp!$A$2:$E$347,4,0) -> ARENA | O19: 46087 | P19: 46087 | S19: DISBURSED | T19: MSSF DISBURSED | U19: =VLOOKUP($K19,Emp!$A$2:$E$347,5,0) -> JINEESH | Y19: {=INDEX(RETAIL!$F:$F,MATCH(1,(RETAIL!$B:$B=B19)*(RETAIL!$N:$N=M19),0))} -> 40/VSL/25001420 | Z19: =_xlfn.XLOOKUP(Y19,RETAIL!F:F,RETAIL!G:G) -> 46088 | AA19: MAPPED | AB19: =_xlfn.XLOOKUP(D19,[2]MAR!$F:$F,[2]MAR!$H:$H) -> DISBURSED
A20: 19 | B20: SOB25002323 | C20: 2567483180 | D20: 168960707 | E20: 168960707 | F20: NUSAIBA JAMALUDHEEN | G20: ERTIGA | H20: 1008186 | I20: HDFC | K20: RAGIL N R | L20: =VLOOKUP($K20,Emp!$A$2:$E$347,2,0) -> VIBIN I B | M20: =VLOOKUP($K20,Emp!$A$2:$E$347,3,0) -> KAIPAMANGALAM | N20: =VLOOKUP($K20,Emp!$A$2:$E$347,4,0) -> STUDIO | O20: 46087 | P20: 46087 | S20: DISBURSED | T20: MSSF DISBURSED | U20: =VLOOKUP($K20,Emp!$A$2:$E$347,5,0) -> JINEESH | Y20: {=INDEX(RETAIL!$F:$F,MATCH(1,(RETAIL!$B:$B=B20)*(RETAIL!$N:$N=M20),0))} -> 40/VSL/25001426 | Z20: =_xlfn.XLOOKUP(Y20,RETAIL!F:F,RETAIL!G:G) -> 46090 | AA20: NAME CHANGE | AB20: =_xlfn.XLOOKUP(D20,[2]MAR!$F:$F,[2]MAR!$H:$H) -> DISBURSED
A21: 20 | D21: 168739156 | F21: LITHIN TOGY | G21: Wagon R | H21: 400000 | I21: MAHINDRA | K21: VISHNU RAJU | L21: =VLOOKUP($K21,Emp!$A$2:$E$347,2,0) -> SIJO VARGHESE GEORGE | M21: =VLOOKUP($K21,Emp!$A$2:$E$347,3,0) -> PERUMBAVOOR | N21: =VLOOKUP($K21,Emp!$A$2:$E$347,4,0) -> ARENA | O21: 46087 | S21: LOGIN | T21: MSSF LOGIN | U21: =VLOOKUP($K21,Emp!$A$2:$E$347,5,0) -> SALMAN | Y21: {=INDEX(RETAIL!$F:$F,MATCH(1,(RETAIL!$B:$B=B21)*(RETAIL!$N:$N=M21),0))} -> #N/A | Z21: =_xlfn.XLOOKUP(Y21,RETAIL!F:F,RETAIL!G:G) -> #N/A | AB21: =_xlfn.XLOOKUP(D21,[2]MAR!$F:$F,[2]MAR!$H:$H) -> UNDER PROCESS
A22: 21 | D22: R-07339491-L | F22: MADHU KUMAR T S | G22: Wagon R | H22: 400000 | I22: ICICI | K22: PRAVEEN KUMAR B | L22: =VLOOKUP($K22,Emp!$A$2:$E$347,2,0) -> ELDHO A JACOB | M22: =VLOOKUP($K22,Emp!$A$2:$E$347,3,0) -> ANGAMALY | N22: =VLOOKUP($K22,Emp!$A$2:$E$347,4,0) -> ARENA | O22: 46087 | S22: LOGIN | T22: MSSF LOGIN | U22: =VLOOKUP($K22,Emp!$A$2:$E$347,5,0) -> SALMAN | Y22: {=INDEX(RETAIL!$F:$F,MATCH(1,(RETAIL!$B:$B=B22)*(RETAIL!$N:$N=M22),0))} -> #N/A | Z22: =_xlfn.XLOOKUP(Y22,RETAIL!F:F,RETAIL!G:G) -> #N/A | AB22: =_xlfn.XLOOKUP(D22,[2]MAR!$F:$F,[2]MAR!$H:$H) -> REJECTED
A23: 22 | B23: SOB25002150 | C23: 2567087596 | D23: NIL | E23: KLGBH26065810703 | F23: JAMSHEER P A | G23: TOUR H3 | H23: 550086 | I23: KGB | J23: VADANAPILLY | K23: SANJAY | L23: =VLOOKUP($K23,Emp!$A$2:$E$347,2,0) -> SIVAPRAKASH K S | M23: =VLOOKUP($K23,Emp!$A$2:$E$347,3,0) -> THRISSUR | N23: =VLOOKUP($K23,Emp!$A$2:$E$347,4,0) -> ARENA | O23: 46087 | P23: 46087 | Q23: =H23*R23 -> 7151.118 | R23: 0.013 | S23: DISBURSED | T23: NO | U23: =VLOOKUP($K23,Emp!$A$2:$E$347,5,0) -> SINTO | Y23: {=INDEX(RETAIL!$F:$F,MATCH(1,(RETAIL!$B:$B=B23)*(RETAIL!$N:$N=M23),0))} -> 40/VSL/25001416 | Z23: =_xlfn.XLOOKUP(Y23,RETAIL!F:F,RETAIL!G:G) -> 46087 | AB23: =_xlfn.XLOOKUP(D23,[2]MAR!$F:$F,[2]MAR!$H:$H) -> #N/A
A24: 23 | B24: SOB25001937 | C24: 2566746837 | D24: NIL | E24: KLGBH26064810356 | F24: SHIBIN K B | G24: TOUR H3 | H24: 616714 | I24: KGB | K24: BINEESH P ANTO | L24: =VLOOKUP($K24,Emp!$A$2:$E$347,2,0) -> SIVAPRAKASH K S | M24: =VLOOKUP($K24,Emp!$A$2:$E$347,3,0) -> THRISSUR | N24: =VLOOKUP($K24,Emp!$A$2:$E$347,4,0) -> ARENA | O24: 46087 | P24: 46087 | Q24: =H24*R24 -> 8017.282 | R24: 0.013 | S24: DISBURSED | T24: NO | U24: =VLOOKUP($K24,Emp!$A$2:$E$347,5,0) -> SINTO | Y24: {=INDEX(RETAIL!$F:$F,MATCH(1,(RETAIL!$B:$B=B24)*(RETAIL!$N:$N=M24),0))} -> 40/VSL/25001415 | Z24: =_xlfn.XLOOKUP(Y24,RETAIL!F:F,RETAIL!G:G) -> 46087 | AB24: =_xlfn.XLOOKUP(D24,[2]MAR!$F:$F,[2]MAR!$H:$H) -> #N/A
A25: 24 | B25: SOB25000379 | C25: 2567473596 | D25: NIL | E25: BKIDY26064208756 | F25: AMBROSE A T | G25: BREZZA | H25: 1000000 | I25: BOI | J25: PALLIPURAM | K25: KRISHNARAJ | L25: =VLOOKUP($K25,Emp!$A$2:$E$347,2,0) -> SACHIN | M25: =VLOOKUP($K25,Emp!$A$2:$E$347,3,0) -> KODUNGALLUR | N25: =VLOOKUP($K25,Emp!$A$2:$E$347,4,0) -> ARENA | O25: 46087 | P25: 46087 | Q25: =H25*R25 -> 12500 | R25: 0.0125 | S25: DISBURSED | T25: NO | U25: =VLOOKUP($K25,Emp!$A$2:$E$347,5,0) -> JINEESH | Y25: {=INDEX(RETAIL!$F:$F,MATCH(1,(RETAIL!$B:$B=B25)*(RETAIL!$N:$N=M25),0))} -> 72/VSL/25000154 | Z25: =_xlfn.XLOOKUP(Y25,RETAIL!F:F,RETAIL!G:G) -> 46088 | AB25: =_xlfn.XLOOKUP(D25,[2]MAR!$F:$F,[2]MAR!$H:$H) -> #N/A
A26: 25 | B26: SOB25002344 | C26: 2567515064 | D26: NIL | E26: KLGBH26064744737 | F26: SANTHOSHKUMAR E K | G26: EECO | H26: 500000 | I26: KGB | J26: CHOONDAL | K26: RISHAD K S | L26: =VLOOKUP($K26,Emp!$A$2:$E$347,2,0) -> BHAGIESH | M26: =VLOOKUP($K26,Emp!$A$2:$E$347,3,0) -> CHAVAKKAD | N26: =VLOOKUP($K26,Emp!$A$2:$E$347,4,0) -> ARENA | O26: 46087 | P26: 46087 | Q26: =H26*R26 -> 6500 | R26: 0.013 | S26: DISBURSED | T26: NO | U26: =VLOOKUP($K26,Emp!$A$2:$E$347,5,0) -> SINTO | Y26: {=INDEX(RETAIL!$F:$F,MATCH(1,(RETAIL!$B:$B=B26)*(RETAIL!$N:$N=M26),0))} -> 40/VSL/25001443 | Z26: =_xlfn.XLOOKUP(Y26,RETAIL!F:F,RETAIL!G:G) -> 46093 | AB26: =_xlfn.XLOOKUP(D26,[2]MAR!$F:$F,[2]MAR!$H:$H) -> #N/A
A27: 26 | B27: SOB25002273 | C27: 2567354817 | D27: KGB_40537_0000124 | E27: KLGBH26065811691 | F27: VINOD KUMAR | G27: TOUR H3 | H27: 540000 | I27: KGB | J27: KALOOR | K27: SREENATH R PRABHU | L27: =VLOOKUP($K27,Emp!$A$2:$E$347,2,0) -> NOUFAL T A | M27: =VLOOKUP($K27,Emp!$A$2:$E$347,3,0) -> EDAPPALLY | N27: =VLOOKUP($K27,Emp!$A$2:$E$347,4,0) -> ARENA | O27: 46087 | P27: 46088 | Q27: =H27*R27 -> 7020 | R27: 0.013 | S27: DISBURSED | T27: MSSF DISBURSED | U27: =VLOOKUP($K27,Emp!$A$2:$E$347,5,0) -> SIVAPRASAD | Y27: {=INDEX(RETAIL!$F:$F,MATCH(1,(RETAIL!$B:$B=B27)*(RETAIL!$N:$N=M27),0))} -> 40/VSL/25001428 | Z27: =_xlfn.XLOOKUP(Y27,RETAIL!F:F,RETAIL!G:G) -> 46090 | AA27: MAPPED | AB27: =_xlfn.XLOOKUP(D27,[2]MAR!$F:$F,[2]MAR!$H:$H) -> DISBURSED
A28: 27 | B28: SOB25000200 | C28: 2567435685 | D28: R-07339635-L | E28: LAKOM0002101302 | F28: AJEESH MATHEW GEORGE | G28: DZIRE | H28: 929746 | I28: ICICI | K28: MIRAJ KAREEM | L28: =VLOOKUP($K28,Emp!$A$2:$E$347,2,0) -> JESTIN UTHUP JOHN | M28: =VLOOKUP($K28,Emp!$A$2:$E$347,3,0) -> PIRAVOM | N28: =VLOOKUP($K28,Emp!$A$2:$E$347,4,0) -> ARENA | O28: 46088 | P28: 46088 | S28: DISBURSED | T28: MSSF DISBURSED | U28: =VLOOKUP($K28,Emp!$A$2:$E$347,5,0) -> AMAL | Y28: {=INDEX(RETAIL!$F:$F,MATCH(1,(RETAIL!$B:$B=B28)*(RETAIL!$N:$N=M28),0))} -> 118/VSL25000097 | Z28: =_xlfn.XLOOKUP(Y28,RETAIL!F:F,RETAIL!G:G) -> 46088 | AA28: MAPPED | AB28: =_xlfn.XLOOKUP(D28,[2]MAR!$F:$F,[2]MAR!$H:$H) -> DISBURSED
A29: 28 | B29: SOB25002339 | C29: 2567546544 | D29: 19506097 | E29: 17729962 | F29: LINU JOSEPH M J | G29: TOUR H3 | H29: 480250 | I29: CHOLA | K29: DINU S | L29: =VLOOKUP($K29,Emp!$A$2:$E$347,2,0) -> REJIM GEORGE | M29: =VLOOKUP($K29,Emp!$A$2:$E$347,3,0) -> FORTKOCHI | N29: =VLOOKUP($K29,Emp!$A$2:$E$347,4,0) -> ARENA | O29: 46088 | P29: 46093 | S29: DISBURSED | T29: MSSF DISBURSED | U29: =VLOOKUP($K29,Emp!$A$2:$E$347,5,0) -> SIVAPRASAD | Y29: {=INDEX(RETAIL!$F:$F,MATCH(1,(RETAIL!$B:$B=B29)*(RETAIL!$N:$N=M29),0))} -> 40/VSL/25001477 | Z29: =_xlfn.XLOOKUP(Y29,RETAIL!F:F,RETAIL!G:G) -> 46100 | AA29: MAPPED | AB29: DISBURSED
A30: 29 | B30: SOB25002331 | C30: 2567497252 | D30: NIL | E30: UBINR220260701807595 | F30: AKHIL VINOD | G30: Wagon R | H30: 300000 | I30: UBI | J30: POOTHOTTA | K30: NIKESHKRISHNA P S | L30: =VLOOKUP($K30,Emp!$A$2:$E$347,2,0) -> BINOY RAJ | M30: =VLOOKUP($K30,Emp!$A$2:$E$347,3,0) -> KODUNGALLUR | N30: =VLOOKUP($K30,Emp!$A$2:$E$347,4,0) -> ARENA | O30: 46087 | P30: 46088 | Q30: =H30*R30 -> 3900 | R30: 0.013 | S30: DISBURSED | T30: NO | U30: =VLOOKUP($K30,Emp!$A$2:$E$347,5,0) -> JINEESH | Y30: {=INDEX(RETAIL!$F:$F,MATCH(1,(RETAIL!$B:$B=B30)*(RETAIL!$N:$N=M30),0))} -> 40/VSL/25001431 | Z30: =_xlfn.XLOOKUP(Y30,RETAIL!F:F,RETAIL!G:G) -> 46090 | AB30: =_xlfn.XLOOKUP(D30,[2]MAR!$F:$F,[2]MAR!$H:$H) -> #N/A
A31: 30 | B31: SOB25000223 | C31: 2567445237 | D31: 19499583 | E31: 17720624 | F31: PRAMOD UNNIKRISHNAN | G31: EECO | H31: 575000 | I31: CHOLA | K31: NYGIL GEORGE | L31: =VLOOKUP($K31,Emp!$A$2:$E$347,2,0) -> SIJO VARGHESE GEORGE | M31: =VLOOKUP($K31,Emp!$A$2:$E$347,3,0) -> PERUMBAVOOR | N31: =VLOOKUP($K31,Emp!$A$2:$E$347,4,0) -> ARENA | O31: 46088 | P31: 46088 | S31: DISBURSED | T31: MSSF DISBURSED | U31: =VLOOKUP($K31,Emp!$A$2:$E$347,5,0) -> SALMAN | Y31: {=INDEX(RETAIL!$F:$F,MATCH(1,(RETAIL!$B:$B=B31)*(RETAIL!$N:$N=M31),0))} -> 126/VSL/25000113 | Z31: =_xlfn.XLOOKUP(Y31,RETAIL!F:F,RETAIL!G:G) -> 46090 | AA31: NAME CHANGE | AB31: =_xlfn.XLOOKUP(D31,[2]MAR!$F:$F,[2]MAR!$H:$H) -> DISBURSED
A32: 31 | B32: SOB25002319 | C32: 2567480248 | D32: R-07338854-L | E32: LACOC00052104460 | F32: SANUJ JOSEPH | G32: ALTO K10 | H32: 447746 | I32: ICICI | K32: ELSON JACOB | L32: =VLOOKUP($K32,Emp!$A$2:$E$347,2,0) -> ANAND K V | M32: =VLOOKUP($K32,Emp!$A$2:$E$347,3,0) -> KOLENCHERY | N32: =VLOOKUP($K32,Emp!$A$2:$E$347,4,0) -> ARENA | O32: 46088 | P32: 46090 | S32: DISBURSED | T32: MSSF DISBURSED | U32: =VLOOKUP($K32,Emp!$A$2:$E$347,5,0) -> AMAL | Y32: {=INDEX(RETAIL!$F:$F,MATCH(1,(RETAIL!$B:$B=B32)*(RETAIL!$N:$N=M32),0))} -> 40/VSL/25001423 | Z32: =_xlfn.XLOOKUP(Y32,RETAIL!F:F,RETAIL!G:G) -> 46088 | AA32: MAPPED | AB32: =_xlfn.XLOOKUP(D32,[2]MAR!$F:$F,[2]MAR!$H:$H) -> DISBURSED
A33: 32 | B33: SOB25000241 | C33: 2567479764 | D33: 19483942 | E33: 17696880 | F33: CHANDRASEKHAR P M | G33: EECO | H33: 590000 | I33: CHOLA | K33: SOORAJ K S | L33: =VLOOKUP($K33,Emp!$A$2:$E$347,2,0) -> ANAND K V | M33: =VLOOKUP($K33,Emp!$A$2:$E$347,3,0) -> KOLENCHERY | N33: =VLOOKUP($K33,Emp!$A$2:$E$347,4,0) -> ARENA | O33: 46088 | P33: 46091 | S33: DISBURSED | T33: MSSF DISBURSED | U33: =VLOOKUP($K33,Emp!$A$2:$E$347,5,0) -> AMAL | Y33: {=INDEX(RETAIL!$F:$F,MATCH(1,(RETAIL!$B:$B=B33)*(RETAIL!$N:$N=M33),0))} -> 255/VSL/25000100 | Z33: =_xlfn.XLOOKUP(Y33,RETAIL!F:F,RETAIL!G:G) -> 46091 | AA33: MAPPED | AB33: =_xlfn.XLOOKUP(D33,[2]MAR!$F:$F,[2]MAR!$H:$H) -> DISBURSED
A34: 33 | D34: 260365319895 | F34: ANIL JOSEPH | G34: TOUR H3 | H34: 400000 | I34: TATA | K34: MANOJ C S | L34: =VLOOKUP($K34,Emp!$A$2:$E$347,2,0) -> ABHILASH K P | M34: =VLOOKUP($K34,Emp!$A$2:$E$347,3,0) -> EDAPPALLY | N34: =VLOOKUP($K34,Emp!$A$2:$E$347,4,0) -> ARENA | O34: 46091 | S34: LOGIN | T34: MSSF LOGIN | U34: =VLOOKUP($K34,Emp!$A$2:$E$347,5,0) -> SIVAPRASAD | Y34: {=INDEX(RETAIL!$F:$F,MATCH(1,(RETAIL!$B:$B=B34)*(RETAIL!$N:$N=M34),0))} -> #N/A | Z34: =_xlfn.XLOOKUP(Y34,RETAIL!F:F,RETAIL!G:G) -> #N/A | AB34: =_xlfn.XLOOKUP(D34,[2]MAR!$F:$F,[2]MAR!$H:$H) -> #N/A
A35: 34 | D35: 169183768 | F35: CHARLES P R | G35: Wagon R | H35: 400000 | I35: HDFC | K35: FAIZAL K N | L35: =VLOOKUP($K35,Emp!$A$2:$E$347,2,0) -> REJIM GEORGE | M35: =VLOOKUP($K35,Emp!$A$2:$E$347,3,0) -> FORTKOCHI | N35: =VLOOKUP($K35,Emp!$A$2:$E$347,4,0) -> ARENA | O35: 46091 | S35: LOGIN | T35: MSSF LOGIN | U35: =VLOOKUP($K35,Emp!$A$2:$E$347,5,0) -> SIVAPRASAD | Y35: {=INDEX(RETAIL!$F:$F,MATCH(1,(RETAIL!$B:$B=B35)*(RETAIL!$N:$N=M35),0))} -> #N/A | Z35: =_xlfn.XLOOKUP(Y35,RETAIL!F:F,RETAIL!G:G) -> #N/A | AB35: =_xlfn.XLOOKUP(D35,[2]MAR!$F:$F,[2]MAR!$H:$H) -> SANCTIONED
A36: 35 | D36: 47940205 | F36: DIVYA L R | G36: DZIRE | H36: 400000 | I36: SBI | K36: MANOJ C S | L36: =VLOOKUP($K36,Emp!$A$2:$E$347,2,0) -> ABHILASH K P | M36: =VLOOKUP($K36,Emp!$A$2:$E$347,3,0) -> EDAPPALLY | N36: =VLOOKUP($K36,Emp!$A$2:$E$347,4,0) -> ARENA | O36: 46091 | S36: LOGIN | T36: MSSF LOGIN | U36: =VLOOKUP($K36,Emp!$A$2:$E$347,5,0) -> SIVAPRASAD | Y36: {=INDEX(RETAIL!$F:$F,MATCH(1,(RETAIL!$B:$B=B36)*(RETAIL!$N:$N=M36),0))} -> #N/A | Z36: =_xlfn.XLOOKUP(Y36,RETAIL!F:F,RETAIL!G:G) -> #N/A | AB36: =_xlfn.XLOOKUP(D36,[2]MAR!$F:$F,[2]MAR!$H:$H) -> SANCTIONED
A37: 36 | B37: SOB25002378 | C37: 2567547876 | D37: 19516231 | E37: 17745522 | F37: KRISHNAPRIYA K B | G37: TOUR S | H37: 635000 | I37: CHOLA | K37: SAJITH V S | L37: =VLOOKUP($K37,Emp!$A$2:$E$347,2,0) -> VIBIN I B | M37: =VLOOKUP($K37,Emp!$A$2:$E$347,3,0) -> KAIPAMANGALAM | N37: =VLOOKUP($K37,Emp!$A$2:$E$347,4,0) -> ARENA | O37: 46092 | P37: 46092 | S37: DISBURSED | T37: MSSF DISBURSED | U37: =VLOOKUP($K37,Emp!$A$2:$E$347,5,0) -> JINEESH | Y37: {=INDEX(RETAIL!$F:$F,MATCH(1,(RETAIL!$B:$B=B37)*(RETAIL!$N:$N=M37),0))} -> 40/VSL/25001471 | Z37: =_xlfn.XLOOKUP(Y37,RETAIL!F:F,RETAIL!G:G) -> 46099 | AA37: MAPPED | AB37: DISBURSED
A38: 37 | B38: SOB25002280 | C38: 2567368472 | D38: 260365263619 | E38: APPL17002137 | F38: SUNIL CHANDRAN P | G38: TOUR H3 | H38: 537330 | I38: TATA | K38: VISHNUDAS P D | L38: =VLOOKUP($K38,Emp!$A$2:$E$347,2,0) -> SIVAPRAKASH K S | M38: =VLOOKUP($K38,Emp!$A$2:$E$347,3,0) -> THRISSUR | N38: =VLOOKUP($K38,Emp!$A$2:$E$347,4,0) -> ARENA | O38: 46091 | P38: 46092 | S38: DISBURSED | T38: MSSF DISBURSED | U38: =VLOOKUP($K38,Emp!$A$2:$E$347,5,0) -> SINTO | Y38: {=INDEX(RETAIL!$F:$F,MATCH(1,(RETAIL!$B:$B=B38)*(RETAIL!$N:$N=M38),0))} -> 40/VSL/25001433 | Z38: =_xlfn.XLOOKUP(Y38,RETAIL!F:F,RETAIL!G:G) -> 46091 | AA38: MAPPED | AB38: =_xlfn.XLOOKUP(D38,[2]MAR!$F:$F,[2]MAR!$H:$H) -> DISBURSED
A39: 38 | B39: SOB25000232 | C39: 2567479082 | D39: DA1113874 | E39: DA1113874 | F39: RAHUL C H | G39: Wagon R | H39: 668159 | I39: IBL | J39: KUNNAMKULAM | K39: RISHAD K S | L39: =VLOOKUP($K39,Emp!$A$2:$E$347,2,0) -> BHAGIESH | M39: =VLOOKUP($K39,Emp!$A$2:$E$347,3,0) -> CHAVAKKAD | N39: =VLOOKUP($K39,Emp!$A$2:$E$347,4,0) -> ARENA | O39: 46091 | P39: 46092 | Q39: =H39*R39 -> 13363.18 | R39: 0.02 | S39: DISBURSED | T39: MSSF DISBURSED | U39: =VLOOKUP($K39,Emp!$A$2:$E$347,5,0) -> SINTO | Y39: {=INDEX(RETAIL!$F:$F,MATCH(1,(RETAIL!$B:$B=B39)*(RETAIL!$N:$N=M39),0))} -> 28/VSL/25000111 | Z39: =_xlfn.XLOOKUP(Y39,RETAIL!F:F,RETAIL!G:G) -> 46093 | AA39: MAPPED | AB39: =_xlfn.XLOOKUP(D39,[2]MAR!$F:$F,[2]MAR!$H:$H) -> DISBURSED
A40: 39 | B40: SOB25000297 | C40: 2567561397 | D40: NIL | E40: KLGBH26070816361 | F40: MANIKANDAN A R | G40: TOUR V | H40: 619835 | I40: KGB | J40: KATTOOR | K40: JITHIN K ANAND | L40: =VLOOKUP($K40,Emp!$A$2:$E$347,2,0) -> KASI VISWANATH | M40: =VLOOKUP($K40,Emp!$A$2:$E$347,3,0) -> KAIPAMANGALAM | N40: =VLOOKUP($K40,Emp!$A$2:$E$347,4,0) -> ARENA | O40: 46091 | P40: 46092 | Q40: =H40*R40 -> 8057.855 | R40: 0.013 | S40: DISBURSED | T40: NO | U40: =VLOOKUP($K40,Emp!$A$2:$E$347,5,0) -> JINEESH | Y40: {=INDEX(RETAIL!$F:$F,MATCH(1,(RETAIL!$B:$B=B40)*(RETAIL!$N:$N=M40),0))} -> 77/VSL/25000161 | Z40: =_xlfn.XLOOKUP(Y40,RETAIL!F:F,RETAIL!G:G) -> 46093 | AB40: =_xlfn.XLOOKUP(D40,[2]MAR!$F:$F,[2]MAR!$H:$H) -> #N/A
A41: 40 | D41: 169219584 | F41: ARJUN T P | G41: Wagon R | H41: 400000 | I41: HDFC | K41: VINAY T V | L41: =VLOOKUP($K41,Emp!$A$2:$E$347,2,0) -> RATISH K R | M41: =VLOOKUP($K41,Emp!$A$2:$E$347,3,0) -> KADAVANTHRA | N41: =VLOOKUP($K41,Emp!$A$2:$E$347,4,0) -> ARENA | O41: 46092 | S41: LOGIN | T41: MSSF LOGIN | U41: =VLOOKUP($K41,Emp!$A$2:$E$347,5,0) -> SALMAN | Y41: {=INDEX(RETAIL!$F:$F,MATCH(1,(RETAIL!$B:$B=B41)*(RETAIL!$N:$N=M41),0))} -> #N/A | Z41: =_xlfn.XLOOKUP(Y41,RETAIL!F:F,RETAIL!G:G) -> #N/A | AB41: =_xlfn.XLOOKUP(D41,[2]MAR!$F:$F,[2]MAR!$H:$H) -> SANCTIONED
A42: 41 | B42: SOB25000207 | C42: 2567533245 | D42: NIL | E42: WHL000002718520 | F42: SHAJU P C | G42: VICTORIS | H42: 1699700 | I42: BAJAJ | K42: ALFIYA ASHRAF | L42: =VLOOKUP($K42,Emp!$A$2:$E$347,2,0) -> JESTIN UTHUP JOHN | M42: =VLOOKUP($K42,Emp!$A$2:$E$347,3,0) -> PIRAVOM | N42: =VLOOKUP($K42,Emp!$A$2:$E$347,4,0) -> ARENA | O42: 46092 | P42: 46092 | Q42: =H42*R42 -> 42492.5 | R42: 0.025 | S42: DISBURSED | T42: NO | U42: =VLOOKUP($K42,Emp!$A$2:$E$347,5,0) -> AMAL | Y42: {=INDEX(RETAIL!$F:$F,MATCH(1,(RETAIL!$B:$B=B42)*(RETAIL!$N:$N=M42),0))} -> 118/VSL25000100 | Z42: =_xlfn.XLOOKUP(Y42,RETAIL!F:F,RETAIL!G:G) -> 46094 | AB42: =_xlfn.XLOOKUP(D42,[2]MAR!$F:$F,[2]MAR!$H:$H) -> #N/A
A43: 42 | B43: SOB25002364 | C43: 2567544011 | D43: 169116591 | E43: 169116591 | F43: SREELAKSHMI K C | G43: Wagon R | H43: 300000 | I43: HDFC | K43: RAGIL N R | L43: =VLOOKUP($K43,Emp!$A$2:$E$347,2,0) -> VIBIN I B | M43: =VLOOKUP($K43,Emp!$A$2:$E$347,3,0) -> KAIPAMANGALAM | N43: =VLOOKUP($K43,Emp!$A$2:$E$347,4,0) -> STUDIO | O43: 46092 | P43: 46093 | S43: DISBURSED | T43: MSSF DISBURSED | U43: =VLOOKUP($K43,Emp!$A$2:$E$347,5,0) -> JINEESH | Y43: {=INDEX(RETAIL!$F:$F,MATCH(1,(RETAIL!$B:$B=B43)*(RETAIL!$N:$N=M43),0))} -> 40/VSL/25001447 | Z43: =_xlfn.XLOOKUP(Y43,RETAIL!F:F,RETAIL!G:G) -> 46094 | AA43: NAME CHANGE | AB43: =_xlfn.XLOOKUP(D43,[2]MAR!$F:$F,[2]MAR!$H:$H) -> DISBURSED
A44: 43 | B44: SOB25002135 | C44: 2567045600 | D44: KGB_40567_0000154 | E44: KLGBH26069815955 | F44: JAFAR KHAN | G44: TOUR S | H44: 500000 | I44: KGB | J44: ELAMAKKARA | K44: LANEESH A S | L44: =VLOOKUP($K44,Emp!$A$2:$E$347,2,0) -> MANU SASI | M44: =VLOOKUP($K44,Emp!$A$2:$E$347,3,0) -> EDAPPALLY | N44: =VLOOKUP($K44,Emp!$A$2:$E$347,4,0) -> ARENA | O44: 46092 | P44: 46093 | Q44: =H44*R44 -> 6500 | R44: 0.013 | S44: DISBURSED | T44: MSSF LOGIN | U44: =VLOOKUP($K44,Emp!$A$2:$E$347,5,0) -> SIVAPRASAD | Y44: {=INDEX(RETAIL!$F:$F,MATCH(1,(RETAIL!$B:$B=B44)*(RETAIL!$N:$N=M44),0))} -> 40/VSL/25001435 | Z44: =_xlfn.XLOOKUP(Y44,RETAIL!F:F,RETAIL!G:G) -> 46092 | AB44: =_xlfn.XLOOKUP(D44,[2]MAR!$F:$F,[2]MAR!$H:$H) -> APPLIED
A45: 44 | D45: IAL-0000534678-A1 | F45: VANI VISWANATH | G45: SWIFT | H45: 400000 | I45: AXIS | K45: AKSHAY RENJAN | L45: =VLOOKUP($K45,Emp!$A$2:$E$347,2,0) -> ELDHO A JACOB | M45: =VLOOKUP($K45,Emp!$A$2:$E$347,3,0) -> ANGAMALY | N45: =VLOOKUP($K45,Emp!$A$2:$E$347,4,0) -> ARENA | O45: 46093 | S45: LOGIN | T45: MSSF LOGIN | U45: =VLOOKUP($K45,Emp!$A$2:$E$347,5,0) -> SALMAN | Y45: {=INDEX(RETAIL!$F:$F,MATCH(1,(RETAIL!$B:$B=B45)*(RETAIL!$N:$N=M45),0))} -> #N/A | Z45: =_xlfn.XLOOKUP(Y45,RETAIL!F:F,RETAIL!G:G) -> #N/A | AB45: =_xlfn.XLOOKUP(D45,[2]MAR!$F:$F,[2]MAR!$H:$H) -> SANCTIONED
A46: 45 | B46: SOB25002295 | C46: 2567580598 | D46: KGB_40567_0000146 | E46: KLGBH26071818804 | F46: SHARLET SHAMY VIVERA | G46: TOUR H3 | H46: 550000 | I46: KGB | J46: ELAMAKKARA | K46: MANU JOY | L46: =VLOOKUP($K46,Emp!$A$2:$E$347,2,0) -> MANU SASI | M46: =VLOOKUP($K46,Emp!$A$2:$E$347,3,0) -> EDAPPALLY | N46: =VLOOKUP($K46,Emp!$A$2:$E$347,4,0) -> ARENA | O46: 46093 | P46: 46094 | Q46: =H46*R46 -> 7150 | R46: 0.013 | S46: DISBURSED | T46: MSSF LOGIN | U46: =VLOOKUP($K46,Emp!$A$2:$E$347,5,0) -> SIVAPRASAD | Y46: {=INDEX(RETAIL!$F:$F,MATCH(1,(RETAIL!$B:$B=B46)*(RETAIL!$N:$N=M46),0))} -> 40/VSL/25001455 | Z46: =_xlfn.XLOOKUP(Y46,RETAIL!F:F,RETAIL!G:G) -> 46094 | AB46: =_xlfn.XLOOKUP(D46,[2]MAR!$F:$F,[2]MAR!$H:$H) -> APPLIED
A47: 46 | B47: SOB25002407 | C47: 2567639079 | D47: DILALMS118741362 | E47: BARBV26071946849 | F47: CHITHRA P | G47: BREZZA | H47: 685000 | I47: BOB | K47: ABHILASH P C | L47: =VLOOKUP($K47,Emp!$A$2:$E$347,2,0) -> ABHILASH K P | M47: =VLOOKUP($K47,Emp!$A$2:$E$347,3,0) -> EDAPPALLY | N47: =VLOOKUP($K47,Emp!$A$2:$E$347,4,0) -> ARENA | O47: 46093 | P47: 46094 | S47: DISBURSED | T47: MSSF LOGIN | U47: =VLOOKUP($K47,Emp!$A$2:$E$347,5,0) -> SIVAPRASAD | Y47: {=INDEX(RETAIL!$F:$F,MATCH(1,(RETAIL!$B:$B=B47)*(RETAIL!$N:$N=M47),0))} -> 40/VSL/25001463 | Z47: =_xlfn.XLOOKUP(Y47,RETAIL!F:F,RETAIL!G:G) -> 46097 | AB47: =_xlfn.XLOOKUP(D47,[2]MAR!$F:$F,[2]MAR!$H:$H) -> UNDER PROCESS
A48: 47 | B48: SOB25001818 | C48: 2566498468 | D48: NIL | E48: KLGBH26071818210 | F48: SABIL N S | G48: TOUR S | H48: 732393 | I48: KGB | J48: OLARIKKARA | K48: SUJEESH P G | L48: =VLOOKUP($K48,Emp!$A$2:$E$347,2,0) -> SIVAPRAKASH K S | M48: =VLOOKUP($K48,Emp!$A$2:$E$347,3,0) -> THRISSUR | N48: =VLOOKUP($K48,Emp!$A$2:$E$347,4,0) -> ARENA | O48: 46092 | P48: 46093 | Q48: =H48*R48 -> 9521.109 | R48: 0.013 | S48: DISBURSED | T48: NO | U48: =VLOOKUP($K48,Emp!$A$2:$E$347,5,0) -> SINTO | Y48: {=INDEX(RETAIL!$F:$F,MATCH(1,(RETAIL!$B:$B=B48)*(RETAIL!$N:$N=M48),0))} -> 40/VSL/25001439 | Z48: =_xlfn.XLOOKUP(Y48,RETAIL!F:F,RETAIL!G:G) -> 46093 | AB48: =_xlfn.XLOOKUP(D48,[2]MAR!$F:$F,[2]MAR!$H:$H) -> #N/A
A49: 48 | B49: SOB25002352 | C49: 2567527116 | D49: 19486276 | E49: 17700689 | F49: AKSHAY P P | G49: TOUR H3 | H49: 524800 | I49: CHOLA | K49: JITHIN K ANAND | L49: =VLOOKUP($K49,Emp!$A$2:$E$347,2,0) -> KASI VISWANATH | M49: =VLOOKUP($K49,Emp!$A$2:$E$347,3,0) -> KAIPAMANGALAM | N49: =VLOOKUP($K49,Emp!$A$2:$E$347,4,0) -> ARENA | O49: 46092 | P49: 46093 | S49: DISBURSED | T49: MSSF DISBURSED | U49: =VLOOKUP($K49,Emp!$A$2:$E$347,5,0) -> JINEESH | Y49: {=INDEX(RETAIL!$F:$F,MATCH(1,(RETAIL!$B:$B=B49)*(RETAIL!$N:$N=M49),0))} -> 40/VSL/25001432 | Z49: =_xlfn.XLOOKUP(Y49,RETAIL!F:F,RETAIL!G:G) -> 46091 | AA49: MAPPED | AB49: =_xlfn.XLOOKUP(D49,[2]MAR!$F:$F,[2]MAR!$H:$H) -> DISBURSED
A50: 49 | B50: SOB25000231 | C50: 2567569135 | D50: WHL000002734482 | E50: WHL000002631601 | F50: A M SHAJAHAN | G50: DZIRE | H50: 899700 | I50: BAJAJ | K50: VISHNU RAJU | L50: =VLOOKUP($K50,Emp!$A$2:$E$347,2,0) -> SIJO VARGHESE GEORGE | M50: =VLOOKUP($K50,Emp!$A$2:$E$347,3,0) -> PERUMBAVOOR | N50: =VLOOKUP($K50,Emp!$A$2:$E$347,4,0) -> ARENA | O50: 46092 | P50: 46094 | Q50: =H50*R50 -> 22492.5 | R50: 0.025 | S50: DISBURSED | T50: MSSF LOGIN | U50: =VLOOKUP($K50,Emp!$A$2:$E$347,5,0) -> SALMAN | Y50: {=INDEX(RETAIL!$F:$F,MATCH(1,(RETAIL!$B:$B=B50)*(RETAIL!$N:$N=M50),0))} -> 126/VSL/25000116 | Z50: =_xlfn.XLOOKUP(Y50,RETAIL!F:F,RETAIL!G:G) -> 46097 | AB50: =_xlfn.XLOOKUP(D50,[2]MAR!$F:$F,[2]MAR!$H:$H) -> APPLIED
A51: 50 | B51: SOB25000251 | C51: 2567602958 | D51: 19550552 | E51: 17798703 | F51: MOHAMED GAZZALI | G51: TOUR S | H51: 583000 | I51: CHOLA | K51: VISHNU K R | L51: =VLOOKUP($K51,Emp!$A$2:$E$347,2,0) -> KASI VISWANATH | M51: =VLOOKUP($K51,Emp!$A$2:$E$347,3,0) -> KAIPAMANGALAM | N51: =VLOOKUP($K51,Emp!$A$2:$E$347,4,0) -> ARENA | O51: 46094 | P51: 46094 | Q51: 9051 | R51: =Q51/H51 -> 0.015524871 | S51: DISBURSED | T51: MSSF DISBURSED | U51: =VLOOKUP($K51,Emp!$A$2:$E$347,5,0) -> JINEESH | Y51: {=INDEX(RETAIL!$F:$F,MATCH(1,(RETAIL!$B:$B=B51)*(RETAIL!$N:$N=M51),0))} -> 77/VSL/25000162 | Z51: =_xlfn.XLOOKUP(Y51,RETAIL!F:F,RETAIL!G:G) -> 46095 | AA51: MAPPED | AB51: DISBURSED
A52: 51 | B52: SOB25002167 | C52: 2567136986 | D52: KGB_40699_0000157 | E52: KLGBH26076823636 | F52: MANOJ M N | G52: TOUR H3 | H52: 544000 | I52: KGB | J52: VARAPUZHA | K52: LANEESH A S | L52: =VLOOKUP($K52,Emp!$A$2:$E$347,2,0) -> MANU SASI | M52: =VLOOKUP($K52,Emp!$A$2:$E$347,3,0) -> EDAPPALLY | N52: =VLOOKUP($K52,Emp!$A$2:$E$347,4,0) -> ARENA | O52: 46094 | P52: 46098 | Q52: =H52*R52 -> 7072 | R52: 0.013 | S52: DISBURSED | T52: MSSF LOGIN | U52: =VLOOKUP($K52,Emp!$A$2:$E$347,5,0) -> SIVAPRASAD | Y52: {=INDEX(RETAIL!$F:$F,MATCH(1,(RETAIL!$B:$B=B52)*(RETAIL!$N:$N=M52),0))} -> 40/VSL/25001466 | Z52: =_xlfn.XLOOKUP(Y52,RETAIL!F:F,RETAIL!G:G) -> 46098 | AB52: =_xlfn.XLOOKUP(D52,[2]MAR!$F:$F,[2]MAR!$H:$H) -> APPLIED
A53: 52 | B53: SOB25002311 | C53: 2567447050 | D53: R-07341099-L | E53: LACOC00052127407 | F53: SIYAD T M | G53: Wagon R | H53: 542566 | I53: ICICI | K53: RIYAS | L53: =VLOOKUP($K53,Emp!$A$2:$E$347,2,0) -> SHEMEER A K | M53: =VLOOKUP($K53,Emp!$A$2:$E$347,3,0) -> EDAPPALLY | N53: =VLOOKUP($K53,Emp!$A$2:$E$347,4,0) -> ARENA | O53: 46094 | P53: 46095 | Q53: =H53*R53 -> 8138.49 | R53: 0.015 | S53: DISBURSED | T53: MSSF DISBURSED | U53: =VLOOKUP($K53,Emp!$A$2:$E$347,5,0) -> SIVAPRASAD | Y53: {=INDEX(RETAIL!$F:$F,MATCH(1,(RETAIL!$B:$B=B53)*(RETAIL!$N:$N=M53),0))} -> 40/VSL/25001458 | Z53: =_xlfn.XLOOKUP(Y53,RETAIL!F:F,RETAIL!G:G) -> 46095 | AA53: MAPPED | AB53: =_xlfn.XLOOKUP(D53,[2]MAR!$F:$F,[2]MAR!$H:$H) -> DISBURSED
A54: 53 | B54: SOB25002318 | C54: 2567479499 | D54: KGB_40539_0000160 | E54: KLGBH26065811492 | F54: MAHESH KUMAR P S | G54: TOUR H3 | H54: 633086 | I54: KGB | J54: ANGAMALY | K54: VISHNU T M | L54: =VLOOKUP($K54,Emp!$A$2:$E$347,2,0) -> ELDHO A JACOB | M54: =VLOOKUP($K54,Emp!$A$2:$E$347,3,0) -> ANGAMALY | N54: =VLOOKUP($K54,Emp!$A$2:$E$347,4,0) -> ARENA | O54: 46093 | P54: 46094 | Q54: =H54*R54 -> 8230.118 | R54: 0.013 | S54: DISBURSED | T54: MSSF LOGIN | U54: =VLOOKUP($K54,Emp!$A$2:$E$347,5,0) -> SALMAN | Y54: {=INDEX(RETAIL!$F:$F,MATCH(1,(RETAIL!$B:$B=B54)*(RETAIL!$N:$N=M54),0))} -> 40/VSL/25001422 | Z54: =_xlfn.XLOOKUP(Y54,RETAIL!F:F,RETAIL!G:G) -> 46088 | AB54: =_xlfn.XLOOKUP(D54,[2]MAR!$F:$F,[2]MAR!$H:$H) -> APPLIED
A55: 54 | D55: 260365384305 | F55: MANUEL SIBU | G55: TOUR H3 | H55: 400000 | I55: TATA | K55: CHANCHAL K G | L55: =VLOOKUP($K55,Emp!$A$2:$E$347,2,0) -> REJIM GEORGE | M55: =VLOOKUP($K55,Emp!$A$2:$E$347,3,0) -> FORTKOCHI | N55: =VLOOKUP($K55,Emp!$A$2:$E$347,4,0) -> ARENA | O55: 46094 | S55: LOGIN | T55: MSSF LOGIN | U55: =VLOOKUP($K55,Emp!$A$2:$E$347,5,0) -> SIVAPRASAD | Y55: {=INDEX(RETAIL!$F:$F,MATCH(1,(RETAIL!$B:$B=B55)*(RETAIL!$N:$N=M55),0))} -> #N/A | Z55: =_xlfn.XLOOKUP(Y55,RETAIL!F:F,RETAIL!G:G) -> #N/A | AB55: =_xlfn.XLOOKUP(D55,[2]MAR!$F:$F,[2]MAR!$H:$H) -> #N/A
A56: 55 | B56: SOB25002382 | C56: 2567570592 | D56: NIL | E56: KLGBH26072820319 | F56: VIBIN VARGHESE | G56: TOUR H3 | H56: 639186 | I56: KGB | J56: KURIACHIRA | K56: BINEESH P ANTO | L56: =VLOOKUP($K56,Emp!$A$2:$E$347,2,0) -> SIVAPRAKASH K S | M56: =VLOOKUP($K56,Emp!$A$2:$E$347,3,0) -> THRISSUR | N56: =VLOOKUP($K56,Emp!$A$2:$E$347,4,0) -> ARENA | O56: 46093 | P56: 46094 | Q56: =H56*R56 -> 8309.418 | R56: 0.013 | S56: DISBURSED | T56: NO | U56: =VLOOKUP($K56,Emp!$A$2:$E$347,5,0) -> SINTO | Y56: {=INDEX(RETAIL!$F:$F,MATCH(1,(RETAIL!$B:$B=B56)*(RETAIL!$N:$N=M56),0))} -> 40/VSL/25001456 | Z56: =_xlfn.XLOOKUP(Y56,RETAIL!F:F,RETAIL!G:G) -> 46094 | AB56: =_xlfn.XLOOKUP(D56,[2]MAR!$F:$F,[2]MAR!$H:$H) -> #N/A
A57: 56 | B57: SOB25002424 | C57: 2567692716 | D57: 19558752 | E57: 17810807 | F57: FABEEJA BEEVI K B | G57: Wagon R | H57: 460000 | I57: CHOLA | K57: ARUN DAS | L57: =VLOOKUP($K57,Emp!$A$2:$E$347,2,0) -> KASI VISWANATH | M57: =VLOOKUP($K57,Emp!$A$2:$E$347,3,0) -> KAIPAMANGALAM | N57: =VLOOKUP($K57,Emp!$A$2:$E$347,4,0) -> ARENA | O57: 46093 | P57: 46095 | Q57: 14304 | R57: =Q57/H57 -> 0.031095652 | S57: DISBURSED | T57: MSSF DISBURSED | U57: =VLOOKUP($K57,Emp!$A$2:$E$347,5,0) -> JINEESH | Y57: {=INDEX(RETAIL!$F:$F,MATCH(1,(RETAIL!$B:$B=B57)*(RETAIL!$N:$N=M57),0))} -> 40/VSL/25001476 | Z57: =_xlfn.XLOOKUP(Y57,RETAIL!F:F,RETAIL!G:G) -> 46100 | AA57: NAME CHANGE | AB57: =_xlfn.XLOOKUP(D57,[2]MAR!$F:$F,[2]MAR!$H:$H) -> DISBURSED
A58: 57 | B58: SOB25000228 | C58: 2567522339 | D58: R-07343441-L | E58: LACOC00052142486 | F58: NOUFAL MAJEED | G58: DZIRE | H58: 892566 | I58: ICICI | K58: BIJO JOY | L58: =VLOOKUP($K58,Emp!$A$2:$E$347,2,0) -> SIJO VARGHESE GEORGE | M58: =VLOOKUP($K58,Emp!$A$2:$E$347,3,0) -> PERUMBAVOOR | N58: =VLOOKUP($K58,Emp!$A$2:$E$347,4,0) -> ARENA | O58: 46095 | P58: 46099 | Q58: =H58*R58 -> 17851.32 | R58: 0.02 | S58: DISBURSED | T58: MSSF DISBURSED | U58: =VLOOKUP($K58,Emp!$A$2:$E$347,5,0) -> SALMAN | Y58: {=INDEX(RETAIL!$F:$F,MATCH(1,(RETAIL!$B:$B=B58)*(RETAIL!$N:$N=M58),0))} -> 126/VSL/25000117 | Z58: =_xlfn.XLOOKUP(Y58,RETAIL!F:F,RETAIL!G:G) -> 46099 | AA58: MAPPED | AB58: =_xlfn.XLOOKUP(D58,[2]MAR!$F:$F,[2]MAR!$H:$H) -> DISBURSED
A59: 58 | B59: SOB25002354 | C59: 2567530237 | D59: NIL | E59: WHL000002595948 | F59: BIBIN BABY | G59: Wagon R | H59: 404700 | I59: BAJAJ | K59: ELSON JACOB | L59: =VLOOKUP($K59,Emp!$A$2:$E$347,2,0) -> ANAND K V | M59: =VLOOKUP($K59,Emp!$A$2:$E$347,3,0) -> KOLENCHERY | N59: =VLOOKUP($K59,Emp!$A$2:$E$347,4,0) -> ARENA | O59: 46095 | P59: 46097 | Q59: =H59*R59 -> 10117.5 | R59: 0.025 | S59: DISBURSED | T59: NO | U59: =VLOOKUP($K59,Emp!$A$2:$E$347,5,0) -> AMAL | Y59: {=INDEX(RETAIL!$F:$F,MATCH(1,(RETAIL!$B:$B=B59)*(RETAIL!$N:$N=M59),0))} -> 40/VSL/25001453 | Z59: =_xlfn.XLOOKUP(Y59,RETAIL!F:F,RETAIL!G:G) -> 46094 | AB59: =_xlfn.XLOOKUP(D59,[2]MAR!$F:$F,[2]MAR!$H:$H) -> #N/A
A60: 59 | B60: SOB25000355 | C60: 2567474135 | D60: EQ1329260075 | E60: V132900058 | F60: VIJAYAN T S | G60: Wagon R | H60: 100000 | I60: SFL | K60: SATHEESH A V | L60: =VLOOKUP($K60,Emp!$A$2:$E$347,2,0) -> ARUN BABU | M60: =VLOOKUP($K60,Emp!$A$2:$E$347,3,0) -> KOOTHATTUKULAM | N60: =VLOOKUP($K60,Emp!$A$2:$E$347,4,0) -> ARENA | O60: 46095 | P60: 46097 | Q60: 1000 | R60: =Q60/H60 -> 0.01 | S60: DISBURSED | T60: MSSF LOGIN | U60: =VLOOKUP($K60,Emp!$A$2:$E$347,5,0) -> AMAL | Y60: {=INDEX(RETAIL!$F:$F,MATCH(1,(RETAIL!$B:$B=B60)*(RETAIL!$N:$N=M60),0))} -> 88/VSL/25000180 | Z60: =_xlfn.XLOOKUP(Y60,RETAIL!F:F,RETAIL!G:G) -> 46095 | AB60: =_xlfn.XLOOKUP(D60,[2]MAR!$F:$F,[2]MAR!$H:$H) -> CANCELLED
A61: 60 | B61: SOB25000230 | C61: 2567431225 | D61: NIL | E61: WHL000002712280 | F61: ABDUL NASEER | G61: Wagon R | H61: 544700 | I61: BAJAJ | K61: RISHAD K S | L61: =VLOOKUP($K61,Emp!$A$2:$E$347,2,0) -> BHAGIESH | M61: =VLOOKUP($K61,Emp!$A$2:$E$347,3,0) -> CHAVAKKAD | N61: =VLOOKUP($K61,Emp!$A$2:$E$347,4,0) -> ARENA | O61: 46093 | P61: 46097 | Q61: =H61*R61 -> 13617.5 | R61: 0.025 | S61: DISBURSED | T61: NO | U61: =VLOOKUP($K61,Emp!$A$2:$E$347,5,0) -> SINTO | Y61: {=INDEX(RETAIL!$F:$F,MATCH(1,(RETAIL!$B:$B=B61)*(RETAIL!$N:$N=M61),0))} -> 28/VSL/25000112 | Z61: =_xlfn.XLOOKUP(Y61,RETAIL!F:F,RETAIL!G:G) -> 46095 | AB61: =_xlfn.XLOOKUP(D61,[2]MAR!$F:$F,[2]MAR!$H:$H) -> #N/A
A62: 61 | B62: SOB25001962 | C62: 2566806016 | D62: M0034300 | E62: CNRBR52026031980624470 | F62: LIVIA THOMAS | G62: Wagon R | H62: 700000 | I62: CANARA | J62: KALAMASSERY | K62: LANEESH A S | L62: =VLOOKUP($K62,Emp!$A$2:$E$347,2,0) -> MANU SASI | M62: =VLOOKUP($K62,Emp!$A$2:$E$347,3,0) -> EDAPPALLY | N62: =VLOOKUP($K62,Emp!$A$2:$E$347,4,0) -> ARENA | O62: 46097 | P62: 46100 | Q62: =H62*R62 -> 9100 | R62: 0.013 | S62: DISBURSED | T62: MSSF DISBURSED | U62: =VLOOKUP($K62,Emp!$A$2:$E$347,5,0) -> SIVAPRASAD | Y62: {=INDEX(RETAIL!$F:$F,MATCH(1,(RETAIL!$B:$B=B62)*(RETAIL!$N:$N=M62),0))} -> 40/VSL/25001484 | Z62: =_xlfn.XLOOKUP(Y62,RETAIL!F:F,RETAIL!G:G) -> 46102 | AA62: MAPPED | AB62: =_xlfn.XLOOKUP(D62,[2]MAR!$F:$F,[2]MAR!$H:$H) -> DISBURSED
A63: 62 | B63: SOB25002304 | C63: 2567441049 | D63: PV04020366 | E63: CF26740840 | F63: SALY SAJAN | G63: EECO | H63: 462000 | I63: KOTAK | K63: SREENATH R PRABHU | L63: =VLOOKUP($K63,Emp!$A$2:$E$347,2,0) -> NOUFAL T A | M63: =VLOOKUP($K63,Emp!$A$2:$E$347,3,0) -> EDAPPALLY | N63: =VLOOKUP($K63,Emp!$A$2:$E$347,4,0) -> ARENA | O63: 46097 | P63: 46098 | S63: DISBURSED | T63: MSSF DISBURSED | U63: =VLOOKUP($K63,Emp!$A$2:$E$347,5,0) -> SIVAPRASAD | Y63: {=INDEX(RETAIL!$F:$F,MATCH(1,(RETAIL!$B:$B=B63)*(RETAIL!$N:$N=M63),0))} -> 40/VSL/25001462 | Z63: =_xlfn.XLOOKUP(Y63,RETAIL!F:F,RETAIL!G:G) -> 46097 | AA63: NAME CHANGE | AB63: =_xlfn.XLOOKUP(D63,[2]MAR!$F:$F,[2]MAR!$H:$H) -> DISBURSED
A64: 63 | B64: SOB25002145 | C64: 2567067945 | D64: 169317863 | E64: 169488265 | F64: P S AFRA SHAMEER | G64: Wagon R | H64: 502536 | I64: HDFC | K64: AMAL RAJ ANTHONY | L64: =VLOOKUP($K64,Emp!$A$2:$E$347,2,0) -> RATISH K R | M64: =VLOOKUP($K64,Emp!$A$2:$E$347,3,0) -> KADAVANTHRA | N64: =VLOOKUP($K64,Emp!$A$2:$E$347,4,0) -> ARENA | O64: 46097 | P64: 46109 | S64: DISBURSED | T64: MSSF LOGIN | U64: =VLOOKUP($K64,Emp!$A$2:$E$347,5,0) -> SALMAN | Y64: {=INDEX(RETAIL!$F:$F,MATCH(1,(RETAIL!$B:$B=B64)*(RETAIL!$N:$N=M64),0))} -> 40/VSL/25001515 | Z64: =_xlfn.XLOOKUP(Y64,RETAIL!F:F,RETAIL!G:G) -> 46109 | AB64: =_xlfn.XLOOKUP(D64,[2]MAR!$F:$F,[2]MAR!$H:$H) -> CANCELLED
A65: 64 | B65: SOB25000102 | C65: 2566474051 | D65: DILALMS118771222 | E65: BARBW26077954999 | F65: JOSE M V | G65: ALTO K10 | H65: 200000 | I65: BOB | J65: ANGAMALY | K65: AKSHAY RENJAN | L65: =VLOOKUP($K65,Emp!$A$2:$E$347,2,0) -> ELDHO A JACOB | M65: =VLOOKUP($K65,Emp!$A$2:$E$347,3,0) -> ANGAMALY | N65: =VLOOKUP($K65,Emp!$A$2:$E$347,4,0) -> ARENA | O65: 46097 | P65: 46099 | S65: DISBURSED | T65: MSSF LOGIN | U65: =VLOOKUP($K65,Emp!$A$2:$E$347,5,0) -> SALMAN | Y65: {=INDEX(RETAIL!$F:$F,MATCH(1,(RETAIL!$B:$B=B65)*(RETAIL!$N:$N=M65),0))} -> 8/VSL/25000059 | Z65: =_xlfn.XLOOKUP(Y65,RETAIL!F:F,RETAIL!G:G) -> 46105 | AB65: =_xlfn.XLOOKUP(D65,[2]MAR!$F:$F,[2]MAR!$H:$H) -> UNDER PROCESS
A66: 65 | D66: 260365370411 | E66: APPL17015847 | F66: VISHNU K B | G66: TOUR H3 | H66: 548350 | I66: TATA | K66: ADWAITH | L66: =VLOOKUP($K66,Emp!$A$2:$E$347,2,0) -> VIBIN I B | M66: =VLOOKUP($K66,Emp!$A$2:$E$347,3,0) -> KAIPAMANGALAM | N66: =VLOOKUP($K66,Emp!$A$2:$E$347,4,0) -> ARENA | O66: 46093 | P66: 46098 | S66: DISBURSED | T66: MSSF DISBURSED | U66: =VLOOKUP($K66,Emp!$A$2:$E$347,5,0) -> JINEESH | Y66: {=INDEX(RETAIL!$F:$F,MATCH(1,(RETAIL!$B:$B=B66)*(RETAIL!$N:$N=M66),0))} -> #N/A | Z66: =_xlfn.XLOOKUP(Y66,RETAIL!F:F,RETAIL!G:G) -> #N/A | AB66: =_xlfn.XLOOKUP(D66,[2]MAR!$F:$F,[2]MAR!$H:$H) -> DISBURSED
A67: 66 | B67: SOB25000195 | C67: 2566867952 | D67: DILALMS118771756 | E67: BARBX26077763758 | F67: DINESH R | G67: Wagon R | H67: 200000 | I67: BOB | J67: A M ROAD | K67: NYGIL GEORGE | L67: =VLOOKUP($K67,Emp!$A$2:$E$347,2,0) -> SIJO VARGHESE GEORGE | M67: =VLOOKUP($K67,Emp!$A$2:$E$347,3,0) -> PERUMBAVOOR | N67: =VLOOKUP($K67,Emp!$A$2:$E$347,4,0) -> ARENA | O67: 46093 | P67: 46098 | S67: DISBURSED | T67: MSSF DISBURSED | U67: =VLOOKUP($K67,Emp!$A$2:$E$347,5,0) -> SALMAN | Y67: {=INDEX(RETAIL!$F:$F,MATCH(1,(RETAIL!$B:$B=B67)*(RETAIL!$N:$N=M67),0))} -> 126/VSL/25000115 | Z67: =_xlfn.XLOOKUP(Y67,RETAIL!F:F,RETAIL!G:G) -> 46097 | AB67: =_xlfn.XLOOKUP(D67,[2]MAR!$F:$F,[2]MAR!$H:$H) -> SANCTIONED
A68: 67 | D68: 260365484305 | F68: KIRAN | G68: TOUR S | H68: 400000 | I68: TATA | K68: JAYESH | L68: =VLOOKUP($K68,Emp!$A$2:$E$347,2,0) -> SHEMEER A K | M68: =VLOOKUP($K68,Emp!$A$2:$E$347,3,0) -> EDAPPALLY | N68: =VLOOKUP($K68,Emp!$A$2:$E$347,4,0) -> ARENA | O68: 46098 | S68: LOGIN | T68: MSSF LOGIN | U68: =VLOOKUP($K68,Emp!$A$2:$E$347,5,0) -> SIVAPRASAD | Y68: {=INDEX(RETAIL!$F:$F,MATCH(1,(RETAIL!$B:$B=B68)*(RETAIL!$N:$N=M68),0))} -> #N/A | Z68: =_xlfn.XLOOKUP(Y68,RETAIL!F:F,RETAIL!G:G) -> #N/A | AB68: =_xlfn.XLOOKUP(D68,[2]MAR!$F:$F,[2]MAR!$H:$H) -> #N/A
A69: 68 | B69: SOB25000233 | C69: 2567550041 | D69: NIL | E69: NIL | F69: HASNA BASHEER | G69: EECO | H69: 554300 | I69: IBL | J69: ALUVA | K69: BIJO JOY | L69: =VLOOKUP($K69,Emp!$A$2:$E$347,2,0) -> SIJO VARGHESE GEORGE | M69: =VLOOKUP($K69,Emp!$A$2:$E$347,3,0) -> PERUMBAVOOR | N69: =VLOOKUP($K69,Emp!$A$2:$E$347,4,0) -> ARENA | O69: 46097 | P69: 46098 | Q69: 3000 | R69: 0.005 | S69: DISBURSED | T69: NO | U69: =VLOOKUP($K69,Emp!$A$2:$E$347,5,0) -> SALMAN | Y69: {=INDEX(RETAIL!$F:$F,MATCH(1,(RETAIL!$B:$B=B69)*(RETAIL!$N:$N=M69),0))} -> 126/VSL/25000118 | Z69: =_xlfn.XLOOKUP(Y69,RETAIL!F:F,RETAIL!G:G) -> 46100 | AB69: =_xlfn.XLOOKUP(D69,[2]MAR!$F:$F,[2]MAR!$H:$H) -> #N/A
A70: 69 | B70: SOB25002335 | C70: 2567485885 | D70: 167683677 | E70: 1002026031700089 | F70: SREEVIDYA S | G70: TOUR M | H70: 939800 | I70: MAHINDRA | K70: MANOJ C S | L70: =VLOOKUP($K70,Emp!$A$2:$E$347,2,0) -> ABHILASH K P | M70: =VLOOKUP($K70,Emp!$A$2:$E$347,3,0) -> EDAPPALLY | N70: =VLOOKUP($K70,Emp!$A$2:$E$347,4,0) -> ARENA | O70: 46098 | P70: 46098 | S70: DISBURSED | T70: MSSF DISBURSED | U70: =VLOOKUP($K70,Emp!$A$2:$E$347,5,0) -> SIVAPRASAD | Y70: {=INDEX(RETAIL!$F:$F,MATCH(1,(RETAIL!$B:$B=B70)*(RETAIL!$N:$N=M70),0))} -> 40/VSL/25001465 | Z70: =_xlfn.XLOOKUP(Y70,RETAIL!F:F,RETAIL!G:G) -> 46098 | AA70: MAPPED | AB70: =_xlfn.XLOOKUP(D70,[2]MAR!$F:$F,[2]MAR!$H:$H) -> DISBURSED
A71: 70 | B71: SOB25000125 | C71: 2567248837 | D71: 169362248 | E71: 169362248 | F71: BEENA VISWANATHAN | G71: SWIFT | H71: 605536 | I71: HDFC | K71: AKSHAY RENJAN | L71: =VLOOKUP($K71,Emp!$A$2:$E$347,2,0) -> ELDHO A JACOB | M71: =VLOOKUP($K71,Emp!$A$2:$E$347,3,0) -> ANGAMALY | N71: =VLOOKUP($K71,Emp!$A$2:$E$347,4,0) -> ARENA | O71: 46098 | P71: 46102 | S71: DISBURSED | T71: MSSF DISBURSED | U71: =VLOOKUP($K71,Emp!$A$2:$E$347,5,0) -> SALMAN | Y71: {=INDEX(RETAIL!$F:$F,MATCH(1,(RETAIL!$B:$B=B71)*(RETAIL!$N:$N=M71),0))} -> 8/VSL/25000058 | Z71: =_xlfn.XLOOKUP(Y71,RETAIL!F:F,RETAIL!G:G) -> 46102 | AA71: NAME CHANGE | AB71: =_xlfn.XLOOKUP(D71,[2]MAR!$F:$F,[2]MAR!$H:$H) -> DISBURSED
A72: 71 | B72: SOB25000318 | C72: 2566736333 | D72: EQ1264260848 | E72: V126400202 | F72: MISIRI P A | G72: EECO | H72: 500000 | I72: SFL | K72: ANVAR SADATH | L72: =VLOOKUP($K72,Emp!$A$2:$E$347,2,0) -> RIJITH | M72: =VLOOKUP($K72,Emp!$A$2:$E$347,3,0) -> STUDIO KDLR | N72: =VLOOKUP($K72,Emp!$A$2:$E$347,4,0) -> STUDIO | O72: 46097 | P72: 46098 | Q72: 10000 | R72: =Q72/H72 -> 0.02 | S72: DISBURSED | T72: MSSF DISBURSED | U72: =VLOOKUP($K72,Emp!$A$2:$E$347,5,0) -> JINEESH | Y72: {=INDEX(RETAIL!$F:$F,MATCH(1,(RETAIL!$B:$B=B72)*(RETAIL!$N:$N=M72),0))} -> 72/VSL/25000155 | Z72: =_xlfn.XLOOKUP(Y72,RETAIL!F:F,RETAIL!G:G) -> 46097 | AA72: MAPPED | AB72: DISBURSED
A73: 72 | B73: SOB25002241 | C73: 2567286964 | D73: 169073366 | E73: 1002026031900328 | F73: AJMAL MOHAMMED | G73: TOUR H3 | H73: 501710 | I73: MAHINDRA | K73: SALAS JUDE | L73: =VLOOKUP($K73,Emp!$A$2:$E$347,2,0) -> NOUFAL T A | M73: =VLOOKUP($K73,Emp!$A$2:$E$347,3,0) -> EDAPPALLY | N73: =VLOOKUP($K73,Emp!$A$2:$E$347,4,0) -> ARENA | O73: 46098 | P73: 46100 | S73: DISBURSED | T73: MSSF DISBURSED | U73: =VLOOKUP($K73,Emp!$A$2:$E$347,5,0) -> SIVAPRASAD | Y73: {=INDEX(RETAIL!$F:$F,MATCH(1,(RETAIL!$B:$B=B73)*(RETAIL!$N:$N=M73),0))} -> 40/VSL/25001479 | Z73: =_xlfn.XLOOKUP(Y73,RETAIL!F:F,RETAIL!G:G) -> 46100 | AA73: MAPPED | AB73: =_xlfn.XLOOKUP(D73,[2]MAR!$F:$F,[2]MAR!$H:$H) -> DISBURSED
A74: 73 | B74: SOB25002413 | C74: 2567669378 | D74: 391750998296 | E74: 168422225 | F74: MELBY MICHEAL | G74: ERTIGA | H74: 593537 | I74: HDFC | K74: ELSON JACOB | L74: =VLOOKUP($K74,Emp!$A$2:$E$347,2,0) -> ANAND K V | M74: =VLOOKUP($K74,Emp!$A$2:$E$347,3,0) -> KOLENCHERY | N74: =VLOOKUP($K74,Emp!$A$2:$E$347,4,0) -> ARENA | O74: 46098 | P74: 46099 | S74: DISBURSED | T74: MSSF DISBURSED | U74: =VLOOKUP($K74,Emp!$A$2:$E$347,5,0) -> AMAL | Y74: {=INDEX(RETAIL!$F:$F,MATCH(1,(RETAIL!$B:$B=B74)*(RETAIL!$N:$N=M74),0))} -> 40/VSL/25001472 | Z74: =_xlfn.XLOOKUP(Y74,RETAIL!F:F,RETAIL!G:G) -> 46099 | AB74: SANCTIONED
A75: 74 | B75: SOB25002438 | C75: 2567770721 | D75: R-700215730-L | E75: LACOC00052138680 | F75: MANOJ P C | G75: EECO | H75: 603246 | I75: ICICI | K75: LIPIN P PAUL | L75: =VLOOKUP($K75,Emp!$A$2:$E$347,2,0) -> JESTIN UTHUP JOHN | M75: =VLOOKUP($K75,Emp!$A$2:$E$347,3,0) -> PIRAVOM | N75: =VLOOKUP($K75,Emp!$A$2:$E$347,4,0) -> ARENA | O75: 46098 | P75: 46099 | S75: DISBURSED | T75: MSSF LOGIN | U75: =VLOOKUP($K75,Emp!$A$2:$E$347,5,0) -> AMAL | Y75: {=INDEX(RETAIL!$F:$F,MATCH(1,(RETAIL!$B:$B=B75)*(RETAIL!$N:$N=M75),0))} -> 40/VSL/25001497 | Z75: =_xlfn.XLOOKUP(Y75,RETAIL!F:F,RETAIL!G:G) -> 46105 | AB75: =_xlfn.XLOOKUP(D75,[2]MAR!$F:$F,[2]MAR!$H:$H) -> #N/A
A76: 75 | B76: SOB25000359 | C76: 2567182039 | D76: 19591986 | E76: 17862272 | F76: GOKUL THILAKAN K T | G76: TOUR H3 | H76: 518232 | I76: CHOLA | K76: ARUN DAS | L76: =VLOOKUP($K76,Emp!$A$2:$E$347,2,0) -> KASI VISWANATH | M76: =VLOOKUP($K76,Emp!$A$2:$E$347,3,0) -> KAIPAMANGALAM | N76: =VLOOKUP($K76,Emp!$A$2:$E$347,4,0) -> ARENA | O76: 46098 | P76: 46099 | S76: DISBURSED | T76: MSSF DISBURSED | U76: =VLOOKUP($K76,Emp!$A$2:$E$347,5,0) -> JINEESH | Y76: {=INDEX(RETAIL!$F:$F,MATCH(1,(RETAIL!$B:$B=B76)*(RETAIL!$N:$N=M76),0))} -> 77/VSL/25000163 | Z76: =_xlfn.XLOOKUP(Y76,RETAIL!F:F,RETAIL!G:G) -> 46104 | AA76: NAME CHANGE | AB76: =_xlfn.XLOOKUP(D76,[2]MAR!$F:$F,[2]MAR!$H:$H) -> DISBURSED
A77: 76 | B77: SOB25002128 | C77: 2567027980 | D77: KGB_40551_0000172 | E77: KLGBH26076824283 | F77: DINURAJ D R | G77: TOUR H3 | H77: 540000 | I77: KGB | J77: TRIPUNITHURA | K77: RATHEESH K B | L77: =VLOOKUP($K77,Emp!$A$2:$E$347,2,0) -> PRANOOB V NAIR | M77: =VLOOKUP($K77,Emp!$A$2:$E$347,3,0) -> TRIPPUNITHURA | N77: =VLOOKUP($K77,Emp!$A$2:$E$347,4,0) -> ARENA | O77: 46098 | P77: 46099 | Q77: =H77*R77 -> 7020 | R77: 0.013 | S77: DISBURSED | T77: MSSF LOGIN | U77: =VLOOKUP($K77,Emp!$A$2:$E$347,5,0) -> SIVAPRASAD | Y77: {=INDEX(RETAIL!$F:$F,MATCH(1,(RETAIL!$B:$B=B77)*(RETAIL!$N:$N=M77),0))} -> 40/VSL/25001467 | Z77: =_xlfn.XLOOKUP(Y77,RETAIL!F:F,RETAIL!G:G) -> 46099 | AB77: =_xlfn.XLOOKUP(D77,[2]MAR!$F:$F,[2]MAR!$H:$H) -> APPLIED
A78: 77 | B78: SOB25002281 | C78: 2567368230 | D78: DILALMS118773348 | E78: BARBT26075276726 | F78: SMIJO JOSE | G78: VICTORIS | H78: 1125000 | I78: BOB | J78: VYTTILA | K78: ALBIN MARTIN | L78: =VLOOKUP($K78,Emp!$A$2:$E$347,2,0) -> RATISH K R | M78: =VLOOKUP($K78,Emp!$A$2:$E$347,3,0) -> KADAVANTHRA | N78: =VLOOKUP($K78,Emp!$A$2:$E$347,4,0) -> ARENA | O78: 46099 | P78: 46099 | S78: DISBURSED | T78: MSSF DISBURSED | U78: =VLOOKUP($K78,Emp!$A$2:$E$347,5,0) -> SALMAN | Y78: {=INDEX(RETAIL!$F:$F,MATCH(1,(RETAIL!$B:$B=B78)*(RETAIL!$N:$N=M78),0))} -> 40/VSL/25001464 | Z78: =_xlfn.XLOOKUP(Y78,RETAIL!F:F,RETAIL!G:G) -> 46098 | AA78: MAPPED | AB78: =_xlfn.XLOOKUP(D78,[2]MAR!$F:$F,[2]MAR!$H:$H) -> DISBURSED
A79: 78 | B79: SOB25002246 | C79: 2567314828 | D79: DA1117395 | E79: DA1117395 | F79: RATHEESH KUMAR M | G79: ALTO K10 | H79: 250000 | I79: IBL | J79: PALAKKAD | K79: PRAMOD K | L79: =VLOOKUP($K79,Emp!$A$2:$E$347,2,0) -> SIVAPRAKASH K S | M79: =VLOOKUP($K79,Emp!$A$2:$E$347,3,0) -> THRISSUR | N79: =VLOOKUP($K79,Emp!$A$2:$E$347,4,0) -> ARENA | O79: 46099 | P79: 46100 | Q79: 7000 | R79: =Q79/H79 -> 0.028 | S79: DISBURSED | T79: MSSF DISBURSED | U79: =VLOOKUP($K79,Emp!$A$2:$E$347,5,0) -> SINTO | Y79: {=INDEX(RETAIL!$F:$F,MATCH(1,(RETAIL!$B:$B=B79)*(RETAIL!$N:$N=M79),0))} -> 40/VSL/25001470 | Z79: =_xlfn.XLOOKUP(Y79,RETAIL!F:F,RETAIL!G:G) -> 46099 | AA79: NAME CHANGE | AB79: =_xlfn.XLOOKUP(D79,[2]MAR!$F:$F,[2]MAR!$H:$H) -> DISBURSED
A80: 79 | B80: SOB25000242 | C80: 2567586386 | D80: 169274557 | E80: 169274557 | F80: NOUFAL VELUTHAPARAMBIL | G80: ERTIGA | H80: 1251536 | I80: HDFC | K80: RISHAD K S | L80: =VLOOKUP($K80,Emp!$A$2:$E$347,2,0) -> BHAGIESH | M80: =VLOOKUP($K80,Emp!$A$2:$E$347,3,0) -> CHAVAKKAD | N80: =VLOOKUP($K80,Emp!$A$2:$E$347,4,0) -> ARENA | O80: 46099 | P80: 46100 | S80: DISBURSED | T80: MSSF DISBURSED | U80: =VLOOKUP($K80,Emp!$A$2:$E$347,5,0) -> SINTO | Y80: {=INDEX(RETAIL!$F:$F,MATCH(1,(RETAIL!$B:$B=B80)*(RETAIL!$N:$N=M80),0))} -> 28/VSL/25000114 | Z80: =_xlfn.XLOOKUP(Y80,RETAIL!F:F,RETAIL!G:G) -> 46100 | AA80: MAPPED | AB80: DISBURSED
A81: 80 | B81: SOB25002391 | C81: 2567583828 | D81: PV04011915 | E81: CF26753016 | F81: FAIZAL C M | G81: TOUR H3 | H81: 273000 | I81: KOTAK | K81: VINAY T V | L81: =VLOOKUP($K81,Emp!$A$2:$E$347,2,0) -> RATISH K R | M81: =VLOOKUP($K81,Emp!$A$2:$E$347,3,0) -> KADAVANTHRA | N81: =VLOOKUP($K81,Emp!$A$2:$E$347,4,0) -> ARENA | O81: 46100 | P81: 46100 | S81: DISBURSED | T81: MSSF DISBURSED | U81: =VLOOKUP($K81,Emp!$A$2:$E$347,5,0) -> SALMAN | Y81: {=INDEX(RETAIL!$F:$F,MATCH(1,(RETAIL!$B:$B=B81)*(RETAIL!$N:$N=M81),0))} -> 40/VSL/25001468 | Z81: =_xlfn.XLOOKUP(Y81,RETAIL!F:F,RETAIL!G:G) -> 46099 | AA81: MAPPED | AB81: =_xlfn.XLOOKUP(D81,[2]MAR!$F:$F,[2]MAR!$H:$H) -> DISBURSED
A82: 81 | B82: SOB25002436 | C82: 2567762057 | D82: DILALMS118861691 | E82: BARBX26077935241 | F82: ANIL KUMAR V | G82: VICTORIS | H82: 1200000 | I82: BOB | J82: VAZHAKKALA | K82: ARVIND SANTHOSH | L82: =VLOOKUP($K82,Emp!$A$2:$E$347,2,0) -> SANDEEP P | M82: =VLOOKUP($K82,Emp!$A$2:$E$347,3,0) -> NEXA COCHIN | N82: =VLOOKUP($K82,Emp!$A$2:$E$347,4,0) -> NEXA COCHIN | O82: 46099 | P82: 46100 | S82: DISBURSED | T82: MSSF LOGIN | U82: =VLOOKUP($K82,Emp!$A$2:$E$347,5,0) -> WILSON | Y82: {=INDEX(RETAIL!$F:$F,MATCH(1,(RETAIL!$B:$B=B82)*(RETAIL!$N:$N=M82),0))} -> 40/VSL/25001491 | Z82: =_xlfn.XLOOKUP(Y82,RETAIL!F:F,RETAIL!G:G) -> 46105 | AB82: =_xlfn.XLOOKUP(D82,[2]MAR!$F:$F,[2]MAR!$H:$H) -> APPLIED
A83: 82 | B83: SOB25000347 | C83: 2567412820 | D83: NIL | E83: 169138358 | F83: ANS THOMAS | G83: Wagon R | H83: 358536 | I83: HDFC | K83: IBIN JOSE | L83: =VLOOKUP($K83,Emp!$A$2:$E$347,2,0) -> ARUN BABU | M83: =VLOOKUP($K83,Emp!$A$2:$E$347,3,0) -> KOOTHATTUKULAM | N83: =VLOOKUP($K83,Emp!$A$2:$E$347,4,0) -> ARENA | O83: 46099 | P83: 46100 | Q83: =H83*R83 -> 3585.36 | R83: 0.01 | S83: DISBURSED | T83: NO | U83: =VLOOKUP($K83,Emp!$A$2:$E$347,5,0) -> AMAL | Y83: {=INDEX(RETAIL!$F:$F,MATCH(1,(RETAIL!$B:$B=B83)*(RETAIL!$N:$N=M83),0))} -> 88/VSL/25000181 | Z83: =_xlfn.XLOOKUP(Y83,RETAIL!F:F,RETAIL!G:G) -> 46099 | AB83: =_xlfn.XLOOKUP(D83,[2]MAR!$F:$F,[2]MAR!$H:$H) -> #N/A
A84: 83 | B84: SOB25002431 | C84: 2567700889 | D84: FBL04260000077666 | E84: FBBT260789429532 | F84: SHAIJO THOMAS A J | G84: VICTORIS | H84: 644100 | I84: FBL | J84: ALUVA | K84: ANUKUTTAN K R | L84: =VLOOKUP($K84,Emp!$A$2:$E$347,2,0) -> NOUFAL T A | M84: =VLOOKUP($K84,Emp!$A$2:$E$347,3,0) -> EDAPPALLY | N84: =VLOOKUP($K84,Emp!$A$2:$E$347,4,0) -> ARENA | O84: 46100 | P84: 46100 | S84: DISBURSED | T84: MSSF DISBURSED | U84: =VLOOKUP($K84,Emp!$A$2:$E$347,5,0) -> SIVAPRASAD | Y84: {=INDEX(RETAIL!$F:$F,MATCH(1,(RETAIL!$B:$B=B84)*(RETAIL!$N:$N=M84),0))} -> 40/VSL/25001478 | Z84: =_xlfn.XLOOKUP(Y84,RETAIL!F:F,RETAIL!G:G) -> 46100 | AA84: MAPPED | AB84: =_xlfn.XLOOKUP(D84,[2]MAR!$F:$F,[2]MAR!$H:$H) -> DISBURSED
A85: 84 | B85: SOB25002371 | C85: 2567550025 | D85: KGB_40537_0000185 | E85: KLGBH26078827501 | F85: SUBAIR B H | G85: TOUR H3 | H85: 540000 | I85: KGB | J85: KALOOR | K85: LANEESH A S | L85: =VLOOKUP($K85,Emp!$A$2:$E$347,2,0) -> MANU SASI | M85: =VLOOKUP($K85,Emp!$A$2:$E$347,3,0) -> EDAPPALLY | N85: =VLOOKUP($K85,Emp!$A$2:$E$347,4,0) -> ARENA | O85: 46100 | P85: 46102 | Q85: =H85*R85 -> 7020 | R85: 0.013 | S85: DISBURSED | T85: MSSF LOGIN | U85: =VLOOKUP($K85,Emp!$A$2:$E$347,5,0) -> SIVAPRASAD | Y85: {=INDEX(RETAIL!$F:$F,MATCH(1,(RETAIL!$B:$B=B85)*(RETAIL!$N:$N=M85),0))} -> 40/VSL/25001483 | Z85: =_xlfn.XLOOKUP(Y85,RETAIL!F:F,RETAIL!G:G) -> 46102 | AB85: =_xlfn.XLOOKUP(D85,[2]MAR!$F:$F,[2]MAR!$H:$H) -> #N/A
A86: 85 | B86: SOB25001907 | C86: 2566692451 | D86: 19616283 | E86: 17900609 | F86: ABHAY MANOJ | G86: TOUR H3 | H86: 424000 | I86: CHOLA | K86: AMAL RAJ ANTHONY | L86: =VLOOKUP($K86,Emp!$A$2:$E$347,2,0) -> RATISH K R | M86: =VLOOKUP($K86,Emp!$A$2:$E$347,3,0) -> KADAVANTHRA | N86: =VLOOKUP($K86,Emp!$A$2:$E$347,4,0) -> ARENA | O86: 46100 | P86: 46102 | Q86: 8480 | R86: =Q86/H86 -> 0.02 | S86: DISBURSED | T86: MSSF DISBURSED | U86: =VLOOKUP($K86,Emp!$A$2:$E$347,5,0) -> SALMAN | Y86: {=INDEX(RETAIL!$F:$F,MATCH(1,(RETAIL!$B:$B=B86)*(RETAIL!$N:$N=M86),0))} -> 40/VSL/25001498 | Z86: =_xlfn.XLOOKUP(Y86,RETAIL!F:F,RETAIL!G:G) -> 46106 | AA86: MAPPED | AB86: =_xlfn.XLOOKUP(D86,[2]MAR!$F:$F,[2]MAR!$H:$H) -> DISBURSED
A87: 86 | B87: SOB25000398 | C87: 2567545752 | D87: 260365323993 | E87: APPL17007301 | F87: AKHIL KUMAR | G87: TOUR H3 | H87: 547351 | I87: TATA | K87: JAYAKRISHNAN K V | L87: =VLOOKUP($K87,Emp!$A$2:$E$347,2,0) -> BINOY RAJ | M87: =VLOOKUP($K87,Emp!$A$2:$E$347,3,0) -> KODUNGALLUR | N87: =VLOOKUP($K87,Emp!$A$2:$E$347,4,0) -> ARENA | O87: 46102 | P87: 46102 | S87: DISBURSED | T87: MSSF LOGIN | U87: =VLOOKUP($K87,Emp!$A$2:$E$347,5,0) -> JINEESH | Y87: {=INDEX(RETAIL!$F:$F,MATCH(1,(RETAIL!$B:$B=B87)*(RETAIL!$N:$N=M87),0))} -> 72/VSL/25000156 | Z87: =_xlfn.XLOOKUP(Y87,RETAIL!F:F,RETAIL!G:G) -> 46100 | AB87: =_xlfn.XLOOKUP(D87,[2]MAR!$F:$F,[2]MAR!$H:$H) -> #N/A
A88: 87 | B88: SOB25002427 | C88: 2567692920 | D88: NIL | E88: FDRLR52026031900534263 | F88: TINCY BABU | G88: Wagon R | H88: 449410 | I88: FBL | J88: KOLENCHERRY | K88: AMITH JACOB | L88: =VLOOKUP($K88,Emp!$A$2:$E$347,2,0) -> ANAND K V | M88: =VLOOKUP($K88,Emp!$A$2:$E$347,3,0) -> KOLENCHERY | N88: =VLOOKUP($K88,Emp!$A$2:$E$347,4,0) -> ARENA | O88: 46100 | P88: 46102 | S88: DISBURSED | T88: NO | U88: =VLOOKUP($K88,Emp!$A$2:$E$347,5,0) -> AMAL | Y88: {=INDEX(RETAIL!$F:$F,MATCH(1,(RETAIL!$B:$B=B88)*(RETAIL!$N:$N=M88),0))} -> 40/VSL/25001474 | Z88: =_xlfn.XLOOKUP(Y88,RETAIL!F:F,RETAIL!G:G) -> 46100 | AB88: =_xlfn.XLOOKUP(D88,[2]MAR!$F:$F,[2]MAR!$H:$H) -> #N/A
A89: 88 | B89: SOB25000348 | C89: 2567417374 | D89: NIL | E89: WHL000002711558 | F89: SIBIN JOSE | G89: ALTO K10 | H89: 301700 | I89: BAJAJ | K89: SATHEESH A V | L89: =VLOOKUP($K89,Emp!$A$2:$E$347,2,0) -> ARUN BABU | M89: =VLOOKUP($K89,Emp!$A$2:$E$347,3,0) -> KOOTHATTUKULAM | N89: =VLOOKUP($K89,Emp!$A$2:$E$347,4,0) -> ARENA | O89: 46100 | P89: 46102 | Q89: =H89*R89 -> 7542.5 | R89: 0.025 | S89: DISBURSED | T89: NO | U89: =VLOOKUP($K89,Emp!$A$2:$E$347,5,0) -> AMAL | Y89: {=INDEX(RETAIL!$F:$F,MATCH(1,(RETAIL!$B:$B=B89)*(RETAIL!$N:$N=M89),0))} -> 88/VSL/25000182 | Z89: =_xlfn.XLOOKUP(Y89,RETAIL!F:F,RETAIL!G:G) -> 46100 | AB89: =_xlfn.XLOOKUP(D89,[2]MAR!$F:$F,[2]MAR!$H:$H) -> #N/A
A90: 89 | B90: SOB25002433 | C90: 2567728060 | D90: 19647051 | E90: 17949016 | F90: KIRAN K S | G90: Wagon R | H90: 552000 | I90: CHOLA | K90: SARATH P J | L90: =VLOOKUP($K90,Emp!$A$2:$E$347,2,0) -> SIVAPRAKASH K S | M90: =VLOOKUP($K90,Emp!$A$2:$E$347,3,0) -> THRISSUR | N90: =VLOOKUP($K90,Emp!$A$2:$E$347,4,0) -> ARENA | O90: 46100 | P90: 46102 | S90: DISBURSED | T90: MSSF DISBURSED | U90: =VLOOKUP($K90,Emp!$A$2:$E$347,5,0) -> SINTO | Y90: {=INDEX(RETAIL!$F:$F,MATCH(1,(RETAIL!$B:$B=B90)*(RETAIL!$N:$N=M90),0))} -> 40/VSL/25001487 | Z90: =_xlfn.XLOOKUP(Y90,RETAIL!F:F,RETAIL!G:G) -> 46104 | AA90: MAPPED | AB90: =_xlfn.XLOOKUP(D90,[2]MAR!$F:$F,[2]MAR!$H:$H) -> DISBURSED
A91: 90 | B91: SOB25000393 | C91: 2567463171 | D91: 48132975 | E91: 45024767262 | F91: PRAVEENKUMAR K P | G91: ALTO K10 | H91: 325000 | I91: SBI | J91: CRANGANORE | K91: VIPIN K G | L91: =VLOOKUP($K91,Emp!$A$2:$E$347,2,0) -> BINOY RAJ | M91: =VLOOKUP($K91,Emp!$A$2:$E$347,3,0) -> KODUNGALLUR | N91: =VLOOKUP($K91,Emp!$A$2:$E$347,4,0) -> ARENA | O91: 46100 | P91: 46104 | Q91: =H91*R91 -> 6500 | R91: 0.02 | S91: DISBURSED | T91: MSSF DISBURSED | U91: =VLOOKUP($K91,Emp!$A$2:$E$347,5,0) -> JINEESH | Y91: {=INDEX(RETAIL!$F:$F,MATCH(1,(RETAIL!$B:$B=B91)*(RETAIL!$N:$N=M91),0))} -> 72/VSL/25000158 | Z91: =_xlfn.XLOOKUP(Y91,RETAIL!F:F,RETAIL!G:G) -> 46107 | AA91: MAPPED | AB91: =_xlfn.XLOOKUP(D91,[2]MAR!$F:$F,[2]MAR!$H:$H) -> DISBURSED
A92: 91 | B92: SOB25002257 | C92: 2567330979 | D92: 169108695 | E92: 169108695 | F92: SHEMEER S | G92: EECO | H92: 578536 | I92: HDFC | K92: VISHNU P V | L92: =VLOOKUP($K92,Emp!$A$2:$E$347,2,0) -> GEORGE KUTTAN JOY | M92: =VLOOKUP($K92,Emp!$A$2:$E$347,3,0) -> NEXA COCHIN | N92: =VLOOKUP($K92,Emp!$A$2:$E$347,4,0) -> NEXA COCHIN | O92: 46100 | P92: 46104 | S92: DISBURSED | T92: MSSF DISBURSED | U92: =VLOOKUP($K92,Emp!$A$2:$E$347,5,0) -> WILSON | Y92: {=INDEX(RETAIL!$F:$F,MATCH(1,(RETAIL!$B:$B=B92)*(RETAIL!$N:$N=M92),0))} -> 40/VSL/25001486 | Z92: =_xlfn.XLOOKUP(Y92,RETAIL!F:F,RETAIL!G:G) -> 46104 | AA92: NAME CHANGE | AB92: =_xlfn.XLOOKUP(D92,[2]MAR!$F:$F,[2]MAR!$H:$H) -> DISBURSED
A93: 92 | B93: SOB25002460 | C93: 2567845023 | D93: KGB_40282_0000186 | E93: KLGBH26086837527 | F93: SHAJU V A | G93: TOUR H3 | H93: 548186 | I93: KGB | J93: THRIPRAYAR | K93: JERRIN ROY | L93: =VLOOKUP($K93,Emp!$A$2:$E$347,2,0) -> PRANOOB V NAIR | M93: =VLOOKUP($K93,Emp!$A$2:$E$347,3,0) -> TRIPPUNITHURA | N93: =VLOOKUP($K93,Emp!$A$2:$E$347,4,0) -> ARENA | O93: 46104 | P93: 46108 | Q93: =H93*R93 -> 7126.418 | R93: 0.013 | S93: DISBURSED | T93: MSSF LOGIN | U93: =VLOOKUP($K93,Emp!$A$2:$E$347,5,0) -> SIVAPRASAD | Y93: {=INDEX(RETAIL!$F:$F,MATCH(1,(RETAIL!$B:$B=B93)*(RETAIL!$N:$N=M93),0))} -> 40/VSL/25001528 | Z93: =_xlfn.XLOOKUP(Y93,RETAIL!F:F,RETAIL!G:G) -> 46109 | AB93: =_xlfn.XLOOKUP(D93,[2]MAR!$F:$F,[2]MAR!$H:$H) -> APPLIED
A94: 93 | D94: KGB_40670_0000187 | E94: KLGBH26077825464 | F94: ANEES T A | G94: TOUR M | H94: 1000000 | I94: KGB | J94: CHERANALLUR | K94: AARJI | L94: =VLOOKUP($K94,Emp!$A$2:$E$347,2,0) -> SHEMEER A K | M94: =VLOOKUP($K94,Emp!$A$2:$E$347,3,0) -> EDAPPALLY | N94: =VLOOKUP($K94,Emp!$A$2:$E$347,4,0) -> ARENA | O94: 46104 | P94: 46109 | Q94: =H94*R94 -> 13000 | R94: 0.013 | S94: DISBURSED | T94: MSSF LOGIN | U94: =VLOOKUP($K94,Emp!$A$2:$E$347,5,0) -> SIVAPRASAD | Y94: {=INDEX(RETAIL!$F:$F,MATCH(1,(RETAIL!$B:$B=B94)*(RETAIL!$N:$N=M94),0))} -> #N/A | Z94: =_xlfn.XLOOKUP(Y94,RETAIL!F:F,RETAIL!G:G) -> #N/A | AB94: =_xlfn.XLOOKUP(D94,[2]MAR!$F:$F,[2]MAR!$H:$H) -> APPLIED
A95: 94 | D95: M0034531 | E95: CNRBR52026032781538467 | F95: GEORGE KURIAKOSE | G95: EECO | H95: 537674 | I95: CANARA | J95: ARAKKUNNAM | K95: JERRIN ROY | L95: =VLOOKUP($K95,Emp!$A$2:$E$347,2,0) -> PRANOOB V NAIR | M95: =VLOOKUP($K95,Emp!$A$2:$E$347,3,0) -> TRIPPUNITHURA | N95: =VLOOKUP($K95,Emp!$A$2:$E$347,4,0) -> ARENA | O95: 46104 | P95: 46108 | Q95: =H95*R95 -> 6989.762 | R95: 0.013 | S95: DISBURSED | T95: MSSF LOGIN | U95: =VLOOKUP($K95,Emp!$A$2:$E$347,5,0) -> SIVAPRASAD | Y95: {=INDEX(RETAIL!$F:$F,MATCH(1,(RETAIL!$B:$B=B95)*(RETAIL!$N:$N=M95),0))} -> #N/A | Z95: =_xlfn.XLOOKUP(Y95,RETAIL!F:F,RETAIL!G:G) -> #N/A | AB95: =_xlfn.XLOOKUP(D95,[2]MAR!$F:$F,[2]MAR!$H:$H) -> APPLIED
A96: 95 | B96: SOB25002337 | C96: 2567470471 | D96: DILALMS118821603 | E96: BARBR52026032300952403 | F96: BINOY KURIAKOSE | G96: SWIFT | H96: 450000 | I96: BOB | J96: ERNAKULAM | K96: LANEESH A S | L96: =VLOOKUP($K96,Emp!$A$2:$E$347,2,0) -> MANU SASI | M96: =VLOOKUP($K96,Emp!$A$2:$E$347,3,0) -> EDAPPALLY | N96: =VLOOKUP($K96,Emp!$A$2:$E$347,4,0) -> ARENA | O96: 46100 | P96: 46104 | S96: DISBURSED | T96: MSSF DISBURSED | U96: =VLOOKUP($K96,Emp!$A$2:$E$347,5,0) -> SIVAPRASAD | Y96: {=INDEX(RETAIL!$F:$F,MATCH(1,(RETAIL!$B:$B=B96)*(RETAIL!$N:$N=M96),0))} -> 40/VSL/25001489 | Z96: =_xlfn.XLOOKUP(Y96,RETAIL!F:F,RETAIL!G:G) -> 46104 | AA96: MAPPED | AB96: =_xlfn.XLOOKUP(D96,[2]MAR!$F:$F,[2]MAR!$H:$H) -> DISBURSED
A97: 96 | B97: SOB25000231 | C97: 2567235354 | D97: UBI1773734556954 | E97: UBINR22026032301108023 | F97: ANJALI RAVEENDRAN | G97: ALTO K10 | H97: 450000 | I97: UBI | J97: KUMARAPURAM | K97: ELSON JACOB | L97: =VLOOKUP($K97,Emp!$A$2:$E$347,2,0) -> ANAND K V | M97: =VLOOKUP($K97,Emp!$A$2:$E$347,3,0) -> KOLENCHERY | N97: =VLOOKUP($K97,Emp!$A$2:$E$347,4,0) -> ARENA | O97: 46100 | P97: 46104 | S97: DISBURSED | T97: MSSF DISBURSED | U97: =VLOOKUP($K97,Emp!$A$2:$E$347,5,0) -> AMAL | Y97: {=INDEX(RETAIL!$F:$F,MATCH(1,(RETAIL!$B:$B=B97)*(RETAIL!$N:$N=M97),0))} -> 255/VSL/25000102 | Z97: =_xlfn.XLOOKUP(Y97,RETAIL!F:F,RETAIL!G:G) -> 46102 | AA97: NAME CHANGE | AB97: =_xlfn.XLOOKUP(D97,[2]MAR!$F:$F,[2]MAR!$H:$H) -> DISBURSED
A98: 97 | B98: SOB25002446 | C98: 2567808397 | D98: 260365329613 | E98: APPL17009188 | F98: SANTHOSH BALAN | G98: TOUR H3 | H98: 537330 | I98: TATA | K98: ASWIN P S | L98: =VLOOKUP($K98,Emp!$A$2:$E$347,2,0) -> BHAGIESH | M98: =VLOOKUP($K98,Emp!$A$2:$E$347,3,0) -> CHAVAKKAD | N98: =VLOOKUP($K98,Emp!$A$2:$E$347,4,0) -> ARENA | O98: 46100 | P98: 46105 | S98: DISBURSED | T98: MSSF DISBURSED | U98: =VLOOKUP($K98,Emp!$A$2:$E$347,5,0) -> SINTO | Y98: {=INDEX(RETAIL!$F:$F,MATCH(1,(RETAIL!$B:$B=B98)*(RETAIL!$N:$N=M98),0))} -> 40/VSL/25001507 | Z98: =_xlfn.XLOOKUP(Y98,RETAIL!F:F,RETAIL!G:G) -> 46107 | AA98: NAME CHANGE | AB98: =_xlfn.XLOOKUP(D98,[2]MAR!$F:$F,[2]MAR!$H:$H) -> DISBURSED
A99: 98 | B99: SOB25000204 | C99: 2566911359 | D99: NIL | E99: KLGBR52026031700823709 | F99: SAHU | G99: TOUR V | H99: 682435 | I99: KGB | J99: POOVATHUR | K99: ABHIJITH K P | L99: =VLOOKUP($K99,Emp!$A$2:$E$347,2,0) -> BHAGIESH | M99: =VLOOKUP($K99,Emp!$A$2:$E$347,3,0) -> CHAVAKKAD | N99: =VLOOKUP($K99,Emp!$A$2:$E$347,4,0) -> ARENA | O99: 46100 | P99: 46105 | Q99: =H99*R99 -> 8871.655 | R99: 0.013 | S99: DISBURSED | T99: NO | U99: =VLOOKUP($K99,Emp!$A$2:$E$347,5,0) -> SINTO | Y99: {=INDEX(RETAIL!$F:$F,MATCH(1,(RETAIL!$B:$B=B99)*(RETAIL!$N:$N=M99),0))} -> 28/VSL/25000115 | Z99: =_xlfn.XLOOKUP(Y99,RETAIL!F:F,RETAIL!G:G) -> 46100 | AB99: =_xlfn.XLOOKUP(D99,[2]MAR!$F:$F,[2]MAR!$H:$H) -> #N/A
